Workbook

Sheet 说明
A1: 中国土地契约（匹兹堡大学 Chinese Land Records, 1584–1978）全件辨读统计表
A3: 来源 | B3: Chinese Land Records, 1584-1978, EAL.2011.01, Archives & Special Collections, University of Pittsburgh Library System. https://digital.library.pitt.edu/collection/chinese-land-records
A4: 范围 | B4: 全部 234 件（407 页图像）。每件一行；若一件含多份文书（正契、契尾、验契凭证等），主要字段记主契，其余写在"附带文书"栏。
A5: 方法 | B5: 根据课程资料包中的图像逐页辨读（2026-10-07，由 Claude 分批完成）。人名、地名等文字统一转为简体；看不清的字作 □，存疑的字加 (?)。
A6: 置信度 | B6: 高＝主要字段清楚；中＝部分存疑；低＝大部分难辨或残缺（共 12 件，在总表中以红色标出，「中」为黄色）。
A7: 派生字段 | B7: "文书大类""交易物大类""时期""币种"是在原判基础上归并的分类，便于统计；原判保留在"文书类型（原判）""交易物类别（原判）"栏。
A8: 县 | B8: 按契文辨读，不照搬目录。闽县、侯官县（清代）与闽侯县（1913 年后）、林森县（1944–1949）在地理上大体重叠，统计时未合并。无法判断者记"不详"。
A9: 价格 | B9: "价格数值"只记契面数字，不做币值换算；银两、银元、铜钱、法币、人民币各自独立。找贴、凑断契的价格是加价部分。官方凭证的税额、纸价记在"价格原文"，不计入价格统计。
A10: 与目录不符 | B10: 图书馆目录（"图书馆目录标题""目录日期"）与图像不一致之处记在"与目录不符"栏，常见情况是把典契记成买卖、买卖方向写反、把中人或保人当成买主、年份换算差一年。
A11: 使用限制 | B11: 图像仅限课堂使用，本表不含任何图像；查看原件请点"链接"栏，引用时请注明匹兹堡大学图书馆。辨读结果未经人工校对，正式引用前请核对原图。
A13: 工作表 | B13: 总表：全部 234 件明细，可筛选；统计：按类别、时期、性别、县等计数，以及按币种 × 时期的价格表（公式随总表更新）；人物索引：重复出现的中人、代笔。

Sheet 总表
A1: 箱 | B1: 夹 | C1: 文书大类 | D1: 文书类型（原判） | E1: 时期 | F1: 年号 | G1: 纪年原文 | H1: 公元年 | I1: 立契人 | J1: 立契人性别 | K1: 立契人身份 | L1: 承受人 | M1: 县 | N1: 地点原文 | O1: 交易物大类 | P1: 交易物类别（原判） | Q1: 交易物细节 | R1: 价格原文 | S1: 价格数值 | T1: 币种 | U1: 中人 | V1: 在见／知见／保人 | W1: 代笔 | X1: 官印／税契 | Y1: 回赎／期限条款 | Z1: 附带文书 | AA1: 值得注意 | AB1: 与目录不符 | AC1: 置信度 | AD1: 存疑 | AE1: 页数 | AF1: 图书馆目录标题 | AG1: 目录日期 | AH1: 链接 | AI1: item_id
A2: 1 | B2: 1 | C2: 其他 | D2: 其他（清丈归户单） | E2: 1 明（-1643） | F2: 万历 | G2: 万历十二年十二月 日 | H2: 1584 | I2: 张炳财 | J2: 男 | K2: 表席里叁图贰甲户长；户丁张万殿执业；纳粮佃户'自'，系民田 | M2: 连城县 | N2: 连城县□□表席里叁图，大土名莲花坑，小土名赤岭 | O2: 田 | P2: 田 | Q2: 吕字壹千伍百柒拾捌号田壹坵；四至：东至一千五百七十二号吴世源界，西至一千五百七十四号吴大传界，南至一千六百五十七号吴光裕界，北至一千五百六十八号张族(?)负(?)界；东丈中直贰拾叁号壹尺、西丈一广叁号、南丈二广陆号伍尺、北丈三广捌号；通计壹百肆拾陆(?)步□分，折田□亩肆分陆厘贰毫(?) | V2: 公正余(?)易(?)美；书算吴□祥 | X2: 木刻印刷格式官方单据，未见红印；照上田起科 | AA2: 万历清丈（张居正丈田）后颁发的归户单，印刷版式填写，以千字文'吕'字编号鱼鳞图册号；是本特藏最早一件，且出自闽西连城而非福州。左边沿有一行模糊墨书批注。 | AC2: 中 | AD2: 旧额亩分、今丈数字及通计步数字迹模糊；公正、书算姓名不确定；北至人名'张族负'存疑 | AE2: 1 | AF2: Owner: 張炳財 [ZHANG Bingcai] -- Place: 福建省連城縣 [Fujian Sheng Liancheng Xian] -- Personal | AG2: 1584 | AH2: 查看原件 | AI2: 31735066267786
A3: 1 | B3: 2 | C3: 买卖（卖／卖断） | D3: 卖契 | E3: 2 清前期（1644-1795） | F3: 顺治 | G3: 顺治十六年□月 日 | H3: 1659 | I3: 范南山 | J3: 男 | K3: 承祖遗下荒山 | L3: 刘宅 | M3: 不详 | N3: 坐落铁狮峯下□□塝□内（土名不全） | O3: 坟地 | P3: 坟地＋山／山林 | Q3: 祖遗荒山一片内抽出一穴，卖与刘宅边前去安葬坟墓 | R3: 时值价银伍钱正 | S3: 0.5 | T3: 银两 | U3: 魏玉璟(?)（说谕人） | V3: 萧秀(?)卿（在见人） | W3: 揭时发(?)（代字人） | X3: 无官印（白契） | Y3: 卖出一穴听买主择日安葬；如有来历不明、出头抵当，不涉买主之事 | AA3: 只卖荒山中一个坟穴，价仅五钱；契纸左方背面大字墨书'福地'。用'说谕人'称中人。 | AC3: 中 | AD3: 月份字不清；土名、中人及代字人名字有存疑 | AE3: 1 | AF3: Seller: 范南山 [FAN Nanshan] -- Personal | AG3: 1659 | AH3: 查看原件 | AI3: 31735066267711
A4: 1 | B4: 3 | C4: 买卖（卖／卖断） | D4: 卖契 | E4: 2 清前期（1644-1795） | F4: 康熙 | G4: 康熙十七年三月十九日 | H4: 1678 | I4: 徐正耀 | J4: 男 | K4: 原祖置为正屋；声明与徐家伯叔兄弟子孙无干 | L4: 杨元管(?)（杨家） | M4: 闽清县 | N4: 闽清县十都□墘地方，土名井墘厝 | O4: 屋／厝 | P4: 屋＋山／山林 | Q4: 正屋壹座六扇五间，上至椽尾下至地基，内有书院壹间空地；连屋后竹林、山业、竹树、水尾牛栏(?)等，统卖与杨家永远起盖住居；四至含水圳、后门阳塝等 | R4: 价银拾捌两正，其银水九五色 | S4: 18 | T4: 银两 | U4: 吴朝宇(?) | W4: 陈五(?)费(?) | X4: 钤闽清县官印多方（红契），左下另有骑缝半印 | Y4: 统卖与杨家永远起盖住居；日后不得言找言赎，如有来历不明，徐家出头支当 | AA4: 清初闽清县红契，盖有大方县印；房屋与竹林山场连带出售。契末有'劈'字骑缝半字。 | AB4: 目录地点作 unknown，契文明载闽清县十都 | AC4: 中 | AD4: 买主名'杨元管'、地名'□墘'、代字人名字存疑；银色'九五'存疑 | AE4: 1 | AF4: Seller: 徐正耀 [XU Zhengyao] -- Place: unknown -- Government | AG4: 1678 | AH4: 查看原件 | AI4: 31735066267729
A5: 1 | B5: 4 | C5: 典当／胎借 | D5: 典契 | E5: 2 清前期（1644-1795） | F5: 乾隆 | G5: 乾隆贰拾伍年伍月 日 | H5: 1760 | I5: 黄毓扆 | J5: 男 | K5: 承祖有民田；凑字中称受主为表伯 | L5: 未写名（凑字称'业表伯处'） | M5: 闽清县 | N5: 拾壹都地方，土名和尚墘、长垅、平水潭台尾、上下大坵尾园前后埕利、吴厝洋上中段、桑园二小坵等处 | O5: 田 | P5: 田 | Q5: 民田数号：佃陈朝彩，土名和尚墘，载租米壹石捌斗；佃许继实，土名长垅平水潭台尾，抽出租米壹石壹(?)斗伍升；佃林于(?)奏(?)，土名上下大坵尾园前后埕利吴厝洋上中段、桑园二小坵，载租米贰石柒斗 | R5: 价银陆拾叁两正，纹广(?)；凑字另凑钱壹拾千文(?) | S5: 63 | T5: 银两 | U5: 薛宜(?)章 | V5: 刘有堂（在见）；谢朝尊(?)；刘有炳(?)（凑字中见） | X5: 两纸均钤方形红官印（县印，印文不清），属红契 | Y5: 典契：限伍年满之日备银取赎；凑字后仍限期取赎 | Z5: 1) 典契，乾隆贰拾伍年伍月，黄毓扆将民田数号（载租米合伍硕余）典出，价银陆拾叁两，限伍年备银取赎；2) 凑字（找贴契），乾隆叁拾贰年伍月，黄毓扆就前典田再向业主表伯处凑出钱壹拾千文(?)，亦钤红印 | AA5: 典与找凑相隔七年，典价外再凑钱，体现'典—凑'的逐步出让；典契附'计开'逐佃列租。契纸左侧有椭圆墨圈内书'大吉(?)'字样。 | AB5: 契文未写县名，目录作闽清县；目录以黄毓扆为Owner | AC5: 中 | AD5: 受主姓名未见；凑字钱数及中见名字草书存疑；部分租额数字存疑 | AE5: 2 | AF5: Owner: 黃毓扆 [HUANG Yuyi] -- Place: 福建省閩清縣 [Fujian Sheng Minqing Xian] -- Government | AG5: 1760 to 1767 | AH5: 查看原件 | AI5: 31735064607546
A6: 1 | B6: 5 | C6: 买卖（卖／卖断） | D6: 卖契 | E6: 2 清前期（1644-1795） | F6: 乾隆 | G6: 乾隆贰拾陆年辛巳岁拾月初二日 | H6: 1761 | I6: 许琼栢、许奕栢 | J6: 男 | K6: 许氏贰房叔侄，祖父遗下山埔 | L6: 吴省忠叔侄 | M6: 永定县 | N6: 土名大溪边磜下尚上 | O6: 山林 | P6: 山／山林＋坟地 | Q6: 山埔壹所，原有土窨贰穴；上至许家坟下为界，下至圳面为界，左右并无土窨相连；准吴家坟安葬 | R6: 九四(?)足色价银叁拾两正 | S6: 30 | T6: 银两 | U6: 官盛清（说合人） | V6: 许芳栢（房户/房亲）；全侄许恭上、许信上等（同立） | X6: 契面钤永定县印多方（红契）；附乾隆二十七年契尾，纳税银玖钱（税率3%） | Y6: 永远为照；不得重复典当、言阻 | Z6: 1) 卖山埔土窨契，乾隆贰拾陆年辛巳拾月初二日，许琼栢、许奕栢卖与吴省忠叔侄，价银叁拾两，钤永定县印；2) 契尾，乾隆贰拾柒年捌月，永字一千四百十三号，业户吴省忠买许琼栢、许奕栢坐落大溪边磜下尚上土窨，用价银叁拾两，纳税银玖钱正，钤永定县印 | AA6: 契尾印刷文引乾隆十五年布政使司奏准契尾格式，前后幅分写；税额正好为价银百分之三。卖的是坟穴用的'土窨'。 | AB6: 目录年代1761-1762与正契、契尾吻合 | AC6: 中 | AD6: 银色成数及同立侄名字存疑 | AE6: 2 | AF6: Seller: 許瓊栢 [XU Qiongbai] -- Buyer: 吳省忠 [WU Shengzhong] -- Place: 福建省永定縣 [Fujian Sheng Yongding Xian] -- Government | AG6: 1761 to 1762 | AH6: 查看原件 | AI6: 31735064607538
A7: 1 | B7: 6 | C7: 买卖（卖／卖断） | D7: 卖契 | E7: 2 清前期（1644-1795） | F7: 乾隆 | G7: 乾隆叁拾贰年拾贰月 日 | H7: 1767 | I7: 徐干通（仝侄徐士孚） | J7: 男 | K7: 叔侄同立；承祖遗下苗田 | L7: 峡阳应熊孙 | M7: 南平县 | N7: 坐落土名小溪漈下垅（峡阳） | O7: 田 | P7: 田 | Q7: 苗田一段，年收苗谷柒箩伍斗，实载苗米柒升伍合(?)；先年已抽出苗谷□箩捌斗与应熊孙为业，此次再卖自己名下苗谷陆斗贰升伍合，实载民苗陆合贰(?)；另随田鸭肆只；粮米在梅北二图三甲徐壬童户内推出，收入峡阳二图二甲应熊茂户内完粮 | R7: 时值土风实卖得契价纹银贰两贰钱正 | S7: 2.2 | T7: 银两 | U7: 徐起孙（代字中） | W7: 徐起孙（代字中） | X7: 钤红色斜方官印数方（红契），印文不清 | Y7: 卖契；声明未曾典挂外人财物，无准折之类，二家各无悔 | AA7: 契内先问房亲兄弟不愿承买，方卖与峡阳应家；'随田鸭'作为附随物一并出卖，罕见。粮户推收写明图甲户名。 | AB7: 目录买主作'熊孙?'，契文为'应熊孙'；目录作南平县，契文只见峡阳、梅北等地名（峡阳属南平） | AC7: 中 | AD7: 契纸有两处虫蛀洞，'先年'抽出谷数、苗米合数不全；代字中名字'起孙'存疑 | AE7: 1 | AF7: Seller: 徐幹通 [XU Gantong] -- Buyer: 熊孫? [XIONG Sun?] -- Place: 福建省南平縣 [Fujian Sheng Nanping Xian] -- Government | AG7: 1767 | AH7: 查看原件 | AI7: 31735066237367
A8: 1 | B8: 7 | C8: 找贴／凑断 | D8: 找贴契／贴尽契 | E8: 2 清前期（1644-1795） | F8: 乾隆 | G8: 乾隆四十四年拾月 日 | H8: 1779 | I8: 李有定 | J8: 男 | K8: 其祖母于乾隆叁拾壹(?)年间手将民田典在谢处，今再立凑字 | L8: 谢（谢家） | M8: 闽清县 | N8: 闽清县陈洋地方 | O8: 田 | P8: 田 | Q8: 民田数号，租额土名俱载在原契内 | R8: 凑出价银贰两五钱正 | S8: 2.5 | T8: 银两 | V8: 段章绶（在见） | X8: 钤大方红官印（斜盖），属红契 | Y8: 面约加限叁年，限满之日听李家备价照原凑契面银两赎回，谢家不得执留 | AA8: 典后加凑并延长赎回期限三年，是典—凑关系的典型样本；出典人为祖母，由孙辈立凑字。 | AB8: 目录买主作'谢氏'，契文作'谢'（谢家），未见'氏'字 | AC8: 高 | AD8: 原典年份'乾隆叁拾壹年'中'壹'字存疑 | AE8: 1 | AF8: Seller: 李有定 [LI Youding] -- Buyer: 謝氏 [XIE] -- Place: 福建省閩清縣 [Fujian Sheng Minqing Xian] -- Government | AG8: 1779 | AH8: 查看原件 | AI8: 31735066237375
A9: 1 | B9: 8 | C9: 买卖（卖／卖断） | D9: 卖契 | E9: 2 清前期（1644-1795） | F9: 乾隆 | G9: 乾隆肆拾玖年拾贰月 日 | H9: 1784 | I9: 熊长生（同侄熊亨伦、熊亨乡） | J9: 男 | K9: 叔侄同立；田系自己所置 | L9: 熊亨读（本房堂侄） | M9: 古田县 | N9: 本处土名俗呌门首亭下大垅 | O9: 田 | P9: 田 | Q9: 民田壹号，受种壹拾伍石，该粮壹亩壹分贰厘伍毫；田叁年以后肆年当收 | R9: 时值价银壹拾玖两广正，每两的钱捌百文正 | S9: 19 | T9: 银两 | U9: 郑成富 | V9: 熊元廷（在见人） | W9: 张东礼(?)（代笔人） | X9: 卖契钤斜方红印一方；附古田县契尾（布政使司印、县印多方），纳税银壹两伍钱（价银3%） | Y9: 面约五拾叁年(?)备价赎田，不得刁难；若无力之日推入读户，买主管耕 | Z9: 1) 卖契，乾隆肆拾玖年拾贰月，熊长生同侄亨伦、亨乡将民田一号卖与本房堂侄熊亨读，价银壹拾玖两（每两折钱捌百文）；2) 契尾，道光拾□年（?），布字贰千玖百贰拾贰号，古田县业户黄鸿吉于道光二年买□廷乐(?)辛(?)氏田叁亩，坐落十八都土名报慈(?)，用价银伍拾两，纳税银壹两伍钱 | AA9: 族内买卖（叔卖与堂侄），价以银两计而折钱交付；所附契尾是道光年间黄鸿吉另一宗买田的税凭，与正契交易人不同，可能是同一田块后来转手到黄家（目录将黄鸿吉列为Owner）。契末大字'斋否(?)'。 | AB9: 目录年代1784–1830；契尾年份为道光拾□年，可能晚于1830 | AC9: 中 | AD9: 契尾年份、卖主姓名'廷乐辛氏'存疑；赎期'五拾叁年'理解存疑；代笔人名字末字不清 | AE9: 2 | AF9: Owner: 黃鴻吉 [HUANG Hongji] --Seller: 熊長生 [XIONG Changsheng] -- Buyer: 熊亨讀 [XIONG Hengdu] -- Place: 福建省古田縣 [Fujian Sheng Gutian Xian] -- Government | AG9: 1784 to 1830 | AH9: 查看原件 | AI9: 31735066237334
A10: 1 | B10: 9 | C10: 找贴／凑断 | D10: 找贴契／贴尽契 | E10: 2 清前期（1644-1795） | F10: 乾隆 | G10: 乾隆肆拾柒年玖月 日 | H10: 1782 | I10: 应梓龙 | J10: 男 | K10: 本年先已卖断，今再增找杜断 | L10: 刘继伍 | M10: 建阳县 | N10: 坐落磋上横窠(?)游岭黄厝垅 | O10: 田 | P10: 田 | Q10: 田皮骨（连皮带骨）米柒箩伍管正 | R10: 增找得杜断价纹银壹拾柒两正；外用中见礼银伍钱壹分正 | S10: 17 | T10: 银两 | U10: 刘礼□（原中人）；刘兆华（劝谕人） | V10: 应梓明（知契人） | W10: 徐(?)迟(?)万(?)（代字人） | X10: 钤建阳县印多方（红契） | Y10: 增找杜断之后仍凭买主永远管业，交租割过户当差完粮；永无言增言找之理 | AA10: 同年先卖断后再增找，'田皮骨'一并出卖；另记中见礼银，显示中人报酬。 | AC10: 中 | AD10: 地名'磋上横窠'、原中人名、代字人名字存疑 | AE10: 1 | AF10: Seller: 應梓龍 [YING Zilong] -- Buyer: 劉繼伍 [LIU Jiwu] -- Place: 福建省建陽縣 [Fujian Sheng Jianyang Xian] -- Government | AG10: 1782 | AH10: 查看原件 | AI10: 31735064607678
A11: 1 | B11: 10 | C11: 典当／胎借 | D11: 典契 | E11: 2 清前期（1644-1795） | F11: 乾隆 | G11: 乾隆四十七年十二月(?) 日 | H11: 1782 | I11: 可翅（叔） | J11: 男 | K11: 承祖手置得潘亨选根面全民田；母陈(?)氏知契 | L11: 侄钦家(?)（钦□） | M11: 不详 | N11: 廿五都土名廖四田地方 | O11: 田 | P11: 田 | Q11: 根面全民田壹号，丈计玖分，粮札载在海字壹千九百壹拾叁号 | R11: 典出价银拾两正纹广 | S11: 10 | T11: 银两 | U11: 程叔顺（中人） | V11: 陈(?)氏（知契母）；兄可森（在见）；叔志涵（仝见） | W11: 自笔 | X11: 无官印（白契） | Y11: 粮色两约六年为限，限满之日听叔照契银两依期取赎，不得执留 | AA11: 叔将田'缴典'与侄；粮立在廿五都四甲林光鹏户下，听侄过甲入户。契纸左上有大字'大吉'。 | AB11: 目录卖主作'可翅'，契中自称'叔可翅'，未写姓 | AC11: 中 | AD11: 月份、受典侄名字、知契母姓氏为草书，存疑 | AE11: 1 | AF11: Seller: 可翅 [KE Chi] -- Place: unknown --Personal | AG11: 1782 | AH11: 查看原件 | AI11: 31735066267844
A12: 1 | B12: 11 | C12: 找贴／凑断 | D12: 找贴契／贴尽契 | E12: 3 嘉道（1796-1850） | F12: 嘉庆 | G12: 嘉庆叁年贰月 日 | H12: 1798 | I12: 刘盛章 | J12: 男 | K12: 旧年冬已将房屋卖断与本族，今再增找杜断 | L12: 刘咸安、刘道建（本族） | M12: 建阳县 | N12: 坐落水北(?) | O12: 屋／厝 | P12: 屋＋地基／屋地 | Q12: 朽房屋地基共计叁榈，四至银两前契载明 | R12: 增找杜断价纹银捌两正；外用中银贰钱肆分正 | S12: 8 | T12: 银两 | U12: 刘如万（原中代字人） | W12: 刘如万（原中代字人） | X12: 钤建阳县印多方（红契） | Y12: 增找杜断之后，仍凭买者永远管业修整架造，开门出入，卖者不敢阻占；日后不得另生枝节言增言找 | AA12: 与 Folder 13（刘咸安契尾，嘉庆十年）为同一宗族内房屋交易的连续文书。 | AC12: 高 | AD12: 地名'水北'存疑 | AE12: 1 | AF12: Seller: 劉盛章 [LIU Shengzhang] --Buyer: 劉咸安 [LIU Xian'an] and 劉道建 [LIU Daojian] -- Place: 福建省建陽縣 [Fujian Sheng Jianyang Xian] -- Government | AG12: 1798 | AH12: 查看原件 | AI12: 31735064607652
A13: 1 | B13: 12 | C13: 找贴／凑断 | D13: 找贴契／贴尽契 | E13: 3 嘉道（1796-1850） | F13: 嘉庆 | G13: 嘉庆柒年贰月 日 | H13: 1802 | I13: 邱有本（仝弟邱有炳、侄邱传学） | J13: 男 | K13: 承嗣祖手置民田；乾隆年间经嗣祖妣手典与傅处；今因造垄（营葬）嗣祖妣急用 | L13: 傅（傅处） | M13: 闽清县 | N13: 闽清十七都半岭桥头里炉地方，土名南仓下洋下分对面山等处 | O13: 田 | P13: 田 | Q13: 民田数号，租额银两钱文俱载典、凑、尽各契内 | R13: 尽出价银贰拾贰两正纹广 | S13: 22 | T13: 银两 | U13: 弟有汉（中见） | X13: 无官印（白契） | Y13: 立尽契后仍面约年限伍年，限满之日听邱备价照各契面取赎，傅不得执留 | AA13: 名为'尽契'却仍保留伍年后回赎的权利，说明'尽'并不必然等于绝卖；用途写明为给嗣祖妣造坟。 | AC13: 高 | AE13: 1 | AF13: Seller: 邱有本 [QIU Youben] 邱有炳 [QIU Youbing] and 邱傳學 [QIU Chuanxue] -- Place: 福建省閩清縣 [Fujian Sheng Minqing Xian] -- Personal | AG13: 1802 | AH13: 查看原件 | AI13: 31735066266523
A14: 1 | B14: 13 | C14: 契尾／验契 | D14: 契尾 | E14: 3 嘉道（1796-1850） | F14: 嘉庆 | G14: 嘉庆十年五月 日 | H14: 1805 | I14: 刘盛章 | J14: 男 | K14: 契尾所记卖主 | L14: 刘咸安 | M14: 建阳县 | N14: 建阳县 | O14: 屋／厝 | P14: 屋 | Q14: 契尾计开：业户刘咸安买刘盛章厝(?)壹契 | R14: 用价银贰拾柒两(?)；纳税银□钱□分 | S14: 27 | T14: 银两 | X14: 建阳县印多方，契尾编号'徵(?)字□百九十二号'(?) | AA14: 与 Folder 11 刘盛章卖房屋给刘咸安、刘道建的增找契相对应，是同一宗交易后补税的官方凭证。 | AC14: 中 | AD14: 价银、税银数字草书存疑；编号不清 | AE14: 1 | AF14: Owner: 劉咸安 [LIU Xian'an] -- Place: 福建省建陽縣 [Fujian Sheng Jianyang Xian] -- Government | AG14: 1805 | AH14: 查看原件 | AI14: 31735064607660
A15: 1 | B15: 14 | C15: 典当／胎借 | D15: 典契 | E15: 3 嘉道（1796-1850） | F15: 嘉庆 | G15: 嘉庆拾年伍月 日 | H15: 1805 | I15: 赵守藻 | J15: 男 | K15: 嘉庆拾年肆月间买得陶天翰民田面数号，旋即转典 | L15: 林（林处） | M15: 侯官县 | N15: 侯官县草市都 | O15: 田面 | P15: 田面 | Q15: 民田面数号，佃林有栋耕作，递年载早晚租谷壹百柒拾筋；粮挂在草市都五甲陶孔镳户下应粮陆分伍厘；计开：第六区地字五百八十六号土名培下则园丈捌厘、五百八十七号土名坑下则园肆分零叁毫柒丝伍忽、五百八十八号土名荒地下则地贰分贰厘叁毫(?)五忽、五百八十九号土名坑里下则园丈伍厘 | R15: 得讫价银壹拾肆两(?)正 | S15: 14 | T15: 银两 | U15: 杨海武（中见友） | W15: 林标人（代笔） | X15: 钤红官印两方；另有民国时期'西湖区验税契事务所 验讫'朱戳及'验'字小戳 | Y15: 面约叁年为限，限满之日听藻备价照契面银两取赎；并缴陶君良原契壹纸 | AA15: 买入一月后即转典；契面有民国验契机关'西湖区验税契事务所'戳记，显示此契在民国时期仍被拿去验税。与 Folder 19 林有柱契尾相关联。 | AB15: 目录作'卖'，契文实为转典契 | AC15: 中 | AD15: 价银数字、个别田号亩分字存疑 | AE15: 1 | AF15: Seller: 趙守藻 [ZHAO Shouzao] -- Buyer: 林 [LIN] -- Place: 福建省侯官縣 [Fujian Sheng Houguan Xian] -- Government | AG15: 1805 | AH15: 查看原件 | AI15: 31735064607843
A16: 1 | B16: 15 | C16: 租佃／欠租 | D16: 领票／欠租字 | E16: 3 嘉道（1796-1850） | F16: 嘉庆 | G16: 嘉庆拾年至拾叁年 | H16: 1805 | I16: 黄隆贯 | J16: 男 | K16: 收租人（业主）出具收条 | L16: 陈国远代陈国龙；仁标代执惠 | M16: 不详 | O16: 田 | P16: 田 | Q16: 租米：国龙户肆斗肆升；执惠户壹斗陆升（法斗） | R16: 租米肆斗肆升；壹斗陆升 | T16: 米谷 | W16: 黄隆贯（自字） | X16: 无官印；部分收条钤收租人私章 | Z16: 共三页租米收条：1) 嘉庆拾贰年八月廿六日，入仁标租米，黄隆贯字（钤小方印）；2) 同纸两条：嘉庆拾年十二月十七日入陈国远代国龙租米肆斗肆升正，嘉庆拾年十二月十五日入仁标代执惠租米壹斗六升正，均黄隆贯字；3) 同纸两条：嘉庆拾叁年十二月十五日入陈国远代国龙(?)租米肆斗肆升正，嘉庆拾叁年十二月十五日入仁标代执惠租米壹斗陆升正，均黄隆贯字并钤印 | AA16: 每年租额固定，连续数年收条可看出定额租；陈国远为其兄弟代缴。与 Folder 21–23 陈国远、黄隆贯文书相关联。 | AC16: 中 | AD16: 第一条租米数额在纸边缺损处；'仁标''执惠'人名存疑 | AE16: 3 | AF16: Seller: 黃隆貫 [HUANG Longguan] -- Buyer: 陳國遠代陳國龍 [CHEN Huoyuan represents CHEN Guolong] -- Personal | AG16: 1805 to 1808 | AH16: 查看原件 | AI16: 31735066266705
A17: 1 | B17: 16 | C17: 典当／胎借 | D17: 典契 | E17: 3 嘉道（1796-1850） | F17: 嘉庆 | G17: 嘉庆十年六月吉日 | H17: 1805 | I17: 吴秉鉴 | J17: 男 | K17: 王氏知契（当为其母）；胞弟秉钧同押 | L17: 谢先经（据契尾） | M17: 闽县 | N17: 闽县 | O17: 屋／厝 | P17: 屋 | Q17: 据契尾为房屋；正契正文缺 | R17: 契尾：用价银肆拾两正，纳税银壹两贰钱正 | S17: 40 | T17: 银两 | U17: 郑长梅；金存国；郑提登 | V17: 王氏（知契）；胞弟吴秉钧；涂正□（乡保） | W17: 林学纶(?)（秉笔） | X17: 转典契钤闽县印及乡保长方戳；附嘉庆二十一年契尾，钤闽县印多方 | Y17: 转典（条款部分缺失） | Z17: 1) 转典契（残），嘉庆十年六月吉日，吴秉鉴立，正文部分未见，仅存落款；2) 契尾，嘉庆贰拾壹年肆月，闽县业户谢先经买吴秉鉴屋，用价银肆拾两，纳税银壹两贰钱 | AA17: 转典契后十一年才由谢先经买绝并纳税；契上有'乡保'署名及戳记。契纸左侧大字'大吉昌(?)'。 | AC17: 中 | AD17: 正契正文缺损未见；秉笔人、乡保名字存疑；契尾编号不清 | AE17: 2 | AF17: Owner: 吳秉鑒 [WU Bingjian] -- Seller: 吳秉鑒 [WU Bingjian] -- Buyer: 謝先經 [XIE Xianjing] -- Place: 福建省閩縣 [Fujian Sheng Min Xian] -- Government | AG17: 1805 to 1816 | AH17: 查看原件 | AI17: 31735064607579
A18: 1 | B18: 17 | C18: 契尾／验契 | D18: 契尾 | E18: 3 嘉道（1796-1850） | F18: 嘉庆 | G18: 嘉庆拾贰年拾(?)月 日 | H18: 1807 | J18: 不详 | L18: 罗□ | M18: 歙县 | N18: 歙县 | O18: 田 | P18: 田 | Q18: 契尾计开：买田(?)□号 | R18: 用价银壹拾伍两，纳税银肆钱伍分(?) | S18: 15 | T18: 银两 | X18: 江南安徽等处承宣布政使司契尾，钤布政使司及县印 | AA18: 批次中唯一一件安徽（徽州歙县）文书，契尾格式与福建契尾不同（顶部有'契尾'大字及宝珠纹）。 | AB18: 目录日期空缺，契尾写嘉庆拾贰年（1807） | AC18: 低 | AD18: 业户名仅见'罗'字；编号、卖主、税额不清；纸张破损 | AE18: 1 | AF18: Owner: 羅? [LUO ?] -- Place: 安徽省歙縣 [Anhui Sheng She Xian] -- Government | AH18: 查看原件 | AI18: 31735066237409
A19: 1 | B19: 18 | C19: 契尾／验契 | D19: 契尾 | E19: 3 嘉道（1796-1850） | F19: 嘉庆 | G19: 嘉庆十八年八月 日 | H19: 1813 | I19: 刘钦达 | J19: 男 | K19: 契尾所记卖主 | L19: 刘王建 | M19: 建阳县 | N19: 建阳县 | O19: 田 | P19: 田 | Q19: 契尾计开：业户刘王建买刘钦达田，坐落□□（未填全） | R19: 用价银贰拾伍(?)两；纳税银壹两□□(?) | S19: 25 | T19: 银两 | X19: 福建布政使司契尾，布字壹拾贰万玖千玖百叁拾玖号，钤建阳县印多方；契尾顶端骑缝号'□字□柳(?)廿九号' | AA19: 布字编号已达十二万余号，可见嘉庆后期契尾发行量。刘王建与 Folder 11、13 的刘咸安、刘道建、刘盛章同属建阳刘氏，可能同一宗族。 | AB19: 目录卖主作'刘钦达(违)'，契尾写'刘钦达'，'违'字未见 | AC19: 中 | AD19: 价银数字与税银数字草书存疑（若价银25两，3%税应为柒钱伍分，与所见'壹两'不符） | AE19: 1 | AF19: Seller: 劉欽達(違) [LIU Qinda(wei)] -- Buyer: 劉王建 [LIU Wangjian] -- Place: 福建省建陽縣 [Fujian Sheng Jianyang Xian] --Government | AG19: 1813 | AH19: 查看原件 | AI19: 31735066267471
A20: 1 | B20: 19 | C20: 契尾／验契 | D20: 契尾 | E20: 3 嘉道（1796-1850） | F20: 嘉庆 | G20: 嘉庆贰拾贰年贰月 日 | H20: 1817 | I20: 赵守藻 | J20: 男 | K20: 契尾所记卖主 | L20: 林有柱 | M20: 侯官县 | N20: 侯官县 | O20: 田 | P20: 田 | Q20: 契尾计开：业户林有柱买赵守藻田壹契，坐落□□ | R20: 用价银□拾柒(?)两；纳税银□两□钱□分 | T20: 银两 | X20: 福建布政使司契尾，布字贰万捌千捌拾叁号，钤侯官县印及布政使司印多方 | AA20: 与 Folder 14 赵守藻1805年转典给'林处'的田契对应：十二年后林有柱买断并纳税，佃户林有栋与买主林有柱可能同族。右上角墨书'久树(?)'。 | AC20: 中 | AD20: 价银、税银数字在印下，难以辨认 | AE20: 1 | AF20: Seller: 趙守藻 [ZHAO Shouzao] -- Buyer: 林有柱 [LIN Youzhu] -- Place: 福建省侯官縣 [Fujian Sheng Houguan Xian] -- Government | AG20: 1817 | AH20: 查看原件 | AI20: 31735064607850
A21: 1 | B21: 20 | C21: 典当／胎借 | D21: 典契 | E21: 3 嘉道（1796-1850） | F21: 道光 | G21: 道光贰年闰叁月吉日 | H21: 1822 | I21: 王志拔 | J21: 男 | K21: 原父手置阄分；父在日重新起盖店屋；今因要用 | L21: 陈（陈处） | M21: 闽县 | N21: 坐产闽(?)邑嘉崇里八(?)甸一中肆保铺沙堤街地方 | O21: 店屋 | P21: 店屋＋地基／屋地 | Q21: 前后两座店屋：原父于乾隆□拾年间用价银壹拾叁两买断陈林氏屋地一所，起盖肆柱店面一榈；嘉庆壹拾年间又用价银壹百贰拾两典得店后史尚才伍柱厝屋一进、二柱厨房一榈；嘉庆拾□年两座俱被火回禄，父在日鸠料将两主空地统重新起盖前伍柱店面一座、中拔榭贰榈又叁柱楼一榈、后拔榭伍榈，外空地一所，园篱一耳至江；道光元年拾贰月史尚才又向拔凑断出屋价银贰拾贰两；四至：前至官街，后至江，左至陈家屋，右至陈家屋，上至椽瓦，下至砾石地基 | R21: 得讫屋价银叁百两正纹广，外加修理银壹拾两，共成银叁百壹拾两 | S21: 310 | T21: 银两 | U21: 陈务睦(?)（中友）；叶闻蔚(?) | V21: 陈国梁(?)（在见） | W21: 王兴朝（代笔） | X21: 无县印；有'地保'长方朱戳（二四保铺保应陞(?)） | Y21: 约年限满之日听拔备价照契面并修理银两赎回，陈家不得执留；面约赎屋之日每两折钱壹千文，用下杭街钱店钱票 | AA21: 随契统付上手契共十五纸（高林周、陈林氏、曾居盛、林文发、郑东人、史尚才等典断契），完整记录一座城区店屋数十年间的买、典、火灾重建、凑断经过；约定赎回时用下杭街钱店钱票。地保戳记显示城市铺保制度。 | AB21: 目录作'王志拨?'与卖契，契文为'王志拔'，且实为典契 | AC21: 中 | AD21: 里甸名、中友及在见人名字存疑；典期年限字迹模糊 | AE21: 1 | AF21: Seller: 王志撥？ [WANG Zhibo] -- Buyer: 陳 [CHEN] -- Personal | AH21: 查看原件 | AI21: 31735066267687
A22: 1 | B22: 21 | C22: 租佃／欠租 | D22: 领票／欠租字 | E22: 3 嘉道（1796-1850） | F22: 道光 | G22: 道光玖年二月 日 | H22: 1829 | I22: 陈国远 | J22: 男 | K22: 欠租佃户，立票人 | L22: 未写名（收租业主，应即黄隆贯） | M22: 不详 | O22: 田 | P22: 田 | Q22: 旧欠租米分期偿还 | R22: 旧欠租米壹石壹斗＋壹石零玖升 | T22: 米谷 | V22: 叶宜全（保票人） | W22: 吴青山（代字） | X22: 无官印 | Y22: 过期每斗每月加利米叁合，系保票代赔无词 | Z22: 同纸两张欠租票：1) 凭票支旧欠租米壹石壹斗正，期至辛卯年八月初十日送仓交纳；2) 凭票支旧欠租米壹石零玖升正，期至辛卯年十二月二十日送仓交纳；两票均道光玖年二月立 | AA22: 欠租转为带利息的期票，保人负代赔责任；立票人名字被墨圈圈出（可能表示已清偿注销）。 | AB22: 目录把叶宜全列作 Buyer，实为保票人 | AC22: 高 | AE22: 1 | AF22: Seller: 陳國遠（立票人） [CHENG Guoyuan] -- Buyer: 葉宜全（保票人） [YE Yiquan] -- Personal | AG22: 1829 | AH22: 查看原件 | AI22: 31735066266580
A23: 1 | B23: 22 | C23: 租佃／欠租 | D23: 领票／欠租字 | E23: 3 嘉道（1796-1850） | F23: 道光 | G23: 道光玖年二月 日 | H23: 1829 | I23: 陈国远 | J23: 男 | K23: 欠租佃户，立票人 | L23: 未写名（收租业主，应即黄隆贯） | M23: 不详 | O23: 田 | P23: 田 | Q23: 旧欠租米分期偿还，期限延至乙未（1835）、丙申（1836）年 | R23: 旧欠租米共叁石柒斗余 | T23: 米谷 | V23: 叶宜全（保票人） | W23: 吴青山（代字） | X23: 无官印 | Y23: 过期每斗每月加利米叁合，系保票代赔无词 | Z23: 同纸三张欠租票，均道光玖年二月立：1) 旧欠租米壹石壹斗正，期至乙未年八月□日送仓；2) 旧欠租米壹石零玖升正，期至乙未年拾二月二十日送仓；3) 旧欠租米壹石伍斗贰升叁合叁勺，期至丙申年十二月二十日送仓 | AA23: 与 Folder 21 同日所立同格式欠租票，但还期推至六七年之后，构成一个长期分期偿还计划；同一保人、同一代字人。 | AB23: 目录把叶宜全列作 Buyer，实为保票人 | AC23: 高 | AD23: 第一票送仓日期字不全 | AE23: 1 | AF23: Seller: 陳國遠（立票人） [CHENG Guoyuan] -- Buyer: 葉宜全（保票人） [YE Yiquan] -- Personal | AG23: 1829 | AH23: 查看原件 | AI23: 31735066266572
A24: 1 | B24: 23 | C24: 租佃／欠租 | D24: 领票／欠租字 | E24: 3 嘉道（1796-1850） | F24: 道光 | G24: 道光九年七月廿八日 | H24: 1829 | I24: 黄隆贯 | J24: 男 | K24: 收租业主，立收字 | L24: 陈国远 | M24: 不详 | O24: 田 | P24: 田 | Q24: 收到陈国远旧欠租米 | R24: 旧欠租米壹石肆斗正 | T24: 米谷 | W24: 黄隆贯（自立） | X24: 无官印；钤黄隆贯私章及两方菱形骑缝章 | AA24: 证实 Folder 21、22 欠租票的债权人就是黄隆贯；黄隆贯从嘉庆十年（Folder 15）到道光九年一直向陈国远家收租。 | AC24: 高 | AE24: 1 | AF24: Seller: 黃隆貫 [HUANG Longguan] -- Buyer: 陳國遠 [CHEN Guoyuan] -- Place: unknown -- Personal | AG24: 1829 | AH24: 查看原件 | AI24: 31735066237722
A25: 1 | B25: 24 | C25: 分家书 | D25: 分家书／阄书 | E25: 3 嘉道（1796-1850） | F25: 道光 | G25: 道光拾柒年拾月 日 | H25: 1837 | I25: 义容（主阄父） | J25: 男 | K25: 父主持阄分；六子：长男良和（诗房）、次男良春（书房）、三男良吉（易房）、四男良禄（礼房）、五男良科（春房）、六男良提(?)（秋房） | L25: 六子：良和、良春、良吉、良禄、良科、良提(?) | M25: 不详 | N25: 养膳田坐产十七都曲山地，土名大垅等处 | O25: 屋／厝 | P25: 屋＋田 | Q25: 房屋按房分配：诗房上厝本厝左边正横厝第一直前壹橔，书房同第一直后壹橔，易房第贰直前壹橔，礼房第贰直后壹橔，春房第□直前壹橔，秋房第□直后壹橔；父抽养膳民田根壹号，受种贰斗，载租早米捌斗伍管，禾米肆斗，纳在县中侯处 | V25: 叔义安（公见）；兄良光（公见）；王绳喜（母舅）；毛元斯（表叔） | W25: 陈明金（代笔叔公） | X25: 无官印（私家文书） | Z25: 线装阄书一册共11页：封面'道光拾柒年拾月吉日立'；序文（父义容述兄弟和宜防争、请宗亲公见、按诗书易礼春秋六房阄分）；父抽养膳田一号；诗、书、易、礼、春、秋六房各一页，分得上厝本厝左边正横厝某直前／后壹橔；末页落款及立阄人、公见、母舅、表叔、代笔署名 | AA25: 以《诗》《书》《易》《礼》《春》《秋》六字为六房阄号，是典型的儒雅化阄书；对房屋按'直''橔'精细切分。目录标为 Folder 24-1，可能还有同组其它册。 | AB25: 目录 Owner 作'义容'，未写姓；阄书亦未见姓氏 | AC25: 中 | AD25: 六男名'良提'、春秋两房的'第□直'数字存疑；养膳田数量字存疑；序文未逐字录 | AE25: 11 | AF25: Owner: 義容 [Yirong] -- Place: unknown -- Personal | AG25: 1837 | AH25: 查看原件 | AI25: 31735066267976
A26: 1 | B26: 25 | C26: 典当／胎借 | D26: 典契 | E26: 3 嘉道（1796-1850） | F26: 道光 | G26: 道光拾玖年十壹月 日 | H26: 1839 | I26: 叶国佑 | J26: 男 | K26: 阄分己分；胞兄国佐在见，胞侄世枝、世桄仝见 | L26: 大绅（绅） | M26: 古田县 | N26: 坐址九都九保太平洋地方，土名俗呌里洋中坂 | O26: 田 | P26: 田 | Q26: 福屯田壹号，该田肆亩贰分，乡正年收租早谷陆石小秤足；粮系屯课，推入绅户 | R26: 田价银陆拾伍两纹广整；外有中用钱捌百文 | S26: 65 | T26: 银两 | U26: 周昌烈(?)（中人） | V26: 胞兄叶国佐（在见）；胞侄叶世枝、叶世桄（仝见） | X26: 钤红色斜方官印三方（红契） | Y26: 约限伍年满足外，任佑备价取赎，不论年限，绅不得揽留；赎田每两折钱捌百捌拾文 | AA26: 典的是'屯田'（屯课），粮由'九都叶步增福屯'户内推出；并缴原典契壹纸、尽契壹纸、借字壹纸共肆纸。契末大字'典契(?)'。受典人只写'大绅'，可能是对士绅的敬称。 | AB26: 目录作卖契、买主'绅'；契文为典契 | AC26: 中 | AD26: 中人名、租谷数存疑；'大绅'是否人名存疑 | AE26: 1 | AF26: Seller: 葉國佑 [YE Guoyou] -- Buyer: 紳 [SHEN] -- Place: 福建省古田縣 [Fujian Sheng Gutian Xian] -- Government | AG26: 1839 | AH26: 查看原件 | AI26: 31735066266515
A27: 1 | B27: 26 | C27: 分家书 | D27: 分家书／阄书 | E27: 3 嘉道（1796-1850） | F27: 道光 | G27: 道光贰拾年□月 日 | H27: 1840 | I27: 林氏（母） | J27: 女 | K27: 寡母主持为二子阄分；长男国诗、次男国书 | L27: 长男国诗、次男国书（福、禄二房） | M27: 不详 | N27: 土名半塘垅、虎啸、马路边、白龙山等处（县未写） | O27: 田 | P27: 田＋屋＋池塘＋坟地 | Q27: 祖遗山场屋宇田园：养膳田（郭大珠早晚租谷陆百肆拾斤等）；大厅、后厅、天井、左右披屋、大厝左边楼等房屋；田（郭其泉、陈肇祺、周雍美等佃，租谷数百斤至壹千余斤）；门前大池壹口（鱼利两房轮收）；陈兆熙造坟等 | V27: 林长宾(?)（在见）；勇(?)春(?)（在见）；陈必祥；杨能波(?)；李仕□；林文愿(?) | W27: 李龙泉(?) | X27: 无官印 | AA27: 母亲（林氏）作为立阄人主持分家，体现寡母在家产分配中的权威；池塘、鱼利、粮色按年轮值；纸张多处虫蛀成洞。契末大字'大长发其祥'。 | AB27: 目录 Owner 作'林氏'；契文为'母林氏' | AC27: 低 | AD27: 纸张大面积虫蛀，许多田名、租额、见人姓名残缺；月份不清 | AE27: 1 | AF27: Owner: 林氏 [LIN Shi] -- Personal | AG27: 1840 | AH27: 查看原件 | AI27: 31735066266259
A28: 1 | B28: 27 | C28: 其他 | D28: 其他（禁鸦片保甲门牌） | E28: 3 嘉道（1796-1850） | F28: 道光 | G28: 道光贰拾年分 | H28: 1840 | I28: 闽清县正堂徐（知县） | J28: 官方 | K28: 县官颁发的保甲门牌 | L28: 陈行典(?)（家长） | M28: 闽清县 | N28: 闽清县上十七都□图 | O28: 其他／非土地 | P28: 其他（户籍门牌，非土地） | Q28: 家长陈行典(?)，不吸烟，年六十八岁，以耕田为业；子立崇，孙邦栋、邦腾、邦镇、邦增、邦煜、邦曾(?)、邦炽，曾孙元具；侄立训、立拱(?)，侄孙邦仪、邦夫(?)、邦佑；十家联保陈立灿等；牌正陈孝朗、副陈孝炳；甲正余邦干、副黄金波 | X28: 木刻印刷官颁门牌，盖有长方形墨印 | AA28: 鸦片战争当年（道光二十年）闽清县'查禁鸦片派保门牌'，逐户登记是否吸烟，并引新例：限一年六个月内戒除，逾限者拟绞监候，十家联保连坐。是土地契约外的社会控制史料。 | AB28: 目录 Owner 作'陈行典'，门牌家长名字'行典'字迹模糊 | AC28: 中 | AD28: 家长名、部分孙辈名字为手写小字，存疑；图号空白 | AE28: 1 | AF28: Owner: 陳行典 [CHENG Xingdian] -- Place: 福建省閩清縣 [Fujian Sheng Minqing Xian] -- Personal | AG28: 1840 | AH28: 查看原件 | AI28: 31735066266408
A29: 1 | B29: 28 | C29: 买卖（卖／卖断） | D29: 卖契 | E29: 3 嘉道（1796-1850） | F29: 道光 | G29: 道光贰拾年八月 日 | H29: 1840 | I29: 刘孝良（仝弟刘孝清） | J29: 男 | K29: 兄弟同立；承祖遗手置有税山；声明系良、清承祖遗，与别房无干 | L29: 林高满 | M29: 闽清县 | N29: 十四都重坑地方，土名桔(?)模(?)坪等处；又土名深田址 | O29: 山林 | P29: 山／山林＋屋＋地基／屋地 | Q29: 税山壹所（内抽出黄(?)甜竹林壹所），四至：上至顶、下至田、左至哲焕(?)失路直上、右至胡家墓仑中宫直上；又卖税山土名深田址，界上下左右水流窝；前坂厝屋壹扇左边等处（中宫直上至椽桁、下至地基）及右边园坪壹半、上下余地；山场松杉什木、笋竹、桐茶等 | R29: 卖出价钱壹拾壹千伍百文；民国验契按卖价拾贰圆，纳税肆角捌分 | S29: 11500 | T29: 铜钱 | U29: 朱明贵（代字中） | V29: 宗兄佑志（在见）；仝弟刘孝清 | W29: 朱明贵（代字中） | X29: 白契上贴民国印花税票；附民国二十六年福建省财政厅官契纸（闽清县印、财政厅印，契税4%） | Y29: 卖断；林家永远入宅住居，刘家不敢异言；如刘家另有吉地，林家不得借批阻；山租钱每年壹百文交还刘家 | Z29: 1) 分卖山契，道光贰拾年八月，刘孝良仝弟孝清将十四都重坑税山一所及庄基地、厝屋卖与林高满，价钱壹拾壹千伍百文；契上贴民国印花税票数枚；2) 福建省财政厅颁发卖契纸（官契纸），中华民国二十六年五月二十七日，闽清县，业主林高满，不动产种类税山，坐落重坑，面积一所，卖价拾贰圆，应纳税银肆角捌分，出卖人刘孝良，中证人朱明贵，立契年月填'道光二十年八月' | AA29: 清道光白契在近百年后（1937）被持去补税并换领民国官契纸，价钱折为法币拾贰圆。卖主保留每年山租钱壹百文。契首大字'大进益(?)'。 | AB29: 目录年代1840–1937与正契、官契纸吻合 | AC29: 中 | AD29: 部分土名（桔模坪、黄甜竹林）及四至人名存疑；官契纸字号不清 | AE29: 2 | AF29: Seller: 劉孝良 [LIU Xiaoliang] -- Buyer: 林高滿 [LIN Gaoman] -- Place: 福建省閩清縣 [Fujian Sheng Minqing Xian] -- Government | AG29: 1840 to 1937 | AH29: 查看原件 | AI29: 31735066266556
A30: 1 | B30: 29 | C30: 典当／胎借 | D30: 胎借／借字 | E30: 3 嘉道（1796-1850） | F30: 道光 | G30: 道光贰拾壹年辛丑二月十六日 | H30: 1841 | I30: 林忠、林荣（兄弟） | J30: 男 | K30: 兄弟同立当季字；会份系自己续买赖绍福名下 | L30: 赖荣松（先生） | M30: 不详 | O30: 其他／非土地 | P30: 其他（关帝会会份） | Q30: 关帝季（神明会）式大股，原由赖绍福名下续买 | R30: 佛银陆大圆正，共重□□ | S30: 6 | T30: 番银 | V30: 赖祥福（在场见人） | W30: 弟(?)荣（执笔） | X30: 无官印；纸张四周裱有蓝色织锦边 | Y30: 每员每月行息式分，其银的限对期之日并本息一足兑还；如违，任凭银主将季起取，改名饮酒分承 | AA30: 抵押品不是土地而是'关帝季'会份（神明会股份），违约则债主可改名入会'饮酒分承'；当日交付买季契二纸。用'佛银大圆'（西班牙银元）计价。 | AB30: 目录作卖主/买主，实为以会份作抵押的当借字 | AC30: 高 | AD30: 执笔人名字存疑；重量数字不清 | AE30: 1 | AF30: Seller: 林忠 [LIN Zhong] and 林榮[LIN Rong]-- Buyer: 賴榮松 [LAI Rongsong] -- Place: Unknown -- Personal | AG30: 1841 | AH30: 查看原件 | AI30: 31735066266457
A31: 1 | B31: 30 | C31: 合同／约字 | D31: 合同 | E31: 3 嘉道（1796-1850） | F31: 道光 | G31: 道光贰拾贰年拾贰月念五日 | H31: 1842 | I31: 黄惟裕、黄惟岑 | J31: 男 | K31: 两家田池相连致口角争端，经亲友公议立合约 | M31: 不详 | O31: 田 | P31: 田＋池塘 | Q31: 一家掌田、一家掌池；田边在池边者递年池水润田，约至春三月末为限；其池土岑内应半埕(?)；侯池主幸(?)池之日挑回应用 | R31: 池土公估价钱叁百伍拾文（田主再买池土） | S31: 350 | T31: 铜钱 | V31: 黄孝甲（公亲）；黄继书（公亲）；黄廉镜（公亲）；黄廉阜（公亲）；黄绍度（公亲） | W31: 黄继书（代笔） | X31: 无官印 | AA31: 同族两家调处田与池塘用水、挖池土纠纷的合约，规定放水时限、池土归属和修理责任；左端有骑缝大字'合同二纸(?)'半字。 | AB31: 目录只列卖主，实为调解合约 | AC31: 中 | AD31: 岑内应半埕''幸池'等词语存疑 | AE31: 1 | AF31: Seller: 黃維裕 [HUANG Weiyu] and 黃維岑[HUANG Weicen] -- Personal | AG31: 1842 | AH31: 查看原件 | AI31: 31735066266366
A32: 1 | B32: 31 | C32: 典＋找贴 | D32: 典契＋找贴契／贴尽契（凑断契） | E32: 3 嘉道（1796-1850） | F32: 道光 | G32: 道光贰拾肆年贰月吉日（典）；道光贰拾伍年陆月吉日（凑断） | H32: 1844 | I32: 林厚成（同胞弟厚禄、厚祥，胞侄春新） | J32: 男 | K32: 承父在日手置店屋；兄弟叔侄同立，知契母郭氏，胞嫂陈氏画押 | L32: 叶家（叶成） | M32: 侯官县 | N32: 侯邑魁辅铺地方 | O32: 店屋 | P32: 店屋 | Q32: 店屋壹栋，坐南朝北，前进五柱、天井、左右过水、第二进五柱、过水相连、后进叁柱，连楼阁地坪、门窗户扇、井厕一切；四至：前至官街、后至河、左至叶家屋、右至金(?)家屋 | R32: 典价银陆拾伍两正＋修理银伍两共成柒拾两；凑断银叁拾两，共成壹百两正，正纹广九七色 | S32: 100 | T32: 银两 | U32: 林道吉 | V32: 知契母郭氏；胞嫂陈氏；胞弟厚祥；胞弟厚禄；胞侄春新；胞孀李氏（在见）；陈元海（在见） | W32: 蒋则荣 | X32: 契面钤多枚朱红大方印（疑为侯官县印，红契）；地保'勤慎'戳记（侯字第拾玖号城内，魁辅铺地保）；1950年代台江区私房改造办公室'国家经租'印及福州土地登记处登记章 | Y32: 典契约伍年为限，限满听备价取赎；凑断后声明永断葛藤，不得言赎言凑 | Z32: ①典契：道光贰拾肆年贰月，林厚成同胞弟等将店屋典与叶家，价银陆拾伍两＋修理银伍两共柒拾两，约伍年为限取赎；②凑断契：道光贰拾伍年陆月，林厚成仝胞弟厚禄、厚祥、胞侄春新将该店屋凑断与叶家，再得价银叁拾两，连前共成壹百两正；凑断契上另加盖1950年代'国家经租 台江区人民委员会私房改造办公室'蓝印及'福州土地登记处'红色登记章（义字230号） | AA32: 同一店屋先典后凑断，两份契纸并存，凑断契注明缴原典契一纸；1950年代被盖'国家经租'章，反映社会主义私房改造。与 Folder 34（31735066267802）为同一交易的契尾与民国验契。 | AB32: 目录作卖契（Seller/Buyer），实为典契加凑断契；目录未列胞弟厚禄为'厚禄'外另有胞侄春新 | AC32: 中 | AD32: 典契右至'金(?)家屋'；代笔'蒋则荣'末字；凑断契左侧残缺，中人等签押可能缺失 | AE32: 2 | AF32: Seller: 林厚成 [LIN Houcheng] and 林厚祿 [Lin Houlu] and 林厚祥 [Lin Houxiang] -- Buyer: 葉成 [YE Cheng] -- Place: 福建省侯官縣 [Fujian Sheng Houguan Xian] -- Personal | AG32: 1844 to 1845 | AH32: 查看原件 | AI32: 31735066266374
A33: 1 | B33: 32 | C33: 契尾／验契 | D33: 契尾 | E33: 3 嘉道（1796-1850） | F33: 道光 | G33: 道光贰拾玖年拾贰月 日 | H33: 1849 | I33: 林元梁(?) | J33: 男 | K33: 契尾填写'业户林元昂(?)买林元梁(?)山一所' | L33: 林元昂(?) | M33: 古田县 | N33: 古田县，本处土名□□、对面山等处 | O33: 山林 | P33: 山／山林 | Q33: 山一所，坐落本处土名□□、对面山等处 | R33: 用价银贰拾伍两陆钱叁分；纳税银□两柒钱陆分玖厘 | S33: 25.63 | T33: 银两 | X33: 福建布政使司颁刻印契尾，布字第捌千贰百捌拾伍号，右给古田县业户；钤多枚官印（骑缝） | AA33: 官颁契尾，仅存契尾不见原契；契尾顶部骑缝处手书号数'捌千贰百捌拾伍'。 | AB33: 目录业主作'林元鼎'，图像上业户名末字更像'昂' | AC33: 中 | AD33: 业户名'林元昂/鼎'、卖主'林元梁'末字、纳税银两数首字均不确定；土名不清 | AE33: 1 | AF33: Owner: 林元鼎 [LIN Yuanding] -- Place: 福建省古田縣 [Fujian Sheng Gutian Xian] -- Government | AG33: 1849 | AH33: 查看原件 | AI33: 31735066237417
A34: 1 | B34: 33 | C34: 典当／胎借 | D34: 卖契（田根，限期可赎） | E34: 3 嘉道（1796-1850） | F34: 道光 | G34: 道光叁拾年玖月吉日 | H34: 1850 | I34: 林世奕 | J34: 男 | K34: 承父阄分份下民田根；知契母萧氏 | L34: 林（名空缺） | M34: 侯官县 | N34: 侯邑三十八都白龙洋地方，土名园坵、深田 | O34: 田根 | P34: 田根 | Q34: 民田根壹号大小伍坵，土名园坵，计官丈贰亩零，年载租谷叁百贰拾肆筋平秤纳在周家；更有壹号土名深田，计官丈壹亩伍分，年载禾租谷壹百贰拾筋平秤纳在面主李家 | R34: 田根价银贰百两正，平戥九七色 | S34: 200 | T34: 银两 | U34: 翁太湖 | V34: 知契母萧氏；胞兄世美（在见）；胞兄世乔(?)（在见）；胞弟世廷 | W34: 王凤鸣 | X34: 无官印（白契） | Y34: 约伍年为限，限满听世奕备价照契面银两取赎；如未取赎仍听买主管业 | AA34: 典型一田二主：卖的是田根，租谷分别纳给周家和面主李家；买主仅写'林'字留空，契末大书'大熟'。另缴原契壹纸，共成贰纸。 | AC34: 高 | AD34: 在见'世乔'一名排列不清 | AE34: 1 | AF34: Seller: 林世奕 [LIN Shiyi] -- Buyer: 林 [LIN] -- Place: 福建省侯官縣 [Fujian Sheng Houguan Xian] -- Personal | AG34: 1850 | AH34: 查看原件 | AI34: 31735064607868
A35: 1 | B35: 33A | C35: 买卖（卖／卖断） | D35: 卖断契 | E35: 3 嘉道（1796-1850） | F35: 道光 | G35: 道光叁拾年拾壹月 日 | H35: 1850 | I35: 游振梅 | J35: 男 | K35: 道光十五年间用价买断陈□□店屋，今转卖；知契母张氏 | L35: 杨家（杨坤贞） | M35: 闽县 | N35: 闽邑嘉崇里八(?)图壹甲四保铺洲(?)堤街地方 | O35: 店屋 | P35: 店屋 | Q35: 店屋壹座，前系店面伍柱壹栋，后天井、披屋叁栋叁堵，又后进一所，楼阁横廊、板地杆廊一切俱全；四至：前至官街、后至江、左至郑家墙、右至陈家 | R35: 卖断出价银玖拾陆两，正纹库平；民国契纸载价壹百捌拾壹元 | S35: 96 | T35: 银两 | U35: 杨隆魁；郑廷源 | V35: 知契母张氏；弟振潮（在见）；弟振文；侄连提；出继男连芳；胞母舅(?)张昌□；胞姊黄游氏 | W35: 周绅杨(?) | X35: 清代契尾（闽县，官印）；民国十二年新颁卖契纸（新颁契纸印）；民国十四年(?)福建财政厅验税契照；光绪年间朱色注记 | Y35: 卖断，永断葛藤，不得言赎 | Z35: ①卖断契：道光叁拾年拾壹月，游振梅将店屋卖断与杨家；②契尾：闽县，□万壹千壹百肆拾玖号，右给闽县业户杨坤贞，载'杨坤贞买游振梅屋一所'；③民国新颁卖契纸：中华民国十二年五月四日，买主杨坤贞、卖主游振梅、中人杨隆魁，不动产种类店屋，卖价壹百捌拾壹元，应纳税额捌元贰角叁占(?)，原契'清红'，立契年月道光卅年十一月，坐落嘉崇里□保铺；④验税契照：中华民国十四年(?)五月，福建财政厅给业户杨坤贞；原契另有光绪拾壹年伍月、光绪廿一年六月红色注记戳 | AA35: 一件之内串连清代卖断契、契尾、民国换契与验契四种文书，跨越1850-1925年；民国换契时按银元重估价格。契末书'长发其祥'。 | AC35: 中 | AD35: 地名'八图''洲堤街'、陈姓原主名、代字人名、民国验契年份（十四年?）与税额均存疑 | AE35: 1 | AF35: Seller: 游振梅 [pin yin] -- Buyer: 楊坤貞 [pin yin] -- Place: 福建省閩縣 [Fujian Sheng Min Xian] -- Personal | AG35: 1850 to 1923 | AH35: 查看原件 | AI35: 31735068223258
A36: 1 | B36: 34 | C36: 契尾／验契 | D36: 契尾＋验契凭证 | E36: 4 咸同光宣（1851-1911） | F36: 咸丰 | G36: 咸丰肆年□月（契尾）；中华民国贰年拾贰月（契单） | H36: 1854 | I36: 林厚成 | J36: 男 | K36: 原卖主（道光二十五年凑断） | L36: 叶成 | M36: 侯官县 | N36: 侯官县魁辅铺／闽侯县魁辅里地方 | O36: 店屋 | P36: 店屋 | Q36: 店屋壹栋，坐南向北 | R36: 价银壹百两；纳税银叁两 | S36: 100 | T36: 银两 | U36: 林道吉 | V36: 陈元海（证） | W36: 蒋则荣 | X36: 布政司契尾（侯官县官印）；民国二年福建国税厅筹备处卖断契单（验契，纸价壹元）；地保戳记 | Z36: ①契尾：咸丰肆年□月，布字壹万玖百玖号，右给侯官县业户叶成，载'业户叶成买林厚成等店屋'，用价银壹百两，纳税银叁两；契尾粘连原典契末段（代笔蒋则荣、中友林道吉、地保'勤慎'戳、'大进'字样）；②卖断契单：福建国税厅筹备处颁，中华民国贰年拾贰月，验字第八万四千四百十七号，载业户叶成于清道光贰拾伍年陆月买受林厚成店屋壹栋，坐落闽侯县魁辅里，价银壹百两，证人陈元海；另有民国十五年三月九日朱色注记 | AA36: 与 Folder 31（31735066266374）为同一店屋的后续官方文书：交易1845年完成，1854年才投税领契尾，1913年再验契。 | AB36: 目录作1854-1913，与图像相符 | AC36: 中 | AD36: 契尾月份、号数个别字不清 | AE36: 2 | AF36: Owner: 葉成 [YE Cheng] --Seller: 林厚成 [LIN Houcheng] -- Buyer: 葉成 [YE Cheng] -- Place: 福建省閩侯縣和侯官縣[Fujian Sheng Minhou Xian and Houguan Xian] -- Government | AG36: 1854 to 1913 | AH36: 查看原件 | AI36: 31735066267802
A37: 1 | B37: 35 | C37: 买卖（卖／卖断） | D37: 卖断契 | E37: 4 咸同光宣（1851-1911） | F37: 咸丰 | G37: 咸丰八年十二月吉日 | H37: 1858 | I37: 陈士曾 | J37: 男 | K37: 原自己阄分份下根面全田；卖与堂兄 | L37: 陈士庆（堂兄） | M37: 侯官县 | N37: 侯邑廿八都富村地方，土名过圳、洋满池等处 | O37: 田（根面全） | P37: 田（根面全）＋池塘 | Q37: 根面全田叁号：土名过圳计官丈壹亩捌分，粮挂壹亩捌分；土名洋满池官丈肆分零，粮挂本都四图九甲陈纯户下；另一号粮挂本都四图四甲陈孟寿户下；年纳租谷叁百肆拾伍筋；内有池壹口，其水永听律派足用 | R37: 南街铜钱壹百叁拾千文正 | S37: 130000 | T37: 铜钱 | U37: 陈开文（族叔） | V37: 胞弟士美（在见） | W37: 卢(?)志高 | X37: 契面钤朱红方印数枚（疑为侯官县印，红契） | Y37: 卖断，永断葛藤，不得别生枝节 | AA37: 兄弟间根面全田卖断，粮户分挂于陈纯户、陈孟寿户，可见户籍粮户与实际业主分离；价以铜钱计，单位'千文'。契末'永远为业'。 | AB37: 目录地点作unknown，契文明写侯邑廿八都富村 | AC37: 中 | AD37: 第三号田土名及部分亩分、代字人首字不清；price_amount按文计 | AE37: 1 | AF37: Seller: 陳士曾 [CHEN Shizeng] -- Place: unknown -- Government | AG37: 1858 | AH37: 查看原件 | AI37: 31735066267885
A38: 1 | B38: 36 | C38: 买卖（卖／卖断） | D38: 卖断契 | E38: 4 咸同光宣（1851-1911） | F38: 同治 | G38: 同治壬戌元年柒月 日 | H38: 1862 | I38: 张华富 | J38: 男 | K38: 承祖遗下 | L38: 程金宝 | M38: 不详 | N38: 田里南坑，土名凤坑仔 | O38: 山林 | P38: 山／山林 | Q38: 皮骨茶山壹片（连竹、茶、杂木）；四至：上至岗顶、下至田、左至本张宅分水为界、右至亦本张分水为界 | R38: 时值价铜钱捌仟五百文正 | S38: 8500 | T38: 铜钱 | U38: 张华春（为中人）；张喜孙（说谕人） | V38: 张华应（在见人） | W38: 詹王佐 | X38: 无官印（白契） | Y38: 卖断，永远管业，不得阻执 | AA38: 皮骨（山面山底）一并卖断；声明上手契一时不及寻出，日后寻出不堪行用。契尾大书'卖断契'。 | AC38: 高 | AD38: 地名'田里'所属县份无法判断 | AE38: 1 | AF38: Seller: 张华富 [ZHANG Huafu] -- Personal | AG38: 1862 | AH38: 查看原件 | AI38: 31735064607454
A39: 1 | B39: 37 | C39: 典当／胎借 | D39: 典契（田根） | E39: 4 咸同光宣（1851-1911） | F39: 同治 | G39: 同治元年八月吉日 | H39: 1862 | I39: 杨兆通 | J39: 男 | K39: 承父阄分份下民田根 | L39: 林（名空缺） | M39: 侯官县 | N39: 侯邑三十八都白龙坛路地方，土名鲫鱼坵 | O39: 田根 | P39: 田根＋池塘 | Q39: 民田根壹号，计官丈贰亩伍分，大小三坵、池壹口，共肆坵；年纳面主王家早晚租谷叁百伍拾筋平秤 | R39: 田根价银贰百捌拾叁两伍钱正；取赎每两银折铜钱柒百伍拾文 | S39: 283.5 | T39: 银两 | U39: 蔡书波（中友）；李兆桐 | V39: 胞弟兆如；堂侄能波；刘朝达（在见） | W39: 李肇(?)松 | X39: 无官印（白契） | Y39: 叁年为限，限满听兆通备价照契面银取赎，每两折钱柒百伍拾文；约赎田以冬至前为期 | AA39: 并缴上手杨昌岳(?)典契、邦铭尽契、海武断契共成肆纸，可见此田根层层转手；与 Folder 33 林世奕契同在三十八都白龙一带，买主同为空名'林'，疑为同一林姓置产人。 | AB39: 目录作Seller，实为典契 | AC39: 中 | AD39: 上手契人名'昌岳''邦铭''海武'及代笔名中字不确定 | AE39: 1 | AF39: Seller: 楊兆通 [YANG Zhaotong] -- Buyer: 林 [LIN] -- Personal | AG39: 1862 | AH39: 查看原件 | AI39: 31735064607728
A40: 1 | B40: 38 | C40: 找贴／凑断 | D40: 找贴契／贴尽契（增找字） | E40: 4 咸同光宣（1851-1911） | F40: 同治 | G40: 同治贰年拾二月 日 | H40: 1863 | I40: 黄志林 | J40: 男 | K40: 自己手卖有田骨，前契载明 | L40: 刘子祥 | M40: 不详 | N40: （前契载明，本字未写） | O40: 田根 | P40: 田根 | Q40: 田骨，坐落、米数、银两俱载前契 | R40: 增找出洋银叁两正；外用中见礼洋银壹钱正 | S40: 3 | T40: 银元／大洋 | U40: 蔡廷有（为中在见人）；刘贵年(?)（为中在见人） | W40: 刘立忠(?) | X40: 无官印；立字人及中见、代笔各钤小私章 | Y40: 增找之后任凭买主前去收租管业，卖者再无言增言找 | AA40: 托原中刘谕向买主增找，属卖后加找；各签名处钤有朱色私章，较少见。 | AB40: 目录买主作'刘子珜'，契文似'刘子祥'；目录无日期，契为同治二年 | AC40: 中 | AD40: 原中名、为中人第二名及代笔名存疑 | AE40: 1 | AF40: Seller: 黃志林 [HUANG Zhilin] -- Buyer: 劉子珜 [LIU Ziyang] -- Personal | AH40: 查看原件 | AI40: 31735066267448
A41: 1 | B41: 39 | C41: 找贴／凑断 | D41: 找贴契／贴尽契（会贴尽契） | E41: 4 咸同光宣（1851-1911） | F41: 同治 | G41: 同治叁年叁月 日 | H41: 1864 | I41: 杨门郑氏娇姑 | J41: 女 | K41: 寡妇（故夫杨大松），以夫阄分己业民田立契；知契养仔 | L41: □（疑为夫胞叔浩士房男大钧等，或张利禧） | M41: 古田县 | N41: 土名东洋及溪井仔 | O41: 田 | P41: 田 | Q41: 民田壹号，土名东洋及溪井仔，租石钱粮俱载原典契 | R41: 会贴尽出价银伍拾两正；外中用银壹两五钱正 | S41: 50 | T41: 银两 | U41: 法功江；张正平（劝谕中） | V41: 夫胞弟大桐（在见）；养仔（知契） | W41: 徐乾三 | X41: 契尾（古田县，布政司官印）；正契无官印 | Y41: 贴尽之后不得言赎言贴；原契约同治伍年冬取赎，逾限不得取赎 | Z41: ①会贴尽契：同治叁年叁月，杨门郑氏娇姑因故夫大松阄分民田出典后再贴尽，得价银伍拾两；②契尾：同治拾壹年叁月，布字叁千贰百拾肆号，右给古田县业户张利禧，载张利禧于咸丰四年买郑章世(?)春苗田壹号，坐落二十一都地方土名浴(?)叶油行门首，民田肆亩，价银壹百肆拾两，纳税银肆两贰钱 | AA41: 寡妇出名立契，田先典给本族，后多次转手再'会贴尽'；所附契尾与正契人名、年代不对应（业户张利禧，咸丰四年买田），可能是同一田的另一层交易记录。 | AB41: 目录买主作'郑淳氏'，图像未见此名；契尾业户为张利禧 | AC41: 低 | AD41: 正契草书潦草，承接人名、转售经过、知契人名多处无法确认；契尾土名'浴叶'及卖主名存疑 | AE41: 2 | AF41: Owner: 張利禧 [ZHANG Lixi] --Seller: 鄭嬌姑 [ZHENG Jiaogu] -- Buyer: 鄭淳氏 [ZHENGchunshi] -- Place: 福建省古田縣 [Fujian Sheng Gutian Xian] -- Government | AG41: 1864 to 1872 | AH41: 查看原件 | AI41: 31735066237359
A42: 1 | B42: 39A | C42: 契尾／验契 | D42: 契尾 | E42: 4 咸同光宣（1851-1911） | F42: 同治 | G42: 同治叁年捌月 日 | H42: 1864 | I42: 吴开扬 | J42: 男 | L42: 陈世旺 | M42: 闽县 | N42: 闽县 | O42: 屋／厝 | P42: 屋／厝 | Q42: 屋一所（坐落处字迹模糊） | R42: 用价银陆拾伍两；纳税银壹两玖钱伍分 | S42: 65 | T42: 银两 | X42: 布政司颁契尾，布字肆千壹百柒拾贰号，右给闽县业户陈世旺；钤闽县官印多枚，顶部骑缝号'闽字肆万□□' | AA42: 仅存契尾，税率按价银3%。 | AC42: 中 | AD42: 坐落地名不清 | AE42: 1 | AF42: Seller: 吳開揚 [WU Kaiyang] -- Buyer: 陳世旺 [CHEN Shiwang] -- Place: 福建省閩縣 [Fujian Sheng Min Xian] -- Government | AG42: 1864 | AH42: 查看原件 | AI42: 31735068223266
A43: 1 | B43: 40 | C43: 买卖（卖／卖断） | D43: 卖断契 | E43: 4 咸同光宣（1851-1911） | F43: 同治 | G43: 同治肆年拾贰月吉日 | H43: 1865 | I43: 僧德诠 | J43: 僧道 | K43: 承师祖遗下寺田面；因修理佛殿要用而卖；粮色立在草市都一甲僧德祖户下 | L43: 林（名空缺） | M43: 侯官县 | N43: 侯邑草市都马坑等处地方 | O43: 田面 | P43: 田面 | Q43: 寺田面叁号，计官丈贰亩叁分贰厘伍毛捌忽，年载面租谷肆百肆拾壹筋；计开：地字四区三百二十八号土名马路下下寺田、三百三十号土名马路下下寺田、三百四十七号土名墓路即井嘴下寺田，各载租谷 | R43: 镜银壹拾捌两正，库码足色 | S43: 18 | T43: 银两 | U43: 郑昌颐（中见）；林万斌（中见） | V43: 师弟德缘（在见）；师侄凤来（在见） | W43: 吴为相 | X43: 钤朱红方印两枚（疑为县印，红契） | Y43: 卖断，永断葛藤，永远为业；声明系祖遗，无原契缴付 | AA43: 寺僧以师徒传承关系出卖寺田，粮户仍以僧名立户；田号采用'地字四区某号'鱼鳞册式编号。 | AB43: 目录作1866，契为同治四年十二月（公历约1866年初） | AC43: 高 | AD43: 中见'林万斌'末字略存疑 | AE43: 1 | AF43: Seller: 德詮（僧人） [Dequan] -- Place: 福建省侯官縣 [Fujian Sheng Houguan Xian] -- Government | AG43: 1866 | AH43: 查看原件 | AI43: 31735066266267
A44: 1 | B44: 41 | C44: 买卖（卖／卖断） | D44: 卖断契 | E44: 4 咸同光宣（1851-1911） | F44: 同治 | G44: 同治伍年叁月吉日 | H44: 1866 | I44: 林春源 | J44: 男 | K44: 承父遗产 | L44: 王家（王元霭?） | M44: 闽县 | N44: 闽邑嘉崇里秋龙巷 | O44: 屋／厝 | P44: 屋＋地基／屋地 | Q44: 二柱破屋一直三堵＋残地一块（在王家店后）；四至：屋前至王家店、后至王家屋、左至李家屋、右至翰家屋；地前至翰家屋、后至王家屋 | R44: 足色镜银库砝壹拾弍两正 | S44: 12 | T44: 银两 | U44: 陈友梅 | V44: 堂叔长发（画圈）；堂弟春荣 | W44: 张东中 | X44: 无官印（白契） | Y44: 卖断，声明不得取赎、凑尽 | AA44: 契首'王'字抬头；地保一栏空缺；注明王姓在店后居住者出入皆由王家店内而行；'内涂遗一字'标记。与 Folder 48（王元霭）为同一交易后续。 | AC44: 高 | AE44: 1 | AF44: Seller: 林春源 [LIN Chunyuan] -- Place: 福建省閩邑 [Fujian Sheng Min Yi] -- Personal | AG44: 1866 | AH44: 查看原件 | AI44: 31735064607447
A45: 1 | B45: 42 | C45: 典当／胎借 | D45: 典契（拨缴典契） | E45: 4 咸同光宣（1851-1911） | F45: 同治 | G45: 同治伍年肆月吉日 | H45: 1866 | I45: 杨鹏超 | J45: 男 | K45: 承祖在日手置、阄分嗣父份下；知契祖妣薛氏、嗣母郭氏 | L45: 林家 | M45: 侯官县 | N45: 侯邑西关外草市都井边亭地方，土名大秧地 | O45: 田面 | P45: 田面 | Q45: 民田面壹号（地字□百号），中则田民池计官丈叁亩陆分，年共面租谷捌百伍拾筋；内拨出壹半，计应田壹亩伍分叁厘零，应面租谷肆百贰拾伍筋；粮色立在草市都柒甲杨绍标户下 | R45: 田价银贰拾玖两柒钱伍分正，纹广 | S45: 29.75 | T45: 银两 | U45: 林万开（中友） | V45: 知契祖妣薛氏；嗣母郭氏；胞伯敦志（在见） | W45: 堂伯敦琏(?) | X45: 契面钤县印（红契）；附布政司契尾（同治十年） | Y45: 陆年为限，限满听备价照契面银两取赎；约赎田之日每两银折钱□伍拾文 | Z45: ①拨缴典契：同治伍年肆月，杨鹏超将承祖阄分民田面半号拨出缴典与林家，价银贰拾玖两柒钱伍分；②契尾：同治拾年叁月，布字壹万伍千陆百陆拾伍号，右给侯官县业户林□，载林家典杨鹏超田，价银贰拾玖两柒钱伍分，纳税银捌钱玖分贰厘伍毛 | AA45: 林万开此处为中友，而在 Folder 54/57/58 中为买主，显示其由中人转为置产者的角色；原契因只拨半号难以缴付。 | AB45: 目录注'出租'，实为典契 | AC45: 中 | AD45: 号数、折钱数、代笔名末字 | AE45: 2 | AF45: Seller: 楊鵬超（出租） [YANG Pengchao] -- Buyer: 林 [LIN] -- Place: 福建省侯官縣 [Fujian Sheng Houguan Xian] -- Government | AG45: 1866 to 1871 | AH45: 查看原件 | AI45: 31735064607835
A46: 1 | B46: 43 | C46: 契尾／验契 | D46: 契尾 | E46: 4 咸同光宣（1851-1911） | F46: 同治 | G46: 同治陆年六月 日 | H46: 1867 | I46: 倪应寿 | J46: 男 | L46: 刘景茂 | M46: 建阳县 | N46: 建阳县（坐落未填清） | O46: 田 | P46: 田 | Q46: 田（坐落栏字迹不清） | R46: 用价银壹拾壹两；纳税银□ | S46: 11 | T46: 银两 | X46: 福建布政使司契尾，布字贰千壹百贰拾伍号，右给建阳县业户刘景茂；骑缝号'建字□千玖佰'；多枚官印 | AA46: 闽北建阳县契尾，与本批其他福州契区域不同。 | AC46: 中 | AD46: 价银'壹拾壹两'及纳税额、坐落均存疑；骑缝号模糊 | AE46: 1 | AF46: Owner: 劉景茂 [LIU Jingmao] -- Place: 福建省建陽縣 [Fujian Sheng Jianyang Xian] -- Government | AG46: 1867 | AH46: 查看原件 | AI46: 31735066237565
A47: 1 | B47: 44 | C47: 典＋找贴 | D47: 典契＋找贴契／贴尽契（尽断契） | E47: 4 咸同光宣（1851-1911） | F47: 同治 | G47: 同治柒年拾贰月（典）；同治拾贰年拾贰月（尽断） | H47: 1868 | I47: 林邦端 | J47: 男 | K47: 自己阄分原祖手置买断得黄家根面全田；知契母王氏 | L47: 程利欲、程利霖 | M47: 闽侯县 | N47: 三十五都土名和尚湾楼里垅（龙）地方 | O47: 田（根面全） | P47: 田（根面全） | Q47: 根面全屯田壹号，计田捌分零；又买断得廖田垅地方上下塅共田壹亩叁分零；粮色立在廿伍都林可琏户下 | R47: 典价银伍拾陆两正纹广；尽断出满价钱贰仟文(?)；民国契单定价银肆拾玖元 | S47: 56 | T47: 银两 | U47: 堂弟邦勋（中见）；族侄兴梅（中人） | V47: 知契母王氏；胞侄巨桂（在见）；胞侄巨兰（在见） | W47: 族侄巨槛（典契代字）；尽断契自笔 | X47: 两契均钤闽(?)县印（红契）；民国五年福建财政厅卖断契单，印花税票贰分，注册李昭、缮契骆茂官、校叶煊 | Y47: 典契伍年为限，取赎每两银折铜钱捌百伍拾文；尽断后永不得言尽言赎 | Z47: ①典契：同治柒年拾贰月，林邦端将根面全田典与程利欲，价银伍拾陆两，伍年为限；②尽断契：同治拾贰年拾贰月，林邦端再向程利欲、程利霖尽断，得钱贰仟文(?)；③福建财政厅卖断契单：中华民国五年十二月十五日，税字第一万一千一百九号，右给闽侯县业户程利欲、程利霖，田地壹亩叁分，价银肆拾玖元，纳税银贰元，粘贴印花税票 | AA47: 一田先典后尽断、再由民国换契单确认，跨1868-1916；并缴黄有美卖断契、林崇和卖断契、林可翘典尽断契共九纸上手契。 | AC47: 中 | AD47: 尽断价钱数字、田亩数存疑 | AE47: 3 | AF47: Seller: 林邦端 [LIN Bangduan] -- Buyer: 程利欲 [Cheng Liyu] and 程利霖[Cheng Lilin] -- Place: 福建省閩侯縣 [Fujian Sheng Minhou Xian] -- Government | AG47: 1868 to 1916 | AH47: 查看原件 | AI47: 31735066266473
A48: 1 | B48: 45 | C48: 买卖（卖／卖断） | D48: 卖断契（卖断皮骨山契） | E48: 4 咸同光宣（1851-1911） | F48: 同治 | G48: 同治捌年十二月 日 | H48: 1869 | I48: 黄奶寿 | J48: 男 | K48: 承祖遗下；因父身故、胞弟年幼，自行出卖 | L48: 程金宝 | M48: 不详 | N48: 任得里虞(?)墩，土名大田仔 | O48: 山林 | P48: 山／山林 | Q48: 皮骨杉木竹山壹片；四至：上至大路、下至田、左至吴宅山分水为界、右至杨宅山分水为界 | R48: 时直契价洋银捌两正足 | S48: 8 | T48: 银元／大洋 | U48: 朱(?)远奴（为中人）；张炳孙（说谕人） | V48: 伯奴老（在见人） | W48: 的笔（黄奶寿自笔） | X48: 无官印（白契） | Y48: 卖断，任从买主前去砍削畜留管业，不敢阻执 | AA48: 契内批明：此山所有契据与卖主别山全契未便缴付，日后寻出不堪行用；注有'山'字二个、'契'字一个。买主程金宝亦见于 Folder 36（张华富卖茶山，1862），疑同一置产人。 | AB48: 目录未列买主，契文为程金宝 | AC48: 中 | AD48: 坐落'虞墩'、为中人名首字存疑 | AE48: 1 | AF48: Seller: 黃奶壽 [HUANG Naishou] -- Personal | AG48: 1869 | AH48: 查看原件 | AI48: 31735066267737
A49: 1 | B49: 46 | C49: 买卖（卖／卖断） | D49: 卖契（直根批，卖田根） | E49: 4 咸同光宣（1851-1911） | F49: 同治 | G49: 同治八年十二月 日 | H49: 1869 | I49: 苏辉煌(?) | J49: 男 | K49: 承父手置民田；自称根主苏作标之'宗弟'；知根胞弟辉烺，在见出嗣弟辉灼 | L49: 苏作标（根主） | M49: 屏南县 | N49: 本处土名俗叫乌石后半岭及四垅 | O49: 田根 | P49: 田根 | Q49: 民田三号，共该租叁石，官正折实田共贰亩四分；但此田大祖前年间出典在根主苏作标处，今将田根退还根主 | R49: 时值根价钱肆拾壹千陆百文正 | S49: 41600 | T49: 铜钱 | U49: 宗弟士治 | V49: 胞弟辉烺（知根）；出嗣弟辉灼（在见） | X49: 契面钤朱红方印两枚（疑为县印，红契） | Y49: 退根归根主，听其子孙前去召佃耕作管业 | Z49: 第二页为同一契纸背面／反印：墨色淡且反向，另有后人批注'此契作标……典契加价……花边……计□元'（字迹潦草） | AA49: 直根批'是将田根直接退卖给原根主，属闽东特有的田根/田面分离文书；同宗之间交易。 | AB49: 目录卖主作'?辉煌'，契只写'宗弟辉煌'，姓氏按宗弟关系推为苏 | AC49: 中 | AD49: 第二页反印文字基本无法辨读；代笔未见 | AE49: 2 | AF49: Seller: ?輝煌 [? Huihuang] -- Buyer: 蘇坐標 [SU Zuobiao] -- Place: 福建省屏南縣 [Fujian Sheng Pingnan Xian] -- Government | AG49: 1869 | AH49: 查看原件 | AI49: 31735066237391
A50: 1 | B50: 47 | C50: 典当／胎借 | D50: 卖断契（卖断山契）＋当山契＋契尾 | E50: 4 咸同光宣（1851-1911） | F50: 同治 | G50: 同治八年十二月 日 | H50: 1869 | I50: 黄象智（仝叔景元、仝弟象炬） | J50: 男 | K50: 叔侄兄弟同立，祖手置产业 | L50: 刘贞文兄弟 | M50: 古田县 | N50: 坐址浙山村地方，土名俗叫小溪南山垅大岗 | O50: 山林 | P50: 山／山林 | Q50: 山场壹所；四至：上至岭顶(?)、下至田、左至何家山、右至利明山 | R50: 时值山价钱肆仟文正，外加钱五百文 | S50: 4500 | T50: 铜钱 | U50: 王清香（钤'王清香记'戳） | V50: 堂叔景运（在见）；仝弟象坤；仝叔景榕；仝弟象蜂 | W50: 执笔叔景元 | X50: 卖断契钤朱红官印（红契）；当山契无官印；契尾为布政司官颁，古田县印 | Y50: 卖断，永远管业，不敢异言；当山契约次年本利送还，逾期由当主管业 | Z50: ①卖断山契：同治八年十二月，黄象智仝叔景元、仝弟象炬将祖手置山场卖断与刘贞文兄弟，价钱肆仟文，外加钱五百文；②当山契：光绪拾捌年十二月，刘贞文将该山场（土名小溪大岗）当与本乡陆元盛，借钱肆仟文，利息加贰伍分，限次年十二月本利送还；③契尾：光绪贰拾伍年拾月，古田县业户阮承苑，买刘复(?)西龄、阮大厚等民田三号（本处土名山垅仔、大路下段、垄里境等段，共田叁亩贰分），价银壹百叁拾壹两零陆分，纳税银叁两玖钱叁分壹厘捌毫 | AA50: 同一山场先卖断给刘贞文，23年后刘又将其出当；中人王清香使用'王清香记'木戳。附契尾的业户阮承苑与前两契人物不对应，属另一宗田产交易。 | AB50: 目录列阮承苑为业主，实为所附契尾业户；与两契山场非同一标的 | AC50: 中 | AD50: 四至'上至岭顶'、契尾卖主名'刘复西龄'存疑 | AE50: 3 | AF50: Owner: 阮承苑 [RUAN Chengyuan] --Seller: 黃象智 [HUANG Xiangzhi] and 劉貞文[LIU Zhenwen] -- Buyer: 劉貞文 [ LIU Zhenwen] and 陸元盛 [LU Yuansheng]-- Place: 福建省古田縣 [Fujian Sheng Gutian Xian] -- Government | AG50: 1869 to 1899 | AH50: 查看原件 | AI50: 31735066268040
A51: 1 | B51: 48 | C51: 买卖（卖／卖断） | D51: 卖断契 | E51: 4 咸同光宣（1851-1911） | F51: 同治 | G51: 同治捌年拾贰月吉日 | H51: 1869 | I51: 林春源 | J51: 男 | K51: 承父遗阄分 | L51: 王元霭 | M51: 闽县 | N51: 闽邑文山铺秋龙巷地方 | O51: 屋／厝 | P51: 屋／厝 | Q51: 坐西向东厝屋壹直五柱叁堵，计直深叁丈捌尺，横阔壹丈柒尺；后右边毗连披屋壹堵；共计伍堵；四至：前至王家店、后至王家屋、左至韩家屋、右至李家屋，上至椽桷砖瓦、下至磉石地基 | R51: 屋价足色库砝银叁拾两正 | S51: 30 | T51: 银两 | U51: 陈友梅（中友） | V51: 堂叔长发（在见）；堂弟春荣（在见） | W51: 李祖谦 | X51: 清代县印（红契）；民国二年卖断契单；民国十五年验契戳；民国十七年验税契证（印花税票）；福州市政府验讫戳 | Y51: 卖断，不得言赎言凑言尽 | Z51: ①卖断契：同治捌年拾贰月，林春源卖断屋与王元霭，价银叁拾两；契面另贴民国印花税票两枚，并盖福州市政府'验讫'紫色戳（编号17438/18438，民国卅七、卅八年及1956年字样）；②卖断契单：福建国税厅筹备处颁，中华民国贰年拾壹月，买林春源厝屋五柱壹座，坐落闽侯县文山铺，原价银叁拾两，证陈友梅，纸价壹元；另有民国十五年八月财政厅闽侯验契朱戳；③验税契证：福建财政厅颁，中华民国十七年□月十五日，新字第□号，右给业户王元霭，产价肆拾肆(?)元，纸价壹元伍角，注册费壹角，附加教育费贰角 | AA51: 与 Folder 41（同治五年林春源卖破屋及残地与王家）为同一卖主、同一买主、同一中友陈友梅和在见人长发、春荣，地点同为秋龙巷，可见王家三年间逐步收购邻屋。注明此屋出入俱由王家店内通行。 | AC51: 中 | AD51: 民国十七年验税契证产价及号数；市政府戳记年份 | AE51: 3 | AF51: Owner: 王元靄 [WANG Yuanai] --Seller: 林春源 [LIN Chunyuan] -- Buyer: 王元靄 [WANG Yuanai] -- Place: 福建省閩侯縣 [Fujian Sheng Minhou Xian] -- Government | AG51: 1869 to 1928 | AH51: 查看原件 | AI51: 31735066237573
A52: 1 | B52: 49 | C52: 典当／胎借 | D52: 典契 | E52: 4 咸同光宣（1851-1911） | F52: 同治 | G52: 同治玖年五月吉日 | H52: 1870 | I52: 张昌畅 | J52: 男 | K52: 因官事无钱使用，将父手阄分己份民田出典 | L52: 邦昔（张邦昔?） | M52: 屏南县 | N52: 本处草坂 | O52: 田 | P52: 田 | Q52: 民田壹号，坐址本处草坂，田该粮捌分正；四至：上至山、下至溪、左至大成田、右至大成田 | R52: 出价银贰拾伍两正，契立银收足讫，无挂分厘 | S52: 25 | T52: 银两 | U52: 胞孙张大都（为中） | X52: 契面钤朱红菱形官印多枚（红契）；附古田县契尾（布政司印） | Y52: 典期内邦昔管业收租并津助完纳钱粮；年限随年备价赎回，无力者任凭管业收租 | Z52: ①典契：同治玖年五月，张昌畅将父手阄分民田典与邦昔，价银贰拾伍两；②契尾：光绪叁拾叁年拾月，布字壹万玖百玖拾贰号，右给古田县业户张兰芬，载张兰芬于光绪叁拾□年买断林智(?)等民田，价银伍拾捌两，纳税银壹两柒钱肆分 | AA52: 出典原因明写'因官事无钱使用'，较少见；中人以'胞孙'身份出现，可见出典人年长。所附光绪契尾业户张兰芬与典契双方不同，似为同族后续交易。 | AB52: 目录列张兰芬为业主，实为所附契尾业户；地点兼列屏南、古田，契尾为古田县 | AC52: 中 | AD52: 坐址'草坂'县属未明（按目录作屏南）；契尾卖主名不清 | AE52: 2 | AF52: Owner: 張蘭芬 [ZHANG Lanfen] --Seller: 張昌暢 [ZHANG Changchang] -- Buyer: （張）邦昔 [(ZHANG) Bangxi] -- Place: 福建省屏南縣和古田縣 [Fujian Sheng Pingnan Xian and Gutian Xian] -- Government | AG52: 1870 to 1907 | AH52: 查看原件 | AI52: 31735066237342
A53: 1 | B53: 50 | C53: 买卖（卖／卖断） | D53: 卖断契（卖断根面全田契） | E53: 4 咸同光宣（1851-1911） | F53: 同治 | G53: 同治拾年拾壹月吉日 | H53: 1871 | I53: 方元慈 | J53: 男 | K53: 承父阄书份下；卖与胞兄；在见母亲许氏、嫂赵氏 | L53: 方潮涛（兄） | M53: 侯官县 | N53: 侯邑三十九都地方，土名圳仔垅 | O53: 田（根面全） | P53: 田（根面全） | Q53: 根面全田叁坵(?)，大小叁坵，官丈贰亩贰分零；粮挂三十九都壹甲方道户下、又挂三十八都四图八甲方福昌户下、又挂三十八都壹图六甲方永平户下 | R53: 田价钱壹百壹拾伍千文正 | S53: 115000 | T53: 铜钱 | U53: 族叔浓官 | V53: 母亲许氏（在见）；嫂赵氏（在见） | W53: 族侄亨霖 | X53: 契面钤闽侯县验契朱印，贴民国印花税票；民国二年卖断契单；1930年代闽侯县已税契验契证（县府印、区长章） | Y53: 卖断，永断葛藤，向后不得别生枝节 | Z53: ①卖断根面全田契：同治拾年拾壹月，方元慈将承父阄书份下根面全田卖断与兄方潮涛，价钱壹百壹拾伍千文；契面贴民国印花税票；②卖断契单：福建国税厅筹备处颁，中华民国贰年拾壹月，验字第四万二千四百六十八(?)号，右给闽侯县业户方潮涛，买方元慈田地贰亩贰分零，坐落闽侯县三十九都圳仔垅，原价银壹百壹拾伍元，证方浓官，纸价壹元贰角，钤'东水汤井验契北督催处'戳；③闽侯县已税契验契证：福建省政府财政厅颁，业主潮涛(?)，住址莲峰(?)，田，坐落圳仔垅，面积二亩二分○，产价一百一十五千文，出卖主元慈，中证人浓官，立契同治十年十一月吉日，中华民国廿四(?)年六月，第49740号 | AA53: 兄弟间卖断，粮额分挂于三个不同的方姓户名；原契因洪水浸湿朽烂无可缴付。民国契单把'壹百壹拾伍千文'直接写作'壹百壹拾伍元'。 | AB53: 目录作1871-1913，但另有1930年代（民国廿四年?）验契证 | AC53: 中 | AD53: 验契证年份与业主住址为铅笔草书；契单号数存疑 | AE53: 4 | AF53: Seller: 方元慈 [FANG Yuanci] -- Buyer: 方潮濤 [FANG Chaotao] -- Place: 福建省閩侯縣 [Fujian Sheng Minhou Xian] -- Government | AG53: 1871 to 1913 | AH53: 查看原件 | AI53: 31735064607587
A54: 2 | B54: 51 | C54: 买卖（卖／卖断） | D54: 卖断契（卖断皮骨杂木茶山契） | E54: 4 咸同光宣（1851-1911） | F54: 同治 | G54: 同治玖年四月 日 | H54: 1870 | I54: 程姑仔 | J54: 男 | K54: 承祖遗下；因父身亡故、自身年幼，缺银使用；知契妈郑氏 | L54: 血叔翁金宝（程金宝） | M54: 不详 | N54: 由里上溪后土名畲乐重；又一片坐落任里虞墩土名石岭后 | O54: 山林 | P54: 山／山林 | Q54: 杂木杉松茶山贰片：一片上至岗顶、下至水堪、左至张宅山合水为界、右至连宅山分水为界；又一片上至岗顶、下至田、左至张宅山合水为界、右至张宅山分水为界 | R54: 时直断契价洋银拾贰两正足 | S54: 12 | T54: 银元／大洋 | U54: 张元寿（为中人）；张贵孙（说谕人） | V54: 朱仕明（在见人）；知契妈郑氏 | W54: 邦如(?)孙 | X54: 无官印（白契） | Y54: 卖断，任从买主前去栽插畜留管业，不敢阻执 | AA54: 卖与血叔程金宝，即 Folder 36、45 的同一买主，金宝在任里虞墩一带持续收购山林；同为'父身亡故、年幼'背景（与 Folder 45 黄奶寿相似）。契后有光绪二十七年批：石岭后山场界至以黄竹檬为界，'后张程两姓不得混争'，说明后来发生山界纠纷。 | AB54: 目录买主作'金宝'，契称'血叔翁金宝'，姓程 | AC54: 中 | AD54: 代笔名、畲乐重地名存疑 | AE54: 1 | AF54: Seller: 程姑仔 [CHENG Guzai] -- Buyer: 金寶 [JIN Bao] -- Personal | AG54: 1870 | AH54: 查看原件 | AI54: 31735066266317
A55: 2 | B55: 52 | C55: 典当／胎借 | D55: 典契 | E55: 4 咸同光宣（1851-1911） | F55: 同治 | G55: 同治拾壹年十二月 日 | H55: 1872 | I55: 陈裔煌（仝弟裔辉） | J55: 男 | K55: 承祖手有民田，兄弟同立 | L55: 郑璟（本墩郑处） | M55: 古田县 | N55: 本处地方土名俗叫棋盘座 | O55: 田 | P55: 田 | Q55: 民田壹号，该田贰亩伍分正，历年收租管业 | R55: 时值契价银肆拾柒两伍钱，纹广正 | S55: 47.5 | T55: 银两 | U55: 吴廷接 | V55: 堂兄裔森（在见）；仝弟裔辉 | W55: 甘兴业 | X55: 契面钤朱红方印及菱形印（红契） | Y55: 约伍年冬满足外任煌备办价银赎回，每两折钱捌百肆拾文；如无力任璟收租管业；钱粮推入郑家户内完纳 | AA55: 并缴原尽断契叁纸，共肆纸；批注'中用酒席俱与再照'。 | AB55: 目录作卖契（Seller/Buyer），实为典契 | AC55: 高 | AD55: 赎回折钱数'捌百肆拾文'略存疑 | AE55: 1 | AF55: Seller: 陳裔煌 [CHEN Yihuang] -- Buyer: 鄭璟 [ZHENG Jing] -- Place: 福建省古田縣 [Fujian Sheng Gutian Xian] -- Government | AG55: 1872 | AH55: 查看原件 | AI55: 31735066237383
A56: 2 | B56: 53 | C56: 契尾／验契 | D56: 契尾 | E56: 4 咸同光宣（1851-1911） | F56: 同治 | G56: 同治拾贰年玖月 日 | H56: 1873 | I56: 吴开成 | J56: 男 | L56: 陈（名不清） | M56: 闽县 | N56: 闽县（坐落残缺） | O56: 屋／厝 | P56: 屋／厝 | Q56: 买吴开成屋（坐落残缺） | R56: 用价银陆拾捌两(?)；纳税银□两□ | S56: 68 | T56: 银两 | X56: 布政司契尾，布字叁万肆百玖拾贰号，右给闽县业户陈□；骑缝号'闽字叁万肆千□□'；闽县官印多枚 | AA56: 契尾上半部严重虫蛀火烧残缺。与 Folder 39A（同治三年吴开扬卖屋给陈世旺）同为吴开某卖与陈姓、闽县，疑为同一家族先后出售房产。 | AC56: 低 | AD56: 价银、税额及业户名均因残损难辨 | AE56: 1 | AF56: Seller: 吳開成 [WU Kaicheng] -- Buyer: 陳 [CHEN] -- Place: 福建省閩縣 [Fujian Sheng Min Xian] -- Government | AG56: 1873 | AH56: 查看原件 | AI56: 31735066266424
A57: 2 | B57: 54 | C57: 买卖（卖／卖断） | D57: 卖断契（卖断根面全民田契） | E57: 4 咸同光宣（1851-1911） | F57: 光绪 | G57: 光绪元年拾贰月 日 | H57: 1876 | I57: 林应香 | J57: 男 | K57: 有手置根面全民田数号 | L57: 族兄林万开 | M57: 侯官县 | N57: 侯邑西关外草市都马坑地方，土名马路下、井嘴等处 | O57: 田（根面全） | P57: 田（根面全）＋池塘 | Q57: 根面全民田：册载地字四区叁百贰拾捌号官丈陆分贰厘；又叁百叁拾号官丈叁分；大小贰坵田头井仔壹口、园仔壹块；又土名井嘴，册载地字四区叁百肆拾柒号官丈壹亩叁分；以上三号共计官丈贰亩叁分贰厘伍毛捌忽；粮色立在草市都壹甲□□户下 | R57: 田价钱壹百零捌千文 | S57: 108000 | T57: 铜钱 | U57: 陈春雷(?) | V57: 叔必祥（在见） | W57: 吴祥麟 | X57: 契面钤朱红大方印两枚（县印，红契）；另有'西湖区'及陈姓（陈泉龙?）后期戳记、铅笔编号 | Y57: 卖断，永断葛藤，不敢别生枝节 | AA57: 地号（地字四区328、330、347号）、亩数（贰亩叁分贰厘伍毛捌忽）与 Folder 40 僧德诠卖出的寺田面完全一致，说明1865年林姓买得寺田面后，1875年由林应香卖断与族兄林万开；并缴杨能燮原典契、陈朝科原典、井嘴根契、尽断契等共七纸。 | AB57: 目录作1875，契为光绪元年十二月（公历约1876年初）；目录地点作闽侯县，契文为侯邑 | AC57: 中 | AD57: 草书较重，中人名、粮户名、上手契人名存疑 | AE57: 1 | AF57: Seller: 林應香 [LIN Yingxiang] -- Buyer: 林萬開 [LIN Wankai] -- Place: 福建省閩侯縣 [Fujian Sheng Minhou Xian] -- Government | AG57: 1875 | AH57: 查看原件 | AI57: 31735064607785
A58: 2 | B58: 55 | C58: 买卖（卖／卖断） | D58: 卖断契（杜卖田皮骨契字） | E58: 4 咸同光宣（1851-1911） | F58: 光绪 | G58: 光绪二年丙子十二月(?)廿七日 | H58: 1877 | I58: 禄中 | J58: 男 | K58: 承父分阄下禾田；因少银使用；在堂母氏苏 | L58: 本家吉昌兄 | M58: 永安县 | N58: 土名下屋仔虎形地堂下塘仔 | O58: 田 | P58: 田 | Q58: 禾田壹坵，田皮骨一并杜卖；载本邑民米陆合 | R58: 尽骨价银壹拾柒员正（并带饭食花押酒席一应在内） | S58: 17 | T58: 银元／大洋 | V58: 在堂母氏苏 | W58: 海中（在场见代笔人） | X58: 契面钤朱红方印两枚（疑为县印，红契） | Y58: 杜卖，价尽，永无收赎 | AA58: 闽西北用语'田皮骨'、'员'计银元，与福州契式明显不同；声明'不是负债准折'。纸张虫蛀严重。 | AB58: 目录作1876，契为光绪二年十二月（公历约1877年初）；契中未写县名，永安县据目录 | AC58: 中 | AD58: 月份'十二月'及县属存疑 | AE58: 1 | AF58: Seller: 祿中 [Luzhong] -- Place: 福建省永安縣 [Fujian Sheng Yongan Xian] -- Government | AG58: 1876 | AH58: 查看原件 | AI58: 31735064607520
A59: 2 | B59: 56 | C59: 买卖（卖／卖断） | D59: 卖断契（尽根断卖契） | E59: 4 咸同光宣（1851-1911） | F59: 光绪 | G59: 光绪己卯伍年贰月 日 | H59: 1879 | I59: 康宗瑞 | J59: 男 | K59: 有自己手置民园 | L59: 陈连孙 | M59: 不详 | N59: 坐在庵后，落侄能干黄□边；南大云字号 | O59: 园 | P59: 园 | Q59: 民园壹段，计额柒分正，南大云字号载在官圻（东西南北四至遍知）；粮米图冬户下，除割过收入陈连孙户下 | R59: 实价九五成色银念拾壹两广戥正 | S59: 21 | T59: 银两 | U59: 庄世宝（中见人） | W59: 庄光耀 | X59: 无官印（白契）；左上有墨书圆戳'合契(?)' | Y59: 尽根断卖，后贵亦无敢找敢赎 | AA59: 园地以'字号'登记并写明粮米过割，可能出自闽南（庄姓、'念拾'用法）；文字为方言化草书。 | AC59: 中 | AD59: 坐落人名、字号、粮户名不清 | AE59: 1 | AF59: Seller: 康宗瑞 [KANG Zongrui] -- Buyer: 陳連孫 [CHEN Liansun] -- Personal | AG59: 1879 | AH59: 查看原件 | AI59: 31735066266648
A60: 2 | B60: 57 | C60: 买卖（卖／卖断） | D60: 卖断契（卖断田根契） | E60: 4 咸同光宣（1851-1911） | F60: 光绪 | G60: 光绪柒年拾贰月 日 | H60: 1882 | I60: 林春发 | J60: 男 | K60: 有手置民田根 | L60: 族叔林万开 | M60: 侯官县 | N60: 侯邑西关外白龙坛路地方，土名鲫鱼坵、牛头长坵等 | O60: 田根 | P60: 田根＋池塘 | Q60: 民田根数号，大小三坵、池壹口，共四坵，计官丈贰亩五分零；年纳面主王家早晚租谷叁百五十筋平秤 | R60: 价钱壹百壹拾千文 | S60: 110000 | T60: 铜钱 | U60: 杨宗盛 | V60: 弟春辉（在见） | W60: 陈□华(?) | X60: 契面钤朱红县印（红契）及菱形印；另有后期'王三?'墨书大字及红色戳记、编号 | Y60: 卖断，永断葛藤，不敢别生枝节 | AA60: 地块（白龙坛路鲫鱼坵，2.5亩，纳面主王家租谷350斤）与 Folder 37（同治元年杨兆通典与林家）同一田根；并缴杨能锋尽断契三纸，可见杨姓→林春发→族叔林万开的流转。 | AB60: 目录作1881，契为光绪七年十二月（公历约1882年初） | AC60: 中 | AD60: 代笔人名不清 | AE60: 1 | AF60: Seller: 林春發 [LIN Chunfa] -- Buyer: 林萬開 [LIN Wankai] -- Place: 福建省閩侯縣 [Fujian Sheng Minhou Xian] -- Government | AG60: 1881 | AH60: 查看原件 | AI60: 31735064607801
A61: 2 | B61: 58 | C61: 典当／胎借 | D61: 典契（拨典田面契） | E61: 4 咸同光宣（1851-1911） | F61: 光绪 | G61: 光绪拾年叁月吉日 | H61: 1884 | I61: 林秋溥 | J61: 男 | K61: 原自己典得何德兴民田面数号，今拨出转典 | L61: 堂兄林万开 | M61: 侯官县 | N61: 侯邑西关外三十八都马坑白龙地方，土名白龙东洋大塍边、水流坵、圆坵等处 | O61: 田面 | P61: 田面 | Q61: 拨出伍号：上中下则田计官丈肆亩捌分零，年载租谷捌百陆拾筋；粮色立在本都二图六甲何德兴户下；计开日字壹区129号大塍边、302号白龙上田、379号水流坵、382号白龙上田、日字十区411号圆坵等，佃户林万齐、李捷荣等 | R61: 田面价镜银肆拾肆两正，大锭库码 | S61: 44 | T61: 银两 | U61: 王有才（中友） | V61: 弟万拱（在见）；弟万叙(?) | W61: 侄荣阳 | X61: 契面钤方形官印（县印，红契）；另有'明并卖与洋人如……'红色长方戳（字迹部分可辨） | Y61: 照凭契面银两取赎，买主亦不得执留；倘原主取赎不拘年限 | AA61: 契面盖有禁止将田产'卖与洋人'一类的红色戳记，值得核对全文；何家原契与别业相连未便缴付。林万开是本批多件的买主/中人（Folder 42、54、57、58）。契末大书'大熟'。 | AB61: 目录作卖契（Seller），实为拨典契 | AC61: 中 | AD61: 红色戳记全文、在见人第二名不清 | AE61: 1 | AF61: Seller: 林秋溥 [LIN Qiupu] -- Buyer: 林萬開 [LIN Wankai] -- Place: 福建省侯官縣 [Fujian Sheng Houguan Xian] -- Government | AG61: 1884 | AH61: 查看原件 | AI61: 31735064607751
A62: 2 | B62: 59 | C62: 典当／胎借 | D62: 典契 | E62: 4 咸同光宣（1851-1911） | F62: 光绪 | G62: 光绪拾年拾月吉日 | H62: 1884 | I62: 林万利 | J62: 男 | K62: 原承父在日阄分己份下田面；所典为其应分壹半 | L62: 官方（契文作'典与八□官庆（?）为业'，'官'字抬头） | M62: 侯官县 | N62: 侯邑西关外草市都井边亭地方，土名大秧地 | O62: 田面 | P62: 田面 | Q62: 民田面壹号，册载地字弍百号，中则田，计官丈叁亩陆厘壹毫壹丝，年共面租谷捌百伍拾筋；万利应分壹半，该田壹亩伍分叁厘伍丝伍忽，面租谷肆百弍拾伍筋；粮色立在草市都柒甲林志户下，年应完粮银壹钱弍分弍厘柒毫、米壹升柒合伍勺 | R62: 典出田面价银壹拾两正（纹广） | S62: 10 | T62: 银两 | U62: 堂兄万顺；堂侄可良；陈金槐 | V62: 胞叔昌意（在见）；堂兄万斌（在见） | W62: 林万利自笔 | X62: 契面及骑缝钤红色方形官印（印文似'侯官县印'，?） | Y62: 典期三年为限，限满之日备价照契面银两（每两银折铜钱票捌百伍拾文）取赎，赎期定冬至；未赎仍照旧管业 | AA62: 契内说明并缴杨鹏起换缴典契壹纸、蔡世端尽契壹纸、税司单壹纸共成叁纸；上手原契并断契因半号别业相连不便缴付。左上大字'大吉（?）'。与同批 31735066266275（光绪十二年侯官县契尾，买林万利田，价银壹拾两）为同一交易的税契。 | AB62: 目录作卖契（Seller/Buyer），实为典田面契；目录日期1884相符 | AC62: 中 | AD62: 承典方名称'八□官庆'字形不确定；'大吉'字形；官印印文模糊 | AE62: 1 | AF62: Seller: 林萬利 [LIN Wanli] -- Buyer: 官方政府 [Government] -- Place: 福建省侯官縣 [Fujian Sheng Houguan Xian] -- Government | AG62: 1884 | AH62: 查看原件 | AI62: 31735064607769
A63: 2 | B63: 60 | C63: 契尾／验契 | D63: 契尾 | E63: 4 咸同光宣（1851-1911） | F63: 光绪 | G63: 光绪拾弍年捌月 | H63: 1886 | J63: 不详 | K63: 契尾未载卖主姓名 | L63: 高恭地（业户） | M63: 福清县 | N63: 福清县高山市街 | O63: 店屋 | P63: 店屋 | Q63: 高山市街至莲店壹间 | R63: 用价银陆拾叁两捌钱玖分；税银壹两玖钱壹分陆厘柒毫 | S63: 63.89 | T63: 银两 | X63: 福建布政使司契尾，布字玖千叁百肆拾肆号；钤红色官印多方（福清县印?、布政使司印?） | AA63: 税银为价银的3%；契尾为刻印套印文书，附乾隆年间部议章程，边框龙纹。 | AC63: 中 | AD63: 至莲店'字形存疑；左边缘残缺，骑缝半字不可读 | AE63: 1 | AF63: Owner: 高恭地[GAO Gongdi] -- Place: 福建省福清縣[Fujian Sheng Fuqing Xian] -- Government | AG63: 1886 | AH63: 查看原件 | AI63: 31735064607413
A64: 2 | B64: 61 | C64: 契尾／验契 | D64: 契尾 | E64: 4 咸同光宣（1851-1911） | F64: 光绪 | G64: 光绪拾弍年叁月 | H64: 1886 | I64: 林万利 | J64: 男 | K64: 契尾作'业户□买林万利田'，业户名空白 | M64: 侯官县 | N64: 侯官县（坐落空白） | O64: 田 | P64: 田 | Q64: 林万利田（坐落、面积未填） | R64: 用价银壹拾两；纳税银叁钱 | S64: 10 | T64: 银两 | X64: 福建布政使司契尾，侯字玖千陆百弍拾肆号；钤侯官县印（红色方印多方及骑缝印） | AA64: 价银壹拾两与同批 31735064607769 林万利典田面契（光绪十年，典价银壹拾两）相符，应为该典契的税契契尾；税率3%。 | AB64: 目录作 Owner 林万利，实际林万利为出业人，业户（买主）姓名空白 | AC64: 中 | AD64: 业户及坐落处似空白未填 | AE64: 1 | AF64: Owner: 林萬利 [LIN Wanli] -- Place: 福建省侯官縣 [Fujian Sheng Houguan Xian] -- Government | AG64: 1886 | AH64: 查看原件 | AI64: 31735066266275
A65: 2 | B65: 62 | C65: 买卖（卖／卖断） | D65: 卖断契 | E65: 4 咸同光宣（1851-1911） | F65: 光绪 | G65: 光绪拾弍年拾壹月吉日 | H65: 1886 | I65: 王师礼 | J65: 男 | K65: 承父阄分份下；知契母陈氏，胞兄师义、胞弟师智在见 | L65: 许大华 | M65: 闽县 | N65: 闽邑嘉崇里下阵洋地方，土名倒楔（?）坵 | O65: 田根 | P65: 田根＋田面 | Q65: 民田根面全弍号，册载青字第弍区第十九号，中则田，计官丈弍亩捌分伍厘零；四至：东至浦、西至林家田、南至吴家田、北至浦；粮色挂在嘉崇里叁啚拾甲王士全户下 | R65: 卖断价银陆拾伍两正（纹广银） | S65: 65 | T65: 银两 | U65: 林天送 | V65: 陈氏（知契母）；胞兄师义（在见）；胞弟师智（在见） | W65: 黄杰（?） | X65: 原契为白契，民国二年经福建国税厅筹备处验契，契上钤筹备处红印及'验'字戳；附断卖契单（验字第69531号） | Y65: 卖断，日後不得言凑言赎 | Z65: ①光绪拾弍年拾壹月王师礼卖断田根面契（白契，後经验印）；②中华民国贰年拾壹月叁拾日福建国税厅筹备处'断卖契单'，验字第六万九千五百三一号，给业户许大华，原价银陆拾伍两、申银玖拾伍元，原契未税，依限呈验，收纸价壹元 | AA65: 根面全业一并卖断，买主可自管或召佃。契末小字注明上手老契因故不得缴付，并注此田水圳由本田东边出入。契单中证人仍记林天送，地名改属闽侯县。 | AC65: 中 | AD65: 代笔名'黄杰'、土名'倒楔坵'、契末小字附注数字存疑；申银数'玖拾伍元'存疑 | AE65: 2 | AF65: Seller: 王師禮 [WANG Shili] -- Buyer: 許大華 [XU Dahua] -- Place: 福建省閩侯縣 [Fujian Sheng Minhou Xian] -- Government | AG65: 1886 to 1913 | AH65: 查看原件 | AI65: 31735066267828
A66: 2 | B66: 63 | C66: 买卖（卖／卖断） | D66: 卖断契 | E66: 4 咸同光宣（1851-1911） | F66: 光绪 | G66: 光绪拾叁年叁月拾捌日 | H66: 1887 | I66: 王锦发 | J66: 男 | K66: 原祖遗阄分份下；知契母林氏，胞弟森发 | L66: 王锦枝（堂兄） | M66: 闽县 | N66: 闽邑横山铺秋龙社地方 | O66: 店屋 | P66: 店屋 | Q66: 肆柱店面右半爿，内门窗户扇、前搨板地棚一切俱全；前至官街，後至王清官屋，左边锦枝半爿店，右至何家店，上至椽桁砖瓦，下至廊石磉石地基 | R66: 价锭银柒拾伍两正，库砝大锭白足色足兑 | S66: 75 | T66: 银两 | U66: 林细弟 | V66: 林氏（知契母）；胞弟森发；堂兄俊发（在见）；堂兄永发（在见） | W66: 李逢铨 | X66: 无官印（白契） | Y66: 卖断，永断葛藤，永不敢言赎言凑言尽 | AA66: 堂兄弟之间买卖祖遗店屋另一半，买主已拥有左半爿；契内并缴林春源典断契司单。左侧大书'为永保千秋'。地点秋龙与规范示例中林春源秋龙巷相近，林春源亦见於本契。 | AC66: 高 | AD66: 地陆'等个别字存疑 | AE66: 1 | AF66: Seller: 王錦發 [WANG Jinfa] -- Buyer: 王錦枝 [WANG Jinzhi] -- Place: 福建省閩縣 [Fujian Sheng Min Xian ] -- Personal | AG66: 1887 | AH66: 查看原件 | AI66: 31735064607470
A67: 2 | B67: 64 | C67: 典当／胎借 | D67: 典契 | E67: 4 咸同光宣（1851-1911） | F67: 光绪 | G67: 光绪拾叁年拾壹月吉日 | H67: 1887 | I67: 陈必清 | J67: 男 | K67: 原承阄分份下本座墙後空地自己起盖墙屋；全室中梁氏、长男锺祥、侄男应祥同署 | L67: 陈必泉 | M67: 闽县 | N67: 闽邑嘉崇里横街铺惠泽境茶叶街地方 | O67: 屋／厝 | P67: 屋 | Q67: 墙屋全座，伍柱肆榀排，四面风火墙，直深伍丈伍尺，并围墙、天井、水井、大厅、後厅、门窗户扇等一切；四至详载 | R67: 典出墙屋价镜（?）银弍百两正，库砝大锭白足色足兑 | S67: 200 | T67: 银两 | U67: 刘志潮；吕光达 | V67: 梁氏（全室中）；长男锺祥；侄男应祥；何鸿壁（?）（在见） | W67: 方忠恭（?） | X67: 契面钤红色菱形大印；右上有'验'字戳及民国时期批记 | Y67: 伍年为限，限满备契面银两照原价赎回；另加修理银肆两；如逾限未赎可展限三年以酬土木石之费 | AA67: 契内并缴吴开杨典契司单弍纸、吴开成断契司单弍纸共成伍纸。左侧小字批注：民国陆年拾月间将前进库屋全座凑卖断与吴家，又批残契遗失等语。左侧大书'财丁贵大发'；另有红色长方戳'该业已经登记……上手契'。 | AB67: 目录作卖契（Seller/Buyer），实为典契 | AC67: 中 | AD67: 代笔、在见人名及左侧小字批注多字存疑 | AE67: 1 | AF67: Seller: 陳必清 [CHEN Biqing] -- Buyer: 陳必泉 [CHEN Biquan] -- Place: 福建省閩縣 [Fujian Sheng Min Xian] -- Government | AG67: 1887 | AH67: 查看原件 | AI67: 31735066267893
A68: 2 | B68: 65 | C68: 租佃／欠租 | D68: 领票／欠租字 | E68: 4 咸同光宣（1851-1911） | F68: 光绪 | G68: 光绪拾叁年冬月／光绪拾叁年五月 | H68: 1887 | I68: 有澧（叔） | J68: 男 | K68: 立收字人，收侄所纳苗米 | L68: 道奎（侄） | M68: 不详 | O68: 其他／非土地 | P68: 其他（苗米收据） | Q68: 苗米壹斗正 | R68: 苗米壹斗正（每纸） | S68: 1 | T68: 米谷 | X68: 无官印 | Z68: ①光绪拾叁年冬月收字：叔有澧收侄道奎纳本年份苗米壹斗；②光绪拾叁年五月收字：叔有澧收侄道奎纳拾四年份苗米壹斗 | AA68: 两张亲属间的苗米收据，简短草书；左侧另有小字批记'收来本年份收了'之类。 | AC68: 中 | AD68: 道奎'、'有澧'、'处理'等字草书存疑；左侧小字未能确认 | AE68: 2 | AF68: Place: unknown -- Personal | AG68: 1887 | AH68: 查看原件 | AI68: 31735066237698
A69: 2 | B69: 66 | C69: 典当／胎借 | D69: 典契 | E69: 4 咸同光宣（1851-1911） | F69: 光绪 | G69: 光绪拾肆年十一月日 | H69: 1888 | I69: 陆元规 | J69: 男 | K69: 父手遗置建屯田；胞叔国华、国器在见 | L69: 陆元赐（堂兄） | M69: 古田县 | N69: 嵩（?）州溪里地方，土名俗叫万（?）壠 | O69: 田 | P69: 田 | Q69: 建屯田壹号计叁亩正，内抽出弍亩出典；粮在三十都陆元规户，至大造之年推入堂兄赐户内完纳 | R69: 典契价银叁拾陆两纹广正（赎时每两折钱捌百叁拾文算）；外中用笔资银共伍钱 | S69: 36 | T69: 银两 | U69: 胡振仁 | V69: 胞叔国华（在见）；胞叔国器（知见） | W69: 刘利辉 | X69: 原契白契；民国二年验契，粘连典按契单，钤福建国税厅筹备处红印 | Y69: 年限五冬满足，外任从元规备办典契价银赎回，每两折钱捌百叁拾文算 | Z69: ①中华民国贰年十一月福建国税厅筹备处'典按契单'，验字第弍万一千三百九九号（?），给业户陆元赐，记其於光绪十四年十一月典受陆元规建屯田弍亩，坐落古田县嵩（?）州溪里乌（?）壠地方，证人胡振仁，原价银□两申银叁拾元，收纸价壹元；②光绪拾肆年十一月陆元规立典契（白契，後与契单粘连） | AA69: 堂兄弟间典田；契内并缴尽契叁纸共肆纸，原契与别项相连难以折缴。契末另书'今领交阅上项典契价银叁拾陆两纹广正'。 | AB69: 目录作 Seller/Buyer（卖契），实为典契；日期1888–1913相符 | AC69: 中 | AD69: 地名'嵩州溪里''万壠''乌壠'字形存疑；契单号码存疑 | AE69: 2 | AF69: Seller: 陸元規 [LU Yuangui] -- Buyer: 陸元賜 [LU Yuanci] -- Place: 福建省古田縣 [Fujian Sheng Gutian Xian] -- Government | AG69: 1888 to 1913 | AH69: 查看原件 | AI69: 31735066266382
A70: 2 | B70: 67 | C70: 契尾／验契 | D70: 契尾 | E70: 4 咸同光宣（1851-1911） | F70: 光绪 | G70: 光绪拾叁年拾壹月 | H70: 1887 | I70: 林秋溥 | J70: 男 | K70: 契尾作'业户林万开买林秋溥田' | L70: 林万开 | M70: 侯官县 | N70: 侯官县三十八都 | O70: 田 | P70: 田 | Q70: 林秋溥田，坐落三十八都 | R70: 用价银肆拾肆两；纳税银壹两叁钱弍分 | S70: 44 | T70: 银两 | X70: 福建布政使司契尾，侯字壹万叁千拾陆号；钤侯官县印多方 | AA70: 税率3%。林万开与林万利（同批 Folder 59/61）似为同辈兄弟，林万利典契中列堂兄万顺、万斌；同属侯官县林氏。 | AB70: 目录作卖主林万开、买主林秋溥，契尾实为业户（买主）林万开买林秋溥田，买卖方向相反；目录年份1888，契尾为光绪十三年（1887） | AC70: 中 | AD70: 年份'拾叁'与月份字迹在左侧骑缝处较模糊 | AE70: 1 | AF70: Seller: 林萬開 [LIN Wankai] -- Buyer: 林秋溥 [LIN Qiupu] -- Place: 福建省侯官縣 [Fujian Sheng Houguan Xian] -- Government | AG70: 1888 | AH70: 查看原件 | AI70: 31735064607876
A71: 2 | B71: 68 | C71: 契尾／验契 | D71: 契尾 | E71: 4 咸同光宣（1851-1911） | F71: 光绪 | G71: 光绪拾肆年拾壹月 | H71: 1888 | I71: 陈必清 | J71: 男 | K71: 契尾作'业户陈必泉买陈必清屋' | L71: 陈必泉 | M71: 闽县 | N71: 闽县（坐落未见） | O71: 屋／厝 | P71: 屋 | Q71: 陈必清屋 | R71: 价银叁百零弍两正；税银玖两零陆分 | S71: 302 | T71: 银两 | X71: 福建布政使司契尾，闽字弍万叁千□百伍（?）号；钤闽县印多方 | AA71: 与同批 Folder 64（光绪十三年典契，典价200两）、Folder 69（光绪十四年十月卖断契）为同一屋业的一组文书；契尾价银302两约为典价与断价之和，税率3%。 | AC71: 中 | AD71: 契尾字号千位以下数字不清 | AE71: 1 | AF71: Seller: 陳必清 [CHEN Biqing] -- Buyer: 陳必泉 [CHEN Biquan] -- Place: 福建省閩縣 [Fujian Sheng Min Xian] -- Government | AG71: 1888 | AH71: 查看原件 | AI71: 31735066266416
A72: 2 | B72: 69 | C72: 买卖（卖／卖断） | D72: 卖断契 | E72: 4 咸同光宣（1851-1911） | F72: 光绪 | G72: 光绪拾肆年拾月吉日 | H72: 1888 | I72: 陈必清 | J72: 男 | K72: 原阄分份下本座墙後空地自己起盖墙屋；全室中梁氏、长男锺祥、侄男应祥同署 | L72: 陈必泉 | M72: 闽县 | N72: 闽邑嘉崇里横街铺惠泽境茶叶街地方 | O72: 屋／厝 | P72: 屋 | Q72: 墙屋全座，伍柱肆榀排，四面风火墙，直深伍丈伍尺，并围墙、天井、水井、大厅、後厅等；与 Folder 64 典契同一屋业 | R72: 卖断出屋价镜银玖（?）拾捌两正，库砝大锭白足色足兑 | S72: 98 | T72: 银两 | U72: 刘志潮；吕光达 | V72: 梁氏（全室中）；长男锺祥；侄男应祥；外甥何鸿壁（在见） | W72: 方忠恭（?） | X72: 契面钤红色菱形官印（闽县印?）；粘连契尾残片；另有红色长方戳'该业已经登记……上手契' | Y72: 永远卖断，不敢言赎言凑言尽 | Z72: 左侧粘连一段印刷契尾残片并钤红印（似为 Folder 68 契尾之骑缝部分） | AA72: 先典（光绪十三年，200两）後断（光绪十四年）的典型例子；并缴吴开杨典契、吴开成断契司单等共陆纸。红笔批注光绪卅二年八月等将此屋当押他人的记录，及民国陆年拾月前进库屋凑卖断与吴家的墨批。 | AC72: 中 | AD72: 断价首字'玖'存疑；红笔批注多字不清 | AE72: 1 | AF72: Seller: 陳必清 [CHEN Biqing] -- Buyer: 陳必泉 [CHEN Biquan] -- Place: 福建省閩縣 [Fujian Sheng Min Xian] -- Government | AG72: 1888 | AH72: 查看原件 | AI72: 31735066267901
A73: 2 | B73: 70 | C73: 买卖（卖／卖断） | D73: 卖断契 | E73: 4 咸同光宣（1851-1911） | F73: 光绪 | G73: 光绪拾五年六月吉日 | H73: 1889 | I73: 黄振发 | J73: 男 | K73: 承祖阄分份下 | L73: 高（姓，抬头书写，未具名） | M73: 闽县 | N73: 闽邑体泉铺，土名下底池地方 | O73: 地基 | P73: 地基 | Q73: 空地壹块；前至官街，後至黄家池磅，左至吴家屋，右至黄家池磅 | R73: 卖断得屋地价镜银壹拾两正，库砝大锭白足色足兑 | S73: 10 | T73: 银两 | U73: 余春仁 | V73: 堂兄黄振福（在见）；母舅高金魁（在见） | W73: 李珪甫 | X73: 无官印（白契） | Y73: 卖断，永不敢言赎言凑言尽 | AA73: 买主'高'仅以单字抬头；在见人为出卖人的母舅高金魁，买方高家可能即其亲属。契中许高家择吉起盖厝屋。左侧大书'永保千秋'。 | AC73: 高 | AD73: 池磅'字形存疑 | AE73: 1 | AF73: Seller: 黃振發 [HUANG Zhenfa] -- Buyer: 高 [GAO] -- Place: 福建省閩邑 [Fujian Sheng Min Xian] -- Personal | AG73: 1889 | AH73: 查看原件 | AI73: 31735066267620
A74: 2 | B74: 70A | C74: 买卖（卖／卖断） | D74: 卖断契 | E74: 4 咸同光宣（1851-1911） | F74: 光绪 | G74: 光绪拾伍年拾月吉日 | H74: 1889 | I74: 高金亮 | J74: 男 | K74: 原自己手置厝屋 | L74: 林（姓，抬头书写，未具名） | M74: 闽县 | N74: 闽邑体泉铺地方 | O74: 屋／厝 | P74: 屋 | Q74: 厝屋壹座，前後直深叁丈四尺五寸，横濶叁丈弍尺；左至吴家屋，右至黄家池墘，前至街，後至谢家屋，上至椽桁砖瓦，下至磉石地基 | R74: 卖断价银叁拾两正，库砝 | S74: 30 | T74: 银两 | U74: 堂兄金魁 | W74: 李钰成（?） | X74: 契面钤闽县红印；粘连布政使司契尾（光绪十六年，税银玖钱） | Y74: 卖断，永断葛藤，不敢言赎言凑 | Z74: 契尾：光绪拾陆年叁（?）月，闽字弍万陆千柒百肆拾捌号（?），业户林买高金亮屋，价银叁拾两正，税银玖钱正，钤闽县印 | AA74: 与 Folder 70 相连：黄振发光绪十五年六月将体泉铺空地卖与高家，高金亮起盖厝屋後同年十月转卖林家，并缴黄家地契壹纸共成弍纸；中人堂兄金魁即 Folder 70 的母舅高金魁。内拨出左爿伍柱厝屋叁堵卖断与杨正春。 | AC74: 中 | AD74: 代笔名、契尾字号及月份存疑 | AE74: 1 | AF74: Seller: 高金亮 [GAO Jinliang] --Buyer: 林 [LIN] -- Place: 福建省閩縣 [Fujian Sheng Min Xian] -- Personal | AG74: 1889 to 1890 | AH74: 查看原件 | AI74: 31735068223290
A75: 2 | B75: 70B | C75: 买卖（卖／卖断） | D75: 卖断契 | E75: 4 咸同光宣（1851-1911） | F75: 光绪 | G75: 光绪拾伍年十一月吉日 | H75: 1889 | I75: 张铨铨 | J75: 男 | K75: 承嗣父遗下阄分份下；知契母董氏 | L75: 邹道明 | M75: 闽县 | N75: 闽邑加崇里横山铺秋龙社地方 | O75: 屋／厝 | P75: 屋 | Q75: 厝屋壹栋三柱弍堵，上有梁椽砖瓦，下有磉石地基，内有门窗户扇俱全；左至郑家墙，右至游家路，前至郑家檐，後至蕴（?）家墙 | R75: 卖断价银拾肆两正，纹广 | S75: 14 | T75: 银两 | U75: □□□（中人名残缺） | V75: 董氏（知契母）；堂弟财财（?）（在见）；侄德良（?）（在见） | W75: 林可辉 | X75: 契面钤闽县红印；粘连光绪二十三年布政使司契尾 | Y75: 卖断，永断葛藤，永不得异言 | Z75: 契尾：光绪弍拾叁年弍月，闽字叁万伍千□百柒拾叁（?）号，业户邹道明买张铨铨屋，价银壹拾肆两正，纳税银肆钱弍分，钤闽县印 | AA75: 交易在光绪十五年，税契迟至光绪二十三年（1897）才办。地点横山铺秋龙社与 Folder 63 王锦发店屋同一社区。 | AC75: 中 | AD75: 中人姓名因纸边残破不全；在见人名字存疑 | AE75: 1 | AF75: Seller: 張銓銓 [ZHANG Quanquan] -- Buyer: 鄒道明 [ZOU Daoming] -- Place: 福建省閩縣 [Fujian Sheng Min Xian] -- Personal | AG75: 1889 to 1897 | AH75: 查看原件 | AI75: 31735068223308
A76: 2 | B76: 71 | C76: 买卖（卖／卖断） | D76: 卖断契 | E76: 4 咸同光宣（1851-1911） | F76: 同治 | G76: 同治玖年十一月吉日 | H76: 1870 | I76: 吴开成仝侄瑞枝、长庚 | J76: 男 | K76: 原承祖遗；兄开扬在日曾於道光弍拾叁、肆、柒等年间先後典在陈、郑、魏各姓；今叔侄向各典主赎回後统卖；知契嫂洪氏、陈氏 | L76: 陈（姓，抬头书写） | M76: 闽县 | N76: 闽邑横街铺地方 | O76: 屋／厝 | P76: 屋 | Q76: 厝屋肆柱弍榀壹座，前叁柱门楼，後引道至横墙，左边肆柱屋，後又有土库肆柱壹栋，右边肆柱，後又有披水壹栋 | R76: 卖断出屋价镜银陆拾捌两正，库砝大锭 | S76: 68 | T76: 银两 | U76: 李怀镜 | V76: 洪氏（知契嫂）；陈氏（知契嫂）；仝侄瑞枝；长庚；亲友陈清霖（?）（在见） | W76: 林枝三（?） | X76: 左下钤红色菱形官印（骑缝）；另有红色长方戳'该契已经登记……上手契' | Y76: 卖断，永断葛藤，不得言赎言凑言尽 | AA76: 契内列出并缴郑、魏、陈、刘等各姓赎回契、典契、借字及上手老契共弍拾伍纸。应即 Folder 64/69 陈必清契中所提'吴开成断契'的原件，同一'百寿 怙之轩'登记戳。 | AB76: 目录日期1890，契文为同治玖年（1870） | AC76: 中 | AD76: 代笔、在见人名及四至细节存疑 | AE76: 1 | AF76: Seller: 吳開成 [WU Kaicheng] -- Buyer: 陳氏 [Chenshi] -- Place: 福建省閩邑（縣） [Fujian Sheng Min Xian] -- Government | AG76: 1890 | AH76: 查看原件 | AI76: 31735064607488
A77: 2 | B77: 72 | C77: 买卖（卖／卖断） | D77: 卖断契 | E77: 4 咸同光宣（1851-1911） | F77: 光绪 | G77: 光绪拾陆年十二月日 | H77: 1890 | I77: 蓝炳孙 | J77: 男 | K77: 自己置有 | L77: 程长孙 | M77: 不详 | N77: 南坑，土名横兰路停仔後 | O77: 山林 | P77: 山林 | Q77: 茶皮骨山壹片（连杪桐荒山尽底）；上至半坪嫂样张宅为界，下至大横路为界，左至石岭顶重为界，右至近荒山林宅黄竹样为界 | R77: 土风时值契价洋银肆两正 | S77: 4 | T77: 银元／大洋 | U77: 赖文仔（说谕人）；张文发（说谕人）；张春老（中见人） | V77: 蓝乃寿（在见）；王永隆（在见） | W77: 张喜老 | X77: 无官印（白契） | Y77: 卖断皮骨，听买主管业摘茶收租 | AA77: 皮骨（田面田底）一并卖断的茶山契；上手全契因出业未便缴付，当日批明。左侧书'山契大发'。蓝姓或为畲族。 | AC77: 高 | AD77: 石岭顶重''嫂样'等地名字形存疑 | AE77: 1 | AF77: Seller: 藍炳孫 [LAN Bingsun] -- Buyer: 程長孫 [CHENG Changsun] -- Personal | AG77: 1890 | AH77: 查看原件 | AI77: 31735066266309
A78: 2 | B78: 73 | C78: 粮单／税单 | D78: 粮单／税单 | E78: 4 咸同光宣（1851-1911） | F78: 光绪 | G78: 光绪拾陆年至光绪拾捌年 | H78: 1890 | I78: 闽清县正堂（知县胡某） | J78: 官方 | K78: 串票由'钦加□品衔署理闽清县正堂加十级纪录十次胡'出给 | L78: 陈雅、陈建玺、陈成嘉、陈道书等陈姓纳户 | M78: 闽清县 | N78: 闽清县（乡、都名未填或不清） | O78: 田 | P78: 田 | Q78: 地丁正耗银及粮米的完纳凭证，未载具体田产 | R78: 地丁银数自陆分至壹两不等（见 attached_docs） | X78: 每纸钤闽清县红色方印；票面印'倘有重完在城限五日、在乡限十日许粮户粘串禀县以凭将来重银米照票发还粮户以杜重征'等字样 | Z78: 共8纸'版串执照'（闽清县徵收地丁钱粮串票，木刻套印，钤红色县印）：①光绪拾捌年地丁，纳户陈雅，银陆分○厘；②光绪拾捌年地丁，纳户陈建玺（?），银□分；③光绪拾捌年粮米，纳户陈建玺（?），米□合□勺（?）；④光绪拾捌年地丁，纳户陈成嘉，银叁钱正；⑤光绪拾捌年地丁，纳户陈万生（?），银壹两正，顶端有手写批注；⑥光绪拾陆年地丁，纳户陈雅，银陆分○厘，完纳；⑦光绪拾陆年地丁，纳户陈道书（?），银壹两正，完纳；⑧光绪拾陆年地丁，纳户陈道书（?），银壹两正，完纳（与⑦相似，或为另一笔） | AA78: 同一陈姓家族数名纳户在两个年度的完粮串票，可见清末地丁徵收的串票格式；光绪十六年票上署衙衔与十八年不同（换了知县）。 | AB78: 目录地点作闽县，串票实为闽清县；目录所列陈道书、陈建玺与票面草书大致相符但不能完全确定 | AC78: 中 | AD78: 纳户名草书（陈建玺、陈道书、陈万生）及部分银数存疑；纸张残破 | AE78: 8 | AF78: Owner: 陳雅 [CHEN Ya] 陳道書 [CHEN Daoshu] 陳建璽 [CHEN Jianxi] and 陳成嘉[CHEN Chengjia]-- Place: 福建省閩縣 [Fujian Sheng Min Xian] -- Government | AG78: 1890 to 1892 | AH78: 查看原件 | AI78: 31735066237656
A79: 2 | B79: 74 | C79: 分家书 | D79: 分家书／阄书 | E79: 4 咸同光宣（1851-1911） | F79: 光绪 | G79: 光绪拾柒年八月吉日 | H79: 1891 | I79: 林万开仝弟万拱、万钦 | J79: 男 | K79: 兄弟三人承父遗物业及手置田园屋宇山场树木，邀请亲友，除拨长子长孙份外，作福、禄、寿三房均分拈阄 | L79: 福、禄、寿三房（林万开兄弟），另长子长孙份及三房公众份 | M79: 侯官县 | N79: 草市都、三十八都二图（白龙、湖尾、后圳、坑里、马路等土名） | O79: 田 | P79: 田＋屋＋园＋山林 | Q79: 长子长孙份：井嘴、马路下、坑里根面全田各壹亩余（粮立草市都五甲林镇户）；福房：厝屋前进二间、厝边牛栏、典杨定亨厝屋、草仓马路松树下、白龙根面田多号、后圳四角横坵、福城林家面租等；禄房：厝屋第三进二间、杨家隔壁、草仓祠堂下、湖尾水流路、流道、猪蹄坵等田，及买断可真典与白龙张家应半田底（典契价壹百两又借弍拾两）；寿房：厝屋第二进、二进前照墙、祠堂边、白龙后圳灯笼坵、坛路磨盘、湖尾长坵头、洋中等田；三房公众份：祠堂边厝地三间、下底园、对面园、坑口园、桃树坪、坑里厝仔前坪、坑里田仔、坑里山二仑（含沈家契买土名王豹四田仔）等，山内树木柴草三房照轮 | V79: 族长昌意（在见）；堂弟万顺；堂侄可娘（?）；外甥涂振海；侄婿萧庆金；李茂炳 | W79: 侄可举（秉笔） | X79: 无官印；各房份下及骑缝钤同一私人朱印（花押式方印） | AA79: 粮色多立於三十八都各甲林溥、林昌元、林维豪、林均、林茂、林润之、林栋等户下，'林溥户'可对应 Folder 67 契尾中林万开买林秋溥田（三十八都）。在见族长昌意、堂弟万顺、堂侄可娘（可良?）亦见於 Folder 59 林万利典契（胞叔昌意、堂兄万顺、堂侄可良），可确认林万利与林万开为堂兄弟、同属侯官草市都林氏。规定祖墓风水树木不得砍伐、新埋造坟及补墓花红三股均分。 | AB79: 目录未列地点；据粮色草市都、三十八都及关联文书推定为侯官县 | AC79: 高 | AD79: 个别土名（坛路、后圳）及在见人'可娘'字形存疑 | AE79: 10 | AF79: Owner: 林萬開 [LIN Wankai] -- Personal | AG79: 1891 | AH79: 查看原件 | AI79: 31735064607645
A80: 2 | B80: 75 | C80: 粮单／税单 | D80: 粮单／税单 | E80: 4 咸同光宣（1851-1911） | F80: 光绪 | G80: 光绪拾捌年至光绪弍拾年 | H80: 1892 | I80: 侯官县正堂（李姓知县） | J80: 官方 | K80: 串票由侯官县正堂出给 | L80: 陈亮（故军李清的户） | M80: 侯官县 | N80: 侯官县□都，伍柜乡伍 | O80: 田 | P80: 田 | Q80: 屯田（卫所军屯）应纳屯银及屯米 | R80: 每年屯银壹钱叁分玖厘左右、屯米壹斗捌升柒合捌勺左右（分数纸完纳） | X80: 每纸钤侯官县红色大方印；左下手写串票号码（苏州码） | Z80: 共15纸侯官县'版串执照'（屯粮串票），纳户均为'故军李清的户陈亮'，伍柜乡伍：光绪拾捌年5纸（屯米壹斗正、屯米伍升正、地丁屯银玖分玖厘、地丁屯银肆分○厘、屯米叁升正），署名'钦加同知衔特授福州府侯官县正堂李'；光绪拾玖年4纸（地丁屯银壹钱正?、屯银叁分玖厘、屯米壹斗正、屯米伍升正）；光绪弍拾年6纸（地丁屯银壹钱正、屯银叁分玖厘、屯米壹斗正、屯米伍升正、屯米叁升正、屯米柒合捌勺） | AA80: 故军李清'为原屯军户名，实际纳粮人陈亮以'的户'身份承纳，反映清末军屯田已归民户耕纳而仍沿用旧军户名。每年分屯银、屯米多张串票，三年格式一致。同批 Folder 79 沈齐的屯米串票也写'故军李清的户'。 | AB80: 目录把李清列为业主之一，实为原屯军户名（故军李清），实际纳户为陈亮 | AC80: 中 | AD80: 第1、2纸上半部年份未能确认（推定光绪拾玖年）；都名不清 | AE80: 15 | AF80: Owner: 陳亮 [CHEN Liang] and 李清 [LI Qing] -- Place: 福建省 [Fujian Sheng] -- Government | AG80: 1892 to 1894 | AH80: 查看原件 | AI80: 31735066267810
A81: 2 | B81: 76 | C81: 典当／胎借 | D81: 典契 | E81: 4 咸同光宣（1851-1911） | F81: 光绪 | G81: 光绪拾玖年四月吉日 | H81: 1893 | I81: 王兆熙 | J81: 男 | K81: 承祖遗阄分自己份下田面；知契母黄氏 | L81: 林（姓，抬头书写'林处'） | M81: 侯官县 | N81: 侯邑西关外三十八都白龙坛路地方，土名郑鱼坵等坵 | O81: 田面 | P81: 田面 | Q81: 田面计□则田面弍亩□分零，年俩面租谷叁百伍拾斤；粮色立在四十弍都三啚五甲王亨贞户下 | R81: 典出田面价银叁拾壹两正，纹广 | S81: 31 | T81: 银两 | U81: 堂弟兆桐（?） | V81: 黄氏（知契母）；胞兄兆清（在见）；胞兄兆荣（在见） | W81: 王兆榕（?） | X81: 契面钤红色方印两方（後期验契印?），左下角另有红色菱形印 | Y81: 原主取赎不拘年限，照契面银两每两折本钱捌百伍拾文算；未取赎仍听照旧管业 | AA81: 小字批注上手原契别业相连未便缴付，如奉官投税赎契所有税耗一起算还，并改大字一字。左侧大书'大吉（?）'。与 Folder 77、78 构成王兆熙→林家同一田面的典、凑断、约字三件。 | AB81: 目录作卖契并标'出租'，实为典田面契；地点目录作闽侯县，契文为侯邑（侯官县） | AC81: 中 | AD81: 面积分数、册载字号、中人及代笔名字形存疑 | AE81: 1 | AF81: Seller: 王兆熙（出租） [WANG Zhaoxi] -- Buyer: 林 [LIN] -- Place: 福建省閩侯縣 [Fujian Sheng Minhou Xian] -- Government | AG81: 1893 | AH81: 查看原件 | AI81: 31735064607793
A82: 2 | B82: 77 | C82: 找贴／凑断 | D82: 找贴契／贴尽契 | E82: 4 咸同光宣（1851-1911） | F82: 光绪 | G82: 光绪二十年十二月吉日 | H82: 1894 | I82: 王兆熙 | J82: 男 | K82: 原有承祖遗阄分份下田面；知契母黄氏 | L82: 林（姓，抬头书写'林处'） | M82: 侯官县 | N82: 侯邑西关外三十八都白龙坛路地方，土名郑鱼坵 | O82: 田面 | P82: 田面 | Q82: 田面数号，计官丈弍亩伍分零，粮色租数俱在原典契内 | R82: 凑断出田面价钱弍千文正 | S82: 2000 | T82: 铜钱 | U82: 叔祖联登（?） | V82: 黄氏（知契母）；胞兄兆清（在见）；胞兄兆荣（在见） | W82: 王瑞臣 | X82: 白契後经验契：右上红色'验'字戳，'闽侯县西湖区验税契事务所'印，'闽侯县西湖区税契□□'印，红字'清查验讫'，及县印两方 | Y82: 凑断，永断葛藤，不得别生枝节、言赎 | AA82: 立'凑断契'，在 Folder 76 典契（价银31两）基础上再凑钱2000文断卖；民国时期在闽侯县西湖区验契。铅笔注'廿六/16'等编号。 | AB82: 目录作卖契，实为凑断（找贴断卖）契；地点契文为侯官县，验契时属闽侯县 | AC82: 中 | AD82: 中人'联登'字形存疑 | AE82: 1 | AF82: Seller: 王兆熙 [WANG Zhaoxi] -- Buyer: 林 [LIN] -- Place: 福建省閩侯縣 [Fujian Sheng Minhou Xian] -- Government | AG82: 1894 | AH82: 查看原件 | AI82: 31735064607827
A83: 2 | B83: 78 | C83: 合同／约字 | D83: 其他（约字：贴纳粮钱约） | E83: 4 咸同光宣（1851-1911） | F83: 光绪 | G83: 光绪弍拾年十二月吉日 | H83: 1894 | I83: 王兆熙 | J83: 男 | K83: 承祖遗阄分份下田面已卖与林家，但粮色仍在祖手多业相连的户下 | L83: 林（姓，'本乡林处'） | M83: 侯官县 | N83: 侯邑三十八都白龙坛路地方，土名郑鱼坵等坵 | O83: 田面 | P83: 田面 | Q83: 田面数号，年俩面租谷叁百伍拾斤（乡平秤） | R83: 林家递年贴纳兆熙完粮钱伍百文 | S83: 500 | T83: 铜钱 | U83: 叔祖联登（?） | V83: 胞兄兆清（在见） | W83: 王瑞臣 | X83: 右上红色小方印；右下大方印（县印?）；左下红色菱形印 | AA83: 因田赋粮色与祖手多业相连未分割，约定由林家每年贴钱500文给王兆熙代为完粮，待兆熙查明自归粮色後撤回由林家自纳，反映'推收过户'不完全的实务安排。与 Folder 76、77 同日／同业。 | AB83: 目录作卖契，实为贴纳粮钱约字 | AC83: 中 | AD83: 左侧大字批记未能辨读 | AE83: 1 | AF83: Seller: 王兆熙 [WANG Zhaoxi] -- Buyer: 林 [LIN] -- Place: 福建省閩侯縣 [Fujian Sheng Minhou Xian] -- Government | AG83: 1894 | AH83: 查看原件 | AI83: 31735064607819
A84: 2 | B84: 79 | C84: 粮单／税单 | D84: 粮单／税单 | E84: 4 咸同光宣（1851-1911） | F84: 光绪 | G84: 光绪弍拾壹年／光绪弍拾陆年 | H84: 1895 | I84: 侯官县正堂、永福县正堂 | J84: 官方 | K84: 两县分别出给的完粮串票 | L84: 沈齐；郑其英 | M84: 侯官县 | N84: 侯官县伍柜乡伍；永福县罗字号 | O84: 田 | P84: 田 | Q84: 屯田屯米及民田地丁银的完纳凭证 | R84: 屯米柒合捌勺；地丁银壹钱叁分□厘 | X84: 各钤县红色大方印 | Z84: ①侯官县'版串执照'，光绪弍拾陆年屯米柒合捌勺，故军李清的户沈齐，署名'钦加同知衔□任永安县调署侯官县正堂叶'，顶部墨书'田□□'；②永福县'粮户执照'，光绪弍拾壹年分地丁银，纳户郑其英，银壹钱叁分□厘，福州府永福县正堂屠（?），红色戳记'倘有重完错写限十日内赴柜改正，如迟自误' | AA84: 沈齐屯米串票也写'故军李清的户'，屯米数'柒合捌勺'与 Folder 75 陈亮光绪二十年的一纸完全相同，可能是同一份屯田转到沈齐名下。 | AB84: 目录地点作永安县和永福县；'永安县'实为侯官县知县叶某的原任官衔，第一纸属侯官县 | AC84: 中 | AD84: 永福县串票的知县姓、厘以下数字不清 | AE84: 2 | AF84: Owner: 鄭其英 [ZHENG Qiying] and 沈齊 [SHEN Qi] -- Place: 福建省永安县和永福县 [Fujian Sheng Yongan Xian and Yongfu Xian] -- Government | AG84: 1895 to 1900 | AH84: 查看原件 | AI84: 31735066237672
A85: 2 | B85: 80 | C85: 买卖（卖／卖断） | D85: 卖契 | E85: 4 咸同光宣（1851-1911） | F85: 光绪 | G85: 光绪贰拾肆年十一月日 | H85: 1898 | I85: 苏章林 | J85: 男 | K85: 承祖遗下置有皮骨分定晚田 | L85: 刘仕懋 | M85: 不详 | N85: 濠墩门前，土名溪壁洲碓下外郎目 | O85: 田 | P85: 田 | Q85: 皮骨（田面田底）晚田，原计大苗糙米壹箩七斗六管，该载民产壹亩零；上至陈宅田，下至杨宅田，左至陈宅田，右至本宅田为界；坐落长埔村 | R85: 土风时值契价纹银叁拾贰两正；另批中书洋银壹两伍钱弍分正 | S85: 32 | T85: 银两 | U85: 刘仕德（说谕人） | V85: 苏章狼（?）（见银人） | W85: 邱宗海 | X85: 无官印（白契） | Y85: 议定叁冬取赎，办得原价即便退还；如无原价任从买主管业收租 | AA85: 批明上手契叁与网房相共不便缴照；粮存太里乙啚五甲苏廷妹户名，当官完粮不得丢累。说谕人刘仕德与买主刘仕懋似为兄弟。左侧书'卖契'。 | AC85: 高 | AD85: 见银人名第三字存疑；县份无法判断 | AE85: 1 | AF85: Seller: 蘇章林 [SU Zhanglin] -- Buyer: 劉仕懋 [LIU Shimao] -- Personal | AG85: 1898 | AH85: 查看原件 | AI85: 31735064607629
A86: 2 | B86: 81 | C86: 找贴／凑断 | D86: 找贴契／贴尽契 | E86: 4 咸同光宣（1851-1911） | F86: 光绪 | G86: 光绪贰拾五年八月日 | H86: 1899 | I86: 张宝詨 | J86: 男 | K86: 承祖遗下置有粟厂屋；立'找断胞头加壹字' | L86: 程长孙 | M86: 不详 | N86: 南坑，土名後门山 | O86: 屋／厝 | P86: 屋 | Q86: 粟厂壹伴（座），四至界内在前契明白 | R86: 找出洋银贰两弍钱伍分正 | S86: 2.25 | T86: 银元／大洋 | U86: 何章林（说找人）；张务孙（劝找人） | W86: 张鉄狗 | X86: 无官印（白契） | Y86: 找断之後任从买主管业收租，不敢阻执 | AA86: 在前卖契基础上找价断卖；买主程长孙与 Folder 72（蓝炳孙卖茶山，光绪十六年）同一人，地点同为南坑。'说找人''劝找人'的称谓少见。 | AB86: 目录日期1890，契文为光绪二十五年（1899）；目录作卖契，实为找断字 | AC86: 高 | AD86: 粟厂'字形、卖主名'詨'字存疑 | AE86: 1 | AF86: Seller: 張寶詨 [ZHANG Baoxiao] -- Buyer: 程長孫 [CHENG Changsun] -- Personal | AG86: 1890 | AH86: 查看原件 | AI86: 31735066266291
A87: 2 | B87: 82 | C87: 买卖（卖／卖断） | D87: 卖断契 | E87: 4 咸同光宣（1851-1911） | F87: 光绪 | G87: 光绪弍拾陆年闰捌月吉日 | H87: 1900 | I87: 邹允春 | J87: 男 | K87: 承父手置；契中言'此屋系父自己手置' | L87: 和意轩老人会 | M87: 闽县 | N87: 闽邑嘉崇里文山铺秋龙社地方 | O87: 屋／厝 | P87: 屋 | Q87: 厝屋叁柱弍榀排弍座共成弍堵，上有梁椽砖瓦，下至地基磉石地坪，内有门窗户扇地坪板榻一切俱全；横阔弍丈弍尺零，直深弍丈肆尺零；左至郑家屋，右至毛家路，前至郑家檐坪，後至蕴家墙；屋角水井通用 | R87: 卖断得厝价库平银弍拾肆两正 | S87: 24 | T87: 银两 | U87: 王伊细 | V87: 表弟黄公弼（在见） | W87: 李松轩 | X87: 白契；民国时期福州市政府紫色'验讫'戳（37年?月，18488A），另有红色戳记若干 | Y87: 卖断，永断葛藤 | AA87: 所卖即 Folder 70B 张铨铨光绪十五年卖与邹道明的秋龙社厝屋（四至相同，并缴张铨铨原契壹纸、司单壹纸共成叁纸），邹允春应为邹道明之子。买主为民间团体'和意轩老人会'。内标注涂用弍字。 | AC87: 高 | AD87: 验讫戳日期数字存疑 | AE87: 1 | AF87: Seller: 鄒允春 [ZOU Yunchun] -- Buyer: 和意軒老人會 [Heyixuan Laorenhui] -- Place: 福建省閩邑（縣） [Fujian Sheng Min Xian ] -- Government | AG87: 1900 | AH87: 查看原件 | AI87: 31735064607496
A88: 2 | B88: 83 | C88: 粮单／税单 | D88: 粮单／税单 | E88: 4 咸同光宣（1851-1911） | F88: 光绪 | G88: 光绪弍拾陆年 | H88: 1900 | I88: 侯官县正堂叶（钦加同知衔本任永安县调署侯官县） | J88: 官方 | K88: 侯官县版串执照 | L88: 沈齐（故军李清的户） | M88: 侯官县 | N88: 侯官县□都，伍柜乡伍，雨字号 | O88: 田 | P88: 田 | Q88: 屯田地丁屯银 | R88: 地丁屯银捌分玖厘 | X88: 钤侯官县红色大方印 | AA88: 与 Folder 79 第一纸同年同官同纳户，沈齐仍以'故军李清的户'名义完纳屯银，延续 Folder 75 陈亮的屯粮户。 | AB88: 目录地点作永安县；'永安县'是知县叶某的本任官衔，串票实属侯官县 | AC88: 中 | AD88: 年份'陆'字、纳户名'齐'字草书存疑 | AE88: 1 | AF88: Owner: 沈齊 [SHEN Qi] -- Place: 福建省永安縣 [Fujian Sheng Yongan Xian] -- Government | AG88: 1900 | AH88: 查看原件 | AI88: 31735066266739
A89: 2 | B89: 83A | C89: 买卖（卖／卖断） | D89: 卖断契 | E89: 4 咸同光宣（1851-1911） | F89: 光绪 | G89: 光绪弍拾陆年闰捌月日 | H89: 1900 | I89: 邹允春 | J89: 男 | K89: 承父手置 | L89: 和意轩老人会 | M89: 闽县 | N89: 闽邑嘉崇里文山铺秋龙社地方 | O89: 屋／厝 | P89: 屋 | Q89: 与 Folder 82 同一厝屋：叁柱弍榀排弍座，横阔弍丈弍尺零，直深弍丈肆尺零，四至同 | R89: 库平银弍拾肆两正 | S89: 24 | T89: 银两 | U89: 王伊细 | V89: 表弟黄公弼（在见） | W89: 李松轩 | X89: 无官印、无验讫戳 | Y89: 卖断，永断葛藤 | AA89: 为 Folder 82 正契的草书副本／底稿：文字相同，但无画押、无印记，左侧同样书'添丁大吉（?）'。 | AB89: 目录买主作'秋意轩老人会'，契文为'和意轩老人会'；目录地点 N/A，契文为闽邑秋龙社 | AC89: 中 | AD89: 草书，个别字依 Folder 82 正本对照辨读 | AE89: 1 | AF89: Seller: 鄒允春 [ZOU Yunchun] -- Buyer: 秋意軒老人會 [Qiuyixuan Laoren Hui] -- Place: N/A -- Personal | AG89: 1900 | AH89: 查看原件 | AI89: 31735068223316
A90: 2 | B90: 84 | C90: 典当／胎借 | D90: 典契 | E90: 4 咸同光宣（1851-1911） | F90: 光绪 | G90: 光绪弍拾玖年十二月日 | H90: 1903 | I90: 林兴清仝胞弟兴佃 | J90: 男 | K90: 承父在日自己手置；知契母洪氏 | L90: 程贞□（?）（'程贞雨处'） | M90: 不详 | N90: □□都土田庄里地方 | O90: 田根 | P90: 田根＋田面 | Q90: 根面全民屯田叁号：册载海字弍千八十三号田壹亩叁分叁□□毛，又弍千八十四号田壹亩肆分，并荒田 | R90: 缴典出价银肆拾伍两正，纹广 | S90: 45 | T90: 银两 | U90: 程本容 | V90: 洪氏（知契母）；胞弟兴佃；胞叔克院（在见） | W90: 林兴清自笔 | X90: 无官印（白契） | Y90: 伍年为限，限满之日照契面银两依期取赎，每两银折铜钱捌百伍拾文 | AA90: 缴典'即将此前典给他人的田转典：并缴林兴火典契、林兴火典程贞嫩（?）典契、黄来宝典契、詹黄二姓合约字共成伍纸。左侧大书'大□'。 | AB90: 目录作卖主林与清，实为'林兴清'，文书为缴典契 | AC90: 中 | AD90: 承典人名、都名及面积零数存疑 | AE90: 1 | AF90: Seller: 林與清 [LIN Yuqing] -- Place: unknown --Personal | AG90: 1903 | AH90: 查看原件 | AI90: 31735066267851
A91: 2 | B91: 85 | C91: 买卖（卖／卖断） | D91: 卖契 | E91: 4 咸同光宣（1851-1911） | F91: 光绪 | G91: 光绪弍拾玖年拾弍月日 | H91: 1903 | I91: 张文楚 | J91: 男 | K91: 自己手置 | L91: 金宽英 | M91: 永泰县 | N91: 本都乌山头地方，土名仙壋後垅头并深垅尾垅仔 | O91: 田根 | P91: 田根＋田面 | Q91: 屯田底面俱全乙号，共受种壹亩，年载大租乙百弍拾斤正民秤，配粮柒分弍厘 | R91: 时值价银壹拾五两正，纹广 | S91: 15 | T91: 银两 | U91: 程章（代字中侄） | V91: 弟文亮（在见） | W91: 程章 | X91: 原契白契；民国三十三年补税，附卖契本契、印花税票 | Y91: 期言约四年，限满之日备出纹银照契面银两对月期取赎；如未赎仍付管业 | Z91: 民国卅三年（1944）六月福建省田赋粮食管理处发印'卖契本契'（云字第□号，永泰县）：买主金宽英住嵩口镇，坐落乌头山，卖主张文楚住嵩口镇，卖价弍拾元，立契日期光绪廿九年十二月，应纳契税叁元；贴国民政府印花税票壹圆，钤福建省永泰田赋粮食管理处红印；上印契税条例摘要（卖契税率15%） | AA91: 并缴杨宋忠卖契、原卖断契乙纸、原赎回契乙纸共成四纸。光绪年间的活卖契到1944年才补税，原价15两被折成20元计税。契上另贴小纸条墨书地名'嵩□羽湖（?）系'，左上书'大吉'及铅笔'1944'。 | AC91: 高 | AD91: 土名'仙壋''垅仔'字形存疑；代字人'程章'次字存疑 | AE91: 2 | AF91: Owner: 金寬英 [JIN Kuanying] -- Seller: 張文楚 [ZHANG Wenchu] -- Buyer: 金寬英 [JIN Kuanying] -- Place: 福建省永泰縣 [Fujian Sheng Yongtai Xian] -- Government | AG91: 1903 to 1943 | AH91: 查看原件 | AI91: 31735066237557
A92: 2 | B92: 86 | C92: 买卖（卖／卖断） | D92: 卖断契 | E92: 4 咸同光宣（1851-1911） | F92: 光绪 | G92: 光绪叁拾年十一月 日 | H92: 1904 | I92: 许春愿 | J92: 男 | K92: 承祖遗下民田根面 | L92: 黄财业 | M92: 闽县 | N92: 坐产涛(?)亭洋地方，土名祠堂门前塘(?)崛(?)等处 | O92: 田（根面全） | P92: 田（根面全） | Q92: 民田根面全壹号，受种柒升伍合，年载租米柒斗伍升，粮立化册许文相户下 | R92: 大洋陆拾员正 | S92: 60 | T92: 银元／大洋 | U92: 黄振章 | V92: 春岐（见兄） | W92: 陈经森 | X92: 原契为白契，后贴中华民国印花税票（贰分）；民国三十二年县卖契盖县印、教育附加税紫印、红色契税条例印 | Y92: 卖断，永不敢别生枝节；粮色由买主过割入户 | Z92: 1) 光绪三十年十一月许春愿立卖断契（白契，后贴民国印花税票贰分一枚）；2) 民国三十二年四月闽侯(?)县'县卖契'官契纸：承买人黄财业、出卖人许春愿、中证人黄振章，契价栏写'陆拾'，盖'附加县教育经费五成''奉准借用'等紫印及县印，执收联第1539号 | AA92: 内注'出字壹字再照'；契末批'带多额未缴再照'。清末白契到1943年才补办县卖契，相隔近四十年。 | AC92: 中 | AD92: 坐落地名'涛亭洋''塘崛'字形存疑；县卖契价格栏仅见'陆拾' | AE92: 2 | AF92: Owner: 黃財業 [HUANG Caiye] -- Seller: 許春願 [XU Chunyuan] -- Buyer: 黃財業 [HUANG Caiye] -- Place: 福建省閩縣 [Fujian Sheng Min Xian] -- Government | AG92: 1904 to 1943 | AH92: 查看原件 | AI92: 31735066237532
A93: 2 | B93: 87 | C93: 买卖（卖／卖断） | D93: 卖断契 | E93: 4 咸同光宣（1851-1911） | F93: 光绪 | G93: 光绪叁拾弍年拾壹月 日 | H93: 1906 | I93: 林为良 | J93: 男 | K93: 将田复还卖断与族弟 | L93: 林可琼（族弟） | M93: 闽侯县 | N93: □□都□□亭地方，坐□洛(?) | O93: 田（根面全） | P93: 田（根面全） | Q93: 根面全民田壹号，册载地字弍百□号，计官丈壹亩伍分二…，粮银壹钱弍分弍厘七毫，色米壹升柒合五勺；挂本都七甲林福户下 | R93: 卖断田价银壹百叁拾两 | S93: 130 | T93: 银两 | U93: 刘兴国 | V93: 叔维屏(?)（在见） | W93: 王清泉 | X93: 闽侯县西门(?)区税契分局印、西湖区验税契事务所'验讫'印（民国补验），另有'永远执业'批字 | Y93: 卖断，永断葛藤，不敢生枝节 | AA93: 文书残破缺角。契内批'由契壹纸并缴杨鹏超(?)典契''林可锜凑断壹纸'，说明此前曾典与杨姓、有凑断契。中人刘兴国后来在1913年成为林可琼该类田产的买主（见Box 2, Folder 94）。 | AB93: 目录作民国闽侯县，契文为光绪年间（闽侯县之名见于民国补验印） | AC93: 中 | AD93: 残缺处坐落、册号不全；在见人名'维屏'存疑 | AE93: 1 | AF93: Seller: 林為良 [LIN Weiliang] -- Buyer: 林可瓊 [LIN Keqiong] -- Place: 福建省閩侯縣 [Fujian Sheng Minhou Xian] -- Government | AG93: 1906 | AH93: 查看原件 | AI93: 31735064607702
A94: 2 | B94: 88 | C94: 买卖（卖／卖断） | D94: 卖断契 | E94: 4 咸同光宣（1851-1911） | F94: 光绪 | G94: 光绪三十二年三月吉日 | H94: 1906 | I94: 郭宗仲 | J94: 男 | K94: 自己手置之屋 | L94: 王齐发 | M94: 闽县 | N94: 闽邑文山铺秋龙社地方 | O94: 屋／厝 | P94: 屋 | Q94: 弍座厝屋壹间左边房屋壹堵、右边廊境壹小堵，共成叁堵，坐北向南；四至：前天井、后墙、左郭境、右王家屋；门窗户扇廊石一切俱全，出入门路水井照旧通行 | R94: 镜银壹拾两正 | S94: 10 | T94: 银两 | U94: 高依赐；林锡甫 | V94: 宗阶（胞弟，在见） | W94: 齐光波(?) | X94: 无官印（白契） | Y94: 卖断，不得言凑言赎，永断葛藤 | AA94: 红格纸书写、无任何印记，应为Folder 88B同一交易的另一纸（草稿或副本）。'原契壹纸共成弍纸缴付'。地点秋龙与规范示例中的秋龙巷相同，买主亦为王家。 | AC94: 高 | AD94: 代笔人名末二字存疑（88B作'齐光茂'?） | AE94: 1 | AF94: Seller: 郭宗仲 [GUO Zongzhong] -- Buyer: 王齊發 [WANG Qifa] -- Personal | AG94: 1906 | AH94: 查看原件 | AI94: 31735066237490
A95: 2 | B95: 88A | C95: 买卖（卖／卖断） | D95: 卖断契 | E95: 4 咸同光宣（1851-1911） | F95: 光绪 | G95: 光绪卅弍年□月吉日 | H95: 1906 | I95: 郭武亮(?)（目录作郭成亮） | J95: 男 | K95: 自己所置之屋 | L95: 王骏发 | M95: 闽县 | N95: □□地方，坐西向东 | O95: 屋／厝 | P95: 屋 | Q95: 壹座左边厨房壹所…坐西向东，上至椽桁砖瓦，前至天井、后至墙、左至王家天井、右至□家壁 | R95: 契单载价银叁拾(?)两 | T95: 银两 | U95: 林玉明(?) | W95: 陈有义(?) | X95: 县契、国税厅筹备处契单（民国三年）、财政厅验税契证（民国十八年）及印花税票、地保方铨(?)印、福州市人民政府印 | Y95: 卖断，不得言凑言赎 | Z95: 1) 光绪卅二年郭武(成?)亮立卖断契（白契，后盖印）；2) 光绪年间县契（官契纸），业户王骏发；3) 福建国税厅筹备处卖断契单，中华民国三年十月；4) 福建财政厅验税契证，中华民国十八年十一月二十七日，业户王骏发，贴印花税票四枚；5) 福州市人民政府印记（1950年代） | AA95: 一件交易连贴清、民国、新中国三个时期的验契文件。买主王骏发与Folder 88/88B的买主王齐发同姓、同年，屋契四至均提'王家'，疑为同一王姓家族在同一街区集中购屋。 | AB95: 目录卖主作郭成亮，图像签名似'郭武亮' | AC95: 低 | AD95: 图像分辨率低，价格、月份、中人、代笔多处难辨 | AE95: 1 | AF95: Seller: 郭成亮 [GUO Chengliang] -- Buyer: 王駿發 [WANG Junfa] -- Place: 福建省閩侯縣 [Fujian Sheng Minhou Xian] -- Personal | AG95: 1906 to 1955 | AH95: 查看原件 | AI95: 31735068223324
A96: 2 | B96: 88B | C96: 买卖（卖／卖断） | D96: 卖断契 | E96: 4 咸同光宣（1851-1911） | F96: 光绪 | G96: 光绪叁拾弍年叁(?)月吉日 | H96: 1906 | I96: 郭宗仲 | J96: 男 | K96: 自己手置之屋 | L96: 王齐发 | M96: 闽县 | N96: 闽邑文山铺秋龙社地方 | O96: 屋／厝 | P96: 屋 | Q96: 弍座厝屋左边房屋壹堵、右边廊境壹小堵，共成叁堵，坐北向南；前至天井、后至墙、左郭境、右王家屋 | R96: 壹拾两正（民国十年卖契折价拾伍元） | S96: 10 | T96: 银两 | U96: 高依赐；林锡甫 | V96: 宗阶（胞弟，在见） | W96: 齐光茂(?) | X96: 闽县文山铺地保方铨(?)印（闽字第□号）、闽县税契局'验讫'椭圆印；县契官印；民国十年卖契盖印并载应纳税额 | Y96: 卖断，不得言凑言赎 | Z96: 1) 光绪叁拾弍年郭宗仲立卖断契（与Folder 88同文，盖地保印与验讫印）；2) 光绪年间县契（官契纸），王齐发买郭宗仲屋；3) 民国十年四月一日'卖契'（例则摘要式），买主王齐发、卖主郭宗仲、中人高依赐，不动产种类屋，卖价拾伍元，坐落文山铺，面积壹间(?) | AA96: 与Folder 88为同一交易，此件为加盖地保及税契印的正式本，并附官契与民国十年补税卖契。'地保'栏有签押与印记。 | AC96: 中 | AD96: 立契月份'叁月'或'冬月'；民国卖契税额难辨 | AE96: 1 | AF96: Seller: 郭宗仲 [GUO Zongzhong] -- Buyer: 王齊發 [WANG Qifa] -- Place: 福建閩侯縣 [Fujian Sheng Minhou Xian] -- Personal | AG96: 1906 to 1921 | AH96: 查看原件 | AI96: 31735068223332
A97: 2 | B97: 89 | C97: 契尾／验契 | D97: 契尾 | E97: 4 咸同光宣（1851-1911） | F97: 宣统 | G97: 宣统元年 月 日 | H97: 1909 | I97: 何振华 | J97: 男 | K97: 契尾载'业户何金盛买何振华田' | L97: 何金盛 | M97: 建阳县 | N97: 建阳县 | O97: 田 | P97: 田 | Q97: 契尾只载买田，未详亩数坐落 | R97: 价银拾玖两捌钱，税银伍钱玖分肆厘 | S97: 19.8 | T97: 银两 | X97: 福建布政使司颁契尾，布字壹百肆拾捌(?)号，骑缝号'二千一百三十九(?)号'，盖建阳县印数方 | AA97: 税额恰为价银3%（19.8×0.03=0.594）。契尾印刷部分引乾隆十五年奏准契尾格式。 | AB97: 目录作卖主何金盛、买主何振华；契尾明写业户何金盛买何振华田，买卖方向相反 | AC97: 中 | AD97: 契尾编号数字部分存疑 | AE97: 1 | AF97: Seller: 何金盛 [HE Jinsheng] -- Buyer: 何振華 [HE Zhenhua] -- Place: 福建省建陽縣 [Fujian Sheng Jianyang Xian] -- Government | AG97: 1909 | AH97: 查看原件 | AI97: 31735066267646
A98: 2 | B98: 90 | C98: 买卖（卖／卖断） | D98: 卖断契 | E98: 4 咸同光宣（1851-1911） | F98: 宣统 | G98: 宣统元年拾壹月吉日 | H98: 1909 | I98: 家炽（胞兄） | J98: 男 | K98: 自己阄分份下，卖与胞弟 | L98: 尚堃(?)（胞弟） | M98: 不详 | N98: 坐址塘口洋，土名坛前 | O98: 田 | P98: 田 | Q98: 民田壹号，受种叁斗叁坵；粮米挂在集壹图壹甲吴玉典(?)户下，粮壹钱零捌厘，仓米壹升柒合，并丁在内 | R98: 纹广银弍拾两正 | S98: 20 | T98: 银两 | U98: 陈端辛(?)（代笔兼中） | V98: 尚彭(?)（胞弟，在见） | W98: 陈端辛(?) | X98: 红印'验讫'及税契印，另有县印一方及骑缝印 | Y98: 卖断，不敢言说取赎尽贴 | AA98: 兄弟间分家后的买卖，田由胞弟召佃收租。代笔人'陈端辛'与Folder 91的中人'族叔端辛'似为同一人，两件格式、验讫印相同，应同出一陈姓家族。 | AB98: 目录卖主作'炽原'，实为'家炽'，'原'属下文'原自己阄分' | AC98: 中 | AD98: 买主名'尚□'字形似'炊'，目录作'堃'；代笔人名存疑 | AE98: 1 | AF98: Seller: 熾原 [Chiyuan] -- Buyer: 尚堃 [Shangkun] -- Place: unknown -- Government | AG98: 1909 | AH98: 查看原件 | AI98: 31735066267836
A99: 2 | B99: 91 | C99: 典当／胎借 | D99: 典契 | E99: 4 咸同光宣（1851-1911） | F99: 宣统 | G99: 宣统弍年拾壹月吉日 | H99: 1910 | I99: 开保（堂侄孙） | J99: 男 | K99: 原父手阄分份下 | L99: 朝朋（叔祖） | M99: 不详 | N99: 坐址本洋，土名尝竹墩(?) | O99: 田 | P99: 田 | Q99: 民田壹号，受种弍斗壹坵；粮米挂在保弍(?)图七甲陈元华户下，粮应壹钱伍分，米应弍升陆合 | R99: 番银柒拾员正，每员陆钱叁分重(?) | S99: 70 | T99: 番银 | U99: 端辛(?)（族叔） | V99: 端理（父，在见知契） | W99: 开次（族弟） | X99: 红印'验讫'，县印数方，另有骑缝印 | Y99: 典，约若干年为限，限满备银照契面原数取赎，外加银水柒占伍厘 | AA99: 典主叔祖'朝朋'可能即Folder 102连江县业主陈朝朋；与Folder 90同族同格式。 | AB99: 目录未列买主（典主朝朋） | AC99: 中 | AD99: 土名、图甲号、典期年限存疑 | AE99: 1 | AF99: Seller: 開保 [Kaibao] -- Government | AG99: 1910 | AH99: 查看原件 | AI99: 31735064607686
A100: 2 | B100: 92 | C100: 买卖（卖／卖断） | D100: 卖断契 | E100: 4 咸同光宣（1851-1911） | F100: 宣统 | G100: 宣统弍年十二月 日 | H100: 1910 | I100: 刘嘉命 | J100: 男 | K100: 承祖遗下 | L100: 刘源森（本村堂孙） | M100: 建阳县 | N100: 本村 | O100: 屋／厝 | P100: 地基／屋地＋园 | Q100: 皮(?)骨坪基壹所及菜园；上至刘宅、左至菜园大路、右至山边为界 | R100: 时值土风断契价洋银捌两弍钱伍分正 | S100: 8.25 | T100: 银两 | U100: 刘孝元(?) | V100: 吴清明（说谕人）；刘华老（堂孙，知契人） | W100: 刘孝铠 | X100: 建阳县印数方 | Y100: 卖断，不敢阻挠 | AA100: 当日面批：菜园上手老契一时不能寻出，日后寻出不得行用。以'洋银'计两。 | AC100: 高 | AD100: 坪基前一字'皮'存疑 | AE100: 1 | AF100: Seller: 劉嘉命 [LIU Jiaming] -- Buyer: 劉源森 [LIU Yuansen] -- Place: 福建省建陽縣 [Fujian Sheng Jianyang Xian] -- Government | AG100: 1910 | AH100: 查看原件 | AI100: 31735066237730
...

Sheet 统计
A1: 统计（公式随“总表”实时计算；在总表中修正后这里会自动更新）
A3: 一、文书大类 | F3: 八、交易价格（仅买卖、典当、找贴类文书；按币种 × 时期）
A4: 类别 | B4: 件数 | C4: 占比 | F4: 注：同一币种内交易物大小差异很大（一间屋到数亩田），均值只作粗略参考；找贴类价格是加价部分而非全价。
A5: 买卖（卖／卖断） | B5: =COUNTIF(总表!$C$2:$C$235,A5) -> 68 | C5: =IFERROR(B5/COUNTA(总表!$AI$2:$AI$235),0) -> 0.29059829 | F5: 币种 | G5: 时期 | H5: 件数 | I5: 平均 | J5: 最低 | K5: 最高
A6: 典当／胎借 | B6: =COUNTIF(总表!$C$2:$C$235,A6) -> 40 | C6: =IFERROR(B6/COUNTA(总表!$AI$2:$AI$235),0) -> 0.17094017 | F6: 银两 | G6: 2 清前期（1644-1795） | H6: =SUMPRODUCT(COUNTIFS(总表!$T$2:$T$235,$F6,总表!$E$2:$E$235,$G6,总表!$C$2:$C$235,{"买卖（卖／卖断）","典当／胎借","找贴／凑断","典＋找贴"},总表!$S$2:$S$235,">0")) -> 9 | I6: =IFERROR(SUMPRODUCT(SUMIFS(总表!$S$2:$S$235,总表!$T$2:$T$235,$F6,总表!$E$2:$E$235,$G6,总表!$C$2:$C$235,{"买卖（卖／卖断）","典当／胎借","找贴／凑断","典＋找贴"},总表!$S$2:$S$235,">0"))/H6,"—") -> 18.022222 | J6: =IF(H6=0,"—",MIN(IF(COUNTIFS(总表!$T$2:$T$235,$F6,总表!$E$2:$E$235,$G6,总表!$C$2:$C$235,"买卖（卖／卖断）",总表!$S$2:$S$235,">0")=0,1E+99,_xlfn.MINIFS(总表!$S$2:$S$235,总表!$T$2:$T$235,$F6,总表!$E$2:$E$235,$G6,总表!$C$2:$C$235,"买卖（卖／卖断）",总表!$S$2:$S$235,">0")),IF(COUNTIFS(总表!$T$2:$T$235,$F6,总表!$E$2:$E$235,$G6,总表!$C$2:$C$235,"典当／胎借",总表!$S$2:$S$235,">0")=0,1E+99,_xlfn.MINIFS(总表!$S$2:$S$235,总表!$T$2:$T$235,$F6,总表!$E$2:$E$235,$G6,总表!$C$2:$C$235,"典当／胎借",总表!$S$2:$S$235,">0")),IF(COUNTIFS(总表!$T$2:$T$235,$F6,总表!$E$2:$E$235,$G6,总表!$C$2:$C$235,"找贴／凑断",总表!$S$2:$S$235,">0")=0,1E+99,_xlfn.MINIFS(总表!$S$2:$S$235,总表!$T$2:$T$235,$F6,总表!$E$2:$E$235,$G6,总表!$C$2:$C$235,"找贴／凑断",总表!$S$2:$S$235,">0")),IF(COUNTIFS(总表!$T$2:$T$235,$F6,总表!$E$2:$E$235,$G6,总表!$C$2:$C$235,"典＋找贴",总表!$S$2:$S$235,">0")=0,1E+99,_xlfn.MINIFS(总表!$S$2:$S$235,总表!$T$2:$T$235,$F6,总表!$E$2:$E$235,$G6,总表!$C$2:$C$235,"典＋找贴",总表!$S$2:$S$235,">0")))) -> 0.5 | K6: =IF(H6=0,"—",MAX(_xlfn.MAXIFS(总表!$S$2:$S$235,总表!$T$2:$T$235,$F6,总表!$E$2:$E$235,$G6,总表!$C$2:$C$235,"买卖（卖／卖断）",总表!$S$2:$S$235,">0"),_xlfn.MAXIFS(总表!$S$2:$S$235,总表!$T$2:$T$235,$F6,总表!$E$2:$E$235,$G6,总表!$C$2:$C$235,"典当／胎借",总表!$S$2:$S$235,">0"),_xlfn.MAXIFS(总表!$S$2:$S$235,总表!$T$2:$T$235,$F6,总表!$E$2:$E$235,$G6,总表!$C$2:$C$235,"找贴／凑断",总表!$S$2:$S$235,">0"),_xlfn.MAXIFS(总表!$S$2:$S$235,总表!$T$2:$T$235,$F6,总表!$E$2:$E$235,$G6,总表!$C$2:$C$235,"典＋找贴",总表!$S$2:$S$235,">0"))) -> 63
A7: 契尾／验契 | B7: =COUNTIF(总表!$C$2:$C$235,A7) -> 37 | C7: =IFERROR(B7/COUNTA(总表!$AI$2:$AI$235),0) -> 0.15811966 | F7: 银两 | G7: 3 嘉道（1796-1850） | H7: =SUMPRODUCT(COUNTIFS(总表!$T$2:$T$235,$F7,总表!$E$2:$E$235,$G7,总表!$C$2:$C$235,{"买卖（卖／卖断）","典当／胎借","找贴／凑断","典＋找贴"},总表!$S$2:$S$235,">0")) -> 9 | I7: =IFERROR(SUMPRODUCT(SUMIFS(总表!$S$2:$S$235,总表!$T$2:$T$235,$F7,总表!$E$2:$E$235,$G7,总表!$C$2:$C$235,{"买卖（卖／卖断）","典当／胎借","找贴／凑断","典＋找贴"},总表!$S$2:$S$235,">0"))/H7,"—") -> 95 | J7: =IF(H7=0,"—",MIN(IF(COUNTIFS(总表!$T$2:$T$235,$F7,总表!$E$2:$E$235,$G7,总表!$C$2:$C$235,"买卖（卖／卖断）",总表!$S$2:$S$235,">0")=0,1E+99,_xlfn.MINIFS(总表!$S$2:$S$235,总表!$T$2:$T$235,$F7,总表!$E$2:$E$235,$G7,总表!$C$2:$C$235,"买卖（卖／卖断）",总表!$S$2:$S$235,">0")),IF(COUNTIFS(总表!$T$2:$T$235,$F7,总表!$E$2:$E$235,$G7,总表!$C$2:$C$235,"典当／胎借",总表!$S$2:$S$235,">0")=0,1E+99,_xlfn.MINIFS(总表!$S$2:$S$235,总表!$T$2:$T$235,$F7,总表!$E$2:$E$235,$G7,总表!$C$2:$C$235,"典当／胎借",总表!$S$2:$S$235,">0")),IF(COUNTIFS(总表!$T$2:$T$235,$F7,总表!$E$2:$E$235,$G7,总表!$C$2:$C$235,"找贴／凑断",总表!$S$2:$S$235,">0")=0,1E+99,_xlfn.MINIFS(总表!$S$2:$S$235,总表!$T$2:$T$235,$F7,总表!$E$2:$E$235,$G7,总表!$C$2:$C$235,"找贴／凑断",总表!$S$2:$S$235,">0")),IF(COUNTIFS(总表!$T$2:$T$235,$F7,总表!$E$2:$E$235,$G7,总表!$C$2:$C$235,"典＋找贴",总表!$S$2:$S$235,">0")=0,1E+99,_xlfn.MINIFS(总表!$S$2:$S$235,总表!$T$2:$T$235,$F7,总表!$E$2:$E$235,$G7,总表!$C$2:$C$235,"典＋找贴",总表!$S$2:$S$235,">0")))) -> 8 | K7: =IF(H7=0,"—",MAX(_xlfn.MAXIFS(总表!$S$2:$S$235,总表!$T$2:$T$235,$F7,总表!$E$2:$E$235,$G7,总表!$C$2:$C$235,"买卖（卖／卖断）",总表!$S$2:$S$235,">0"),_xlfn.MAXIFS(总表!$S$2:$S$235,总表!$T$2:$T$235,$F7,总表!$E$2:$E$235,$G7,总表!$C$2:$C$235,"典当／胎借",总表!$S$2:$S$235,">0"),_xlfn.MAXIFS(总表!$S$2:$S$235,总表!$T$2:$T$235,$F7,总表!$E$2:$E$235,$G7,总表!$C$2:$C$235,"找贴／凑断",总表!$S$2:$S$235,">0"),_xlfn.MAXIFS(总表!$S$2:$S$235,总表!$T$2:$T$235,$F7,总表!$E$2:$E$235,$G7,总表!$C$2:$C$235,"典＋找贴",总表!$S$2:$S$235,">0"))) -> 310
A8: 粮单／税单 | B8: =COUNTIF(总表!$C$2:$C$235,A8) -> 25 | C8: =IFERROR(B8/COUNTA(总表!$AI$2:$AI$235),0) -> 0.10683761 | F8: 银两 | G8: 4 咸同光宣（1851-1911） | H8: =SUMPRODUCT(COUNTIFS(总表!$T$2:$T$235,$F8,总表!$E$2:$E$235,$G8,总表!$C$2:$C$235,{"买卖（卖／卖断）","典当／胎借","找贴／凑断","典＋找贴"},总表!$S$2:$S$235,">0")) -> 32 | I8: =IFERROR(SUMPRODUCT(SUMIFS(总表!$S$2:$S$235,总表!$T$2:$T$235,$F8,总表!$E$2:$E$235,$G8,总表!$C$2:$C$235,{"买卖（卖／卖断）","典当／胎借","找贴／凑断","典＋找贴"},总表!$S$2:$S$235,">0"))/H8,"—") -> 49.125 | J8: =IF(H8=0,"—",MIN(IF(COUNTIFS(总表!$T$2:$T$235,$F8,总表!$E$2:$E$235,$G8,总表!$C$2:$C$235,"买卖（卖／卖断）",总表!$S$2:$S$235,">0")=0,1E+99,_xlfn.MINIFS(总表!$S$2:$S$235,总表!$T$2:$T$235,$F8,总表!$E$2:$E$235,$G8,总表!$C$2:$C$235,"买卖（卖／卖断）",总表!$S$2:$S$235,">0")),IF(COUNTIFS(总表!$T$2:$T$235,$F8,总表!$E$2:$E$235,$G8,总表!$C$2:$C$235,"典当／胎借",总表!$S$2:$S$235,">0")=0,1E+99,_xlfn.MINIFS(总表!$S$2:$S$235,总表!$T$2:$T$235,$F8,总表!$E$2:$E$235,$G8,总表!$C$2:$C$235,"典当／胎借",总表!$S$2:$S$235,">0")),IF(COUNTIFS(总表!$T$2:$T$235,$F8,总表!$E$2:$E$235,$G8,总表!$C$2:$C$235,"找贴／凑断",总表!$S$2:$S$235,">0")=0,1E+99,_xlfn.MINIFS(总表!$S$2:$S$235,总表!$T$2:$T$235,$F8,总表!$E$2:$E$235,$G8,总表!$C$2:$C$235,"找贴／凑断",总表!$S$2:$S$235,">0")),IF(COUNTIFS(总表!$T$2:$T$235,$F8,总表!$E$2:$E$235,$G8,总表!$C$2:$C$235,"典＋找贴",总表!$S$2:$S$235,">0")=0,1E+99,_xlfn.MINIFS(总表!$S$2:$S$235,总表!$T$2:$T$235,$F8,总表!$E$2:$E$235,$G8,总表!$C$2:$C$235,"典＋找贴",总表!$S$2:$S$235,">0")))) -> 8.25 | K8: =IF(H8=0,"—",MAX(_xlfn.MAXIFS(总表!$S$2:$S$235,总表!$T$2:$T$235,$F8,总表!$E$2:$E$235,$G8,总表!$C$2:$C$235,"买卖（卖／卖断）",总表!$S$2:$S$235,">0"),_xlfn.MAXIFS(总表!$S$2:$S$235,总表!$T$2:$T$235,$F8,总表!$E$2:$E$235,$G8,总表!$C$2:$C$235,"典当／胎借",总表!$S$2:$S$235,">0"),_xlfn.MAXIFS(总表!$S$2:$S$235,总表!$T$2:$T$235,$F8,总表!$E$2:$E$235,$G8,总表!$C$2:$C$235,"找贴／凑断",总表!$S$2:$S$235,">0"),_xlfn.MAXIFS(总表!$S$2:$S$235,总表!$T$2:$T$235,$F8,总表!$E$2:$E$235,$G8,总表!$C$2:$C$235,"典＋找贴",总表!$S$2:$S$235,">0"))) -> 283.5
A9: 官方产权证照 | B9: =COUNTIF(总表!$C$2:$C$235,A9) -> 25 | C9: =IFERROR(B9/COUNTA(总表!$AI$2:$AI$235),0) -> 0.10683761 | F9: 银两 | G9: 5 北洋（1912-1927） | H9: =SUMPRODUCT(COUNTIFS(总表!$T$2:$T$235,$F9,总表!$E$2:$E$235,$G9,总表!$C$2:$C$235,{"买卖（卖／卖断）","典当／胎借","找贴／凑断","典＋找贴"},总表!$S$2:$S$235,">0")) -> 2 | I9: =IFERROR(SUMPRODUCT(SUMIFS(总表!$S$2:$S$235,总表!$T$2:$T$235,$F9,总表!$E$2:$E$235,$G9,总表!$C$2:$C$235,{"买卖（卖／卖断）","典当／胎借","找贴／凑断","典＋找贴"},总表!$S$2:$S$235,">0"))/H9,"—") -> 32 | J9: =IF(H9=0,"—",MIN(IF(COUNTIFS(总表!$T$2:$T$235,$F9,总表!$E$2:$E$235,$G9,总表!$C$2:$C$235,"买卖（卖／卖断）",总表!$S$2:$S$235,">0")=0,1E+99,_xlfn.MINIFS(总表!$S$2:$S$235,总表!$T$2:$T$235,$F9,总表!$E$2:$E$235,$G9,总表!$C$2:$C$235,"买卖（卖／卖断）",总表!$S$2:$S$235,">0")),IF(COUNTIFS(总表!$T$2:$T$235,$F9,总表!$E$2:$E$235,$G9,总表!$C$2:$C$235,"典当／胎借",总表!$S$2:$S$235,">0")=0,1E+99,_xlfn.MINIFS(总表!$S$2:$S$235,总表!$T$2:$T$235,$F9,总表!$E$2:$E$235,$G9,总表!$C$2:$C$235,"典当／胎借",总表!$S$2:$S$235,">0")),IF(COUNTIFS(总表!$T$2:$T$235,$F9,总表!$E$2:$E$235,$G9,总表!$C$2:$C$235,"找贴／凑断",总表!$S$2:$S$235,">0")=0,1E+99,_xlfn.MINIFS(总表!$S$2:$S$235,总表!$T$2:$T$235,$F9,总表!$E$2:$E$235,$G9,总表!$C$2:$C$235,"找贴／凑断",总表!$S$2:$S$235,">0")),IF(COUNTIFS(总表!$T$2:$T$235,$F9,总表!$E$2:$E$235,$G9,总表!$C$2:$C$235,"典＋找贴",总表!$S$2:$S$235,">0")=0,1E+99,_xlfn.MINIFS(总表!$S$2:$S$235,总表!$T$2:$T$235,$F9,总表!$E$2:$E$235,$G9,总表!$C$2:$C$235,"典＋找贴",总表!$S$2:$S$235,">0")))) -> 24 | K9: =IF(H9=0,"—",MAX(_xlfn.MAXIFS(总表!$S$2:$S$235,总表!$T$2:$T$235,$F9,总表!$E$2:$E$235,$G9,总表!$C$2:$C$235,"买卖（卖／卖断）",总表!$S$2:$S$235,">0"),_xlfn.MAXIFS(总表!$S$2:$S$235,总表!$T$2:$T$235,$F9,总表!$E$2:$E$235,$G9,总表!$C$2:$C$235,"典当／胎借",总表!$S$2:$S$235,">0"),_xlfn.MAXIFS(总表!$S$2:$S$235,总表!$T$2:$T$235,$F9,总表!$E$2:$E$235,$G9,总表!$C$2:$C$235,"找贴／凑断",总表!$S$2:$S$235,">0"),_xlfn.MAXIFS(总表!$S$2:$S$235,总表!$T$2:$T$235,$F9,总表!$E$2:$E$235,$G9,总表!$C$2:$C$235,"典＋找贴",总表!$S$2:$S$235,">0"))) -> 40
A10: 找贴／凑断 | B10: =COUNTIF(总表!$C$2:$C$235,A10) -> 14 | C10: =IFERROR(B10/COUNTA(总表!$AI$2:$AI$235),0) -> 0.05982906 | F10: 银两 | G10: 6 南京国民政府（1928-1948） | H10: =SUMPRODUCT(COUNTIFS(总表!$T$2:$T$235,$F10,总表!$E$2:$E$235,$G10,总表!$C$2:$C$235,{"买卖（卖／卖断）","典当／胎借","找贴／凑断","典＋找贴"},总表!$S$2:$S$235,">0")) -> 1 | I10: =IFERROR(SUMPRODUCT(SUMIFS(总表!$S$2:$S$235,总表!$T$2:$T$235,$F10,总表!$E$2:$E$235,$G10,总表!$C$2:$C$235,{"买卖（卖／卖断）","典当／胎借","找贴／凑断","典＋找贴"},总表!$S$2:$S$235,">0"))/H10,"—") -> 150 | J10: =IF(H10=0,"—",MIN(IF(COUNTIFS(总表!$T$2:$T$235,$F10,总表!$E$2:$E$235,$G10,总表!$C$2:$C$235,"买卖（卖／卖断）",总表!$S$2:$S$235,">0")=0,1E+99,_xlfn.MINIFS(总表!$S$2:$S$235,总表!$T$2:$T$235,$F10,总表!$E$2:$E$235,$G10,总表!$C$2:$C$235,"买卖（卖／卖断）",总表!$S$2:$S$235,">0")),IF(COUNTIFS(总表!$T$2:$T$235,$F10,总表!$E$2:$E$235,$G10,总表!$C$2:$C$235,"典当／胎借",总表!$S$2:$S$235,">0")=0,1E+99,_xlfn.MINIFS(总表!$S$2:$S$235,总表!$T$2:$T$235,$F10,总表!$E$2:$E$235,$G10,总表!$C$2:$C$235,"典当／胎借",总表!$S$2:$S$235,">0")),IF(COUNTIFS(总表!$T$2:$T$235,$F10,总表!$E$2:$E$235,$G10,总表!$C$2:$C$235,"找贴／凑断",总表!$S$2:$S$235,">0")=0,1E+99,_xlfn.MINIFS(总表!$S$2:$S$235,总表!$T$2:$T$235,$F10,总表!$E$2:$E$235,$G10,总表!$C$2:$C$235,"找贴／凑断",总表!$S$2:$S$235,">0")),IF(COUNTIFS(总表!$T$2:$T$235,$F10,总表!$E$2:$E$235,$G10,总表!$C$2:$C$235,"典＋找贴",总表!$S$2:$S$235,">0")=0,1E+99,_xlfn.MINIFS(总表!$S$2:$S$235,总表!$T$2:$T$235,$F10,总表!$E$2:$E$235,$G10,总表!$C$2:$C$235,"典＋找贴",总表!$S$2:$S$235,">0")))) -> 150 | K10: =IF(H10=0,"—",MAX(_xlfn.MAXIFS(总表!$S$2:$S$235,总表!$T$2:$T$235,$F10,总表!$E$2:$E$235,$G10,总表!$C$2:$C$235,"买卖（卖／卖断）",总表!$S$2:$S$235,">0"),_xlfn.MAXIFS(总表!$S$2:$S$235,总表!$T$2:$T$235,$F10,总表!$E$2:$E$235,$G10,总表!$C$2:$C$235,"典当／胎借",总表!$S$2:$S$235,">0"),_xlfn.MAXIFS(总表!$S$2:$S$235,总表!$T$2:$T$235,$F10,总表!$E$2:$E$235,$G10,总表!$C$2:$C$235,"找贴／凑断",总表!$S$2:$S$235,">0"),_xlfn.MAXIFS(总表!$S$2:$S$235,总表!$T$2:$T$235,$F10,总表!$E$2:$E$235,$G10,总表!$C$2:$C$235,"典＋找贴",总表!$S$2:$S$235,">0"))) -> 150
A11: 其他 | B11: =COUNTIF(总表!$C$2:$C$235,A11) -> 12 | C11: =IFERROR(B11/COUNTA(总表!$AI$2:$AI$235),0) -> 0.051282051 | F11: 银元／大洋 | G11: 4 咸同光宣（1851-1911） | H11: =SUMPRODUCT(COUNTIFS(总表!$T$2:$T$235,$F11,总表!$E$2:$E$235,$G11,总表!$C$2:$C$235,{"买卖（卖／卖断）","典当／胎借","找贴／凑断","典＋找贴"},总表!$S$2:$S$235,">0")) -> 7 | I11: =IFERROR(SUMPRODUCT(SUMIFS(总表!$S$2:$S$235,总表!$T$2:$T$235,$F11,总表!$E$2:$E$235,$G11,总表!$C$2:$C$235,{"买卖（卖／卖断）","典当／胎借","找贴／凑断","典＋找贴"},总表!$S$2:$S$235,">0"))/H11,"—") -> 15.178571 | J11: =IF(H11=0,"—",MIN(IF(COUNTIFS(总表!$T$2:$T$235,$F11,总表!$E$2:$E$235,$G11,总表!$C$2:$C$235,"买卖（卖／卖断）",总表!$S$2:$S$235,">0")=0,1E+99,_xlfn.MINIFS(总表!$S$2:$S$235,总表!$T$2:$T$235,$F11,总表!$E$2:$E$235,$G11,总表!$C$2:$C$235,"买卖（卖／卖断）",总表!$S$2:$S$235,">0")),IF(COUNTIFS(总表!$T$2:$T$235,$F11,总表!$E$2:$E$235,$G11,总表!$C$2:$C$235,"典当／胎借",总表!$S$2:$S$235,">0")=0,1E+99,_xlfn.MINIFS(总表!$S$2:$S$235,总表!$T$2:$T$235,$F11,总表!$E$2:$E$235,$G11,总表!$C$2:$C$235,"典当／胎借",总表!$S$2:$S$235,">0")),IF(COUNTIFS(总表!$T$2:$T$235,$F11,总表!$E$2:$E$235,$G11,总表!$C$2:$C$235,"找贴／凑断",总表!$S$2:$S$235,">0")=0,1E+99,_xlfn.MINIFS(总表!$S$2:$S$235,总表!$T$2:$T$235,$F11,总表!$E$2:$E$235,$G11,总表!$C$2:$C$235,"找贴／凑断",总表!$S$2:$S$235,">0")),IF(COUNTIFS(总表!$T$2:$T$235,$F11,总表!$E$2:$E$235,$G11,总表!$C$2:$C$235,"典＋找贴",总表!$S$2:$S$235,">0")=0,1E+99,_xlfn.MINIFS(总表!$S$2:$S$235,总表!$T$2:$T$235,$F11,总表!$E$2:$E$235,$G11,总表!$C$2:$C$235,"典＋找贴",总表!$S$2:$S$235,">0")))) -> 2.25 | K11: =IF(H11=0,"—",MAX(_xlfn.MAXIFS(总表!$S$2:$S$235,总表!$T$2:$T$235,$F11,总表!$E$2:$E$235,$G11,总表!$C$2:$C$235,"买卖（卖／卖断）",总表!$S$2:$S$235,">0"),_xlfn.MAXIFS(总表!$S$2:$S$235,总表!$T$2:$T$235,$F11,总表!$E$2:$E$235,$G11,总表!$C$2:$C$235,"典当／胎借",总表!$S$2:$S$235,">0"),_xlfn.MAXIFS(总表!$S$2:$S$235,总表!$T$2:$T$235,$F11,总表!$E$2:$E$235,$G11,总表!$C$2:$C$235,"找贴／凑断",总表!$S$2:$S$235,">0"),_xlfn.MAXIFS(总表!$S$2:$S$235,总表!$T$2:$T$235,$F11,总表!$E$2:$E$235,$G11,总表!$C$2:$C$235,"典＋找贴",总表!$S$2:$S$235,">0"))) -> 60
A12: 租佃／欠租 | B12: =COUNTIF(总表!$C$2:$C$235,A12) -> 5 | C12: =IFERROR(B12/COUNTA(总表!$AI$2:$AI$235),0) -> 0.021367521 | F12: 银元／大洋 | G12: 5 北洋（1912-1927） | H12: =SUMPRODUCT(COUNTIFS(总表!$T$2:$T$235,$F12,总表!$E$2:$E$235,$G12,总表!$C$2:$C$235,{"买卖（卖／卖断）","典当／胎借","找贴／凑断","典＋找贴"},总表!$S$2:$S$235,">0")) -> 10 | I12: =IFERROR(SUMPRODUCT(SUMIFS(总表!$S$2:$S$235,总表!$T$2:$T$235,$F12,总表!$E$2:$E$235,$G12,总表!$C$2:$C$235,{"买卖（卖／卖断）","典当／胎借","找贴／凑断","典＋找贴"},总表!$S$2:$S$235,">0"))/H12,"—") -> 226.4 | J12: =IF(H12=0,"—",MIN(IF(COUNTIFS(总表!$T$2:$T$235,$F12,总表!$E$2:$E$235,$G12,总表!$C$2:$C$235,"买卖（卖／卖断）",总表!$S$2:$S$235,">0")=0,1E+99,_xlfn.MINIFS(总表!$S$2:$S$235,总表!$T$2:$T$235,$F12,总表!$E$2:$E$235,$G12,总表!$C$2:$C$235,"买卖（卖／卖断）",总表!$S$2:$S$235,">0")),IF(COUNTIFS(总表!$T$2:$T$235,$F12,总表!$E$2:$E$235,$G12,总表!$C$2:$C$235,"典当／胎借",总表!$S$2:$S$235,">0")=0,1E+99,_xlfn.MINIFS(总表!$S$2:$S$235,总表!$T$2:$T$235,$F12,总表!$E$2:$E$235,$G12,总表!$C$2:$C$235,"典当／胎借",总表!$S$2:$S$235,">0")),IF(COUNTIFS(总表!$T$2:$T$235,$F12,总表!$E$2:$E$235,$G12,总表!$C$2:$C$235,"找贴／凑断",总表!$S$2:$S$235,">0")=0,1E+99,_xlfn.MINIFS(总表!$S$2:$S$235,总表!$T$2:$T$235,$F12,总表!$E$2:$E$235,$G12,总表!$C$2:$C$235,"找贴／凑断",总表!$S$2:$S$235,">0")),IF(COUNTIFS(总表!$T$2:$T$235,$F12,总表!$E$2:$E$235,$G12,总表!$C$2:$C$235,"典＋找贴",总表!$S$2:$S$235,">0")=0,1E+99,_xlfn.MINIFS(总表!$S$2:$S$235,总表!$T$2:$T$235,$F12,总表!$E$2:$E$235,$G12,总表!$C$2:$C$235,"典＋找贴",总表!$S$2:$S$235,">0")))) -> 28 | K12: =IF(H12=0,"—",MAX(_xlfn.MAXIFS(总表!$S$2:$S$235,总表!$T$2:$T$235,$F12,总表!$E$2:$E$235,$G12,总表!$C$2:$C$235,"买卖（卖／卖断）",总表!$S$2:$S$235,">0"),_xlfn.MAXIFS(总表!$S$2:$S$235,总表!$T$2:$T$235,$F12,总表!$E$2:$E$235,$G12,总表!$C$2:$C$235,"典当／胎借",总表!$S$2:$S$235,">0"),_xlfn.MAXIFS(总表!$S$2:$S$235,总表!$T$2:$T$235,$F12,总表!$E$2:$E$235,$G12,总表!$C$2:$C$235,"找贴／凑断",总表!$S$2:$S$235,">0"),_xlfn.MAXIFS(总表!$S$2:$S$235,总表!$T$2:$T$235,$F12,总表!$E$2:$E$235,$G12,总表!$C$2:$C$235,"典＋找贴",总表!$S$2:$S$235,">0"))) -> 721
A13: 分家书 | B13: =COUNTIF(总表!$C$2:$C$235,A13) -> 3 | C13: =IFERROR(B13/COUNTA(总表!$AI$2:$AI$235),0) -> 0.012820513 | F13: 银元／大洋 | G13: 6 南京国民政府（1928-1948） | H13: =SUMPRODUCT(COUNTIFS(总表!$T$2:$T$235,$F13,总表!$E$2:$E$235,$G13,总表!$C$2:$C$235,{"买卖（卖／卖断）","典当／胎借","找贴／凑断","典＋找贴"},总表!$S$2:$S$235,">0")) -> 11 | I13: =IFERROR(SUMPRODUCT(SUMIFS(总表!$S$2:$S$235,总表!$T$2:$T$235,$F13,总表!$E$2:$E$235,$G13,总表!$C$2:$C$235,{"买卖（卖／卖断）","典当／胎借","找贴／凑断","典＋找贴"},总表!$S$2:$S$235,">0"))/H13,"—") -> 130.36364 | J13: =IF(H13=0,"—",MIN(IF(COUNTIFS(总表!$T$2:$T$235,$F13,总表!$E$2:$E$235,$G13,总表!$C$2:$C$235,"买卖（卖／卖断）",总表!$S$2:$S$235,">0")=0,1E+99,_xlfn.MINIFS(总表!$S$2:$S$235,总表!$T$2:$T$235,$F13,总表!$E$2:$E$235,$G13,总表!$C$2:$C$235,"买卖（卖／卖断）",总表!$S$2:$S$235,">0")),IF(COUNTIFS(总表!$T$2:$T$235,$F13,总表!$E$2:$E$235,$G13,总表!$C$2:$C$235,"典当／胎借",总表!$S$2:$S$235,">0")=0,1E+99,_xlfn.MINIFS(总表!$S$2:$S$235,总表!$T$2:$T$235,$F13,总表!$E$2:$E$235,$G13,总表!$C$2:$C$235,"典当／胎借",总表!$S$2:$S$235,">0")),IF(COUNTIFS(总表!$T$2:$T$235,$F13,总表!$E$2:$E$235,$G13,总表!$C$2:$C$235,"找贴／凑断",总表!$S$2:$S$235,">0")=0,1E+99,_xlfn.MINIFS(总表!$S$2:$S$235,总表!$T$2:$T$235,$F13,总表!$E$2:$E$235,$G13,总表!$C$2:$C$235,"找贴／凑断",总表!$S$2:$S$235,">0")),IF(COUNTIFS(总表!$T$2:$T$235,$F13,总表!$E$2:$E$235,$G13,总表!$C$2:$C$235,"典＋找贴",总表!$S$2:$S$235,">0")=0,1E+99,_xlfn.MINIFS(总表!$S$2:$S$235,总表!$T$2:$T$235,$F13,总表!$E$2:$E$235,$G13,总表!$C$2:$C$235,"典＋找贴",总表!$S$2:$S$235,">0")))) -> 30 | K13: =IF(H13=0,"—",MAX(_xlfn.MAXIFS(总表!$S$2:$S$235,总表!$T$2:$T$235,$F13,总表!$E$2:$E$235,$G13,总表!$C$2:$C$235,"买卖（卖／卖断）",总表!$S$2:$S$235,">0"),_xlfn.MAXIFS(总表!$S$2:$S$235,总表!$T$2:$T$235,$F13,总表!$E$2:$E$235,$G13,总表!$C$2:$C$235,"典当／胎借",总表!$S$2:$S$235,">0"),_xlfn.MAXIFS(总表!$S$2:$S$235,总表!$T$2:$T$235,$F13,总表!$E$2:$E$235,$G13,总表!$C$2:$C$235,"找贴／凑断",总表!$S$2:$S$235,">0"),_xlfn.MAXIFS(总表!$S$2:$S$235,总表!$T$2:$T$235,$F13,总表!$E$2:$E$235,$G13,总表!$C$2:$C$235,"典＋找贴",总表!$S$2:$S$235,">0"))) -> 240
A14: 合同／约字 | B14: =COUNTIF(总表!$C$2:$C$235,A14) -> 3 | C14: =IFERROR(B14/COUNTA(总表!$AI$2:$AI$235),0) -> 0.012820513 | F14: 银元／大洋 | G14: 7 1949 以后 | H14: =SUMPRODUCT(COUNTIFS(总表!$T$2:$T$235,$F14,总表!$E$2:$E$235,$G14,总表!$C$2:$C$235,{"买卖（卖／卖断）","典当／胎借","找贴／凑断","典＋找贴"},总表!$S$2:$S$235,">0")) -> 1 | I14: =IFERROR(SUMPRODUCT(SUMIFS(总表!$S$2:$S$235,总表!$T$2:$T$235,$F14,总表!$E$2:$E$235,$G14,总表!$C$2:$C$235,{"买卖（卖／卖断）","典当／胎借","找贴／凑断","典＋找贴"},总表!$S$2:$S$235,">0"))/H14,"—") -> 30 | J14: =IF(H14=0,"—",MIN(IF(COUNTIFS(总表!$T$2:$T$235,$F14,总表!$E$2:$E$235,$G14,总表!$C$2:$C$235,"买卖（卖／卖断）",总表!$S$2:$S$235,">0")=0,1E+99,_xlfn.MINIFS(总表!$S$2:$S$235,总表!$T$2:$T$235,$F14,总表!$E$2:$E$235,$G14,总表!$C$2:$C$235,"买卖（卖／卖断）",总表!$S$2:$S$235,">0")),IF(COUNTIFS(总表!$T$2:$T$235,$F14,总表!$E$2:$E$235,$G14,总表!$C$2:$C$235,"典当／胎借",总表!$S$2:$S$235,">0")=0,1E+99,_xlfn.MINIFS(总表!$S$2:$S$235,总表!$T$2:$T$235,$F14,总表!$E$2:$E$235,$G14,总表!$C$2:$C$235,"典当／胎借",总表!$S$2:$S$235,">0")),IF(COUNTIFS(总表!$T$2:$T$235,$F14,总表!$E$2:$E$235,$G14,总表!$C$2:$C$235,"找贴／凑断",总表!$S$2:$S$235,">0")=0,1E+99,_xlfn.MINIFS(总表!$S$2:$S$235,总表!$T$2:$T$235,$F14,总表!$E$2:$E$235,$G14,总表!$C$2:$C$235,"找贴／凑断",总表!$S$2:$S$235,">0")),IF(COUNTIFS(总表!$T$2:$T$235,$F14,总表!$E$2:$E$235,$G14,总表!$C$2:$C$235,"典＋找贴",总表!$S$2:$S$235,">0")=0,1E+99,_xlfn.MINIFS(总表!$S$2:$S$235,总表!$T$2:$T$235,$F14,总表!$E$2:$E$235,$G14,总表!$C$2:$C$235,"典＋找贴",总表!$S$2:$S$235,">0")))) -> 30 | K14: =IF(H14=0,"—",MAX(_xlfn.MAXIFS(总表!$S$2:$S$235,总表!$T$2:$T$235,$F14,总表!$E$2:$E$235,$G14,总表!$C$2:$C$235,"买卖（卖／卖断）",总表!$S$2:$S$235,">0"),_xlfn.MAXIFS(总表!$S$2:$S$235,总表!$T$2:$T$235,$F14,总表!$E$2:$E$235,$G14,总表!$C$2:$C$235,"典当／胎借",总表!$S$2:$S$235,">0"),_xlfn.MAXIFS(总表!$S$2:$S$235,总表!$T$2:$T$235,$F14,总表!$E$2:$E$235,$G14,总表!$C$2:$C$235,"找贴／凑断",总表!$S$2:$S$235,">0"),_xlfn.MAXIFS(总表!$S$2:$S$235,总表!$T$2:$T$235,$F14,总表!$E$2:$E$235,$G14,总表!$C$2:$C$235,"典＋找贴",总表!$S$2:$S$235,">0"))) -> 30
A15: 典＋找贴 | B15: =COUNTIF(总表!$C$2:$C$235,A15) -> 2 | C15: =IFERROR(B15/COUNTA(总表!$AI$2:$AI$235),0) -> 0.0085470085 | F15: 铜钱 | G15: 3 嘉道（1796-1850） | H15: =SUMPRODUCT(COUNTIFS(总表!$T$2:$T$235,$F15,总表!$E$2:$E$235,$G15,总表!$C$2:$C$235,{"买卖（卖／卖断）","典当／胎借","找贴／凑断","典＋找贴"},总表!$S$2:$S$235,">0")) -> 1 | I15: =IFERROR(SUMPRODUCT(SUMIFS(总表!$S$2:$S$235,总表!$T$2:$T$235,$F15,总表!$E$2:$E$235,$G15,总表!$C$2:$C$235,{"买卖（卖／卖断）","典当／胎借","找贴／凑断","典＋找贴"},总表!$S$2:$S$235,">0"))/H15,"—") -> 11500 | J15: =IF(H15=0,"—",MIN(IF(COUNTIFS(总表!$T$2:$T$235,$F15,总表!$E$2:$E$235,$G15,总表!$C$2:$C$235,"买卖（卖／卖断）",总表!$S$2:$S$235,">0")=0,1E+99,_xlfn.MINIFS(总表!$S$2:$S$235,总表!$T$2:$T$235,$F15,总表!$E$2:$E$235,$G15,总表!$C$2:$C$235,"买卖（卖／卖断）",总表!$S$2:$S$235,">0")),IF(COUNTIFS(总表!$T$2:$T$235,$F15,总表!$E$2:$E$235,$G15,总表!$C$2:$C$235,"典当／胎借",总表!$S$2:$S$235,">0")=0,1E+99,_xlfn.MINIFS(总表!$S$2:$S$235,总表!$T$2:$T$235,$F15,总表!$E$2:$E$235,$G15,总表!$C$2:$C$235,"典当／胎借",总表!$S$2:$S$235,">0")),IF(COUNTIFS(总表!$T$2:$T$235,$F15,总表!$E$2:$E$235,$G15,总表!$C$2:$C$235,"找贴／凑断",总表!$S$2:$S$235,">0")=0,1E+99,_xlfn.MINIFS(总表!$S$2:$S$235,总表!$T$2:$T$235,$F15,总表!$E$2:$E$235,$G15,总表!$C$2:$C$235,"找贴／凑断",总表!$S$2:$S$235,">0")),IF(COUNTIFS(总表!$T$2:$T$235,$F15,总表!$E$2:$E$235,$G15,总表!$C$2:$C$235,"典＋找贴",总表!$S$2:$S$235,">0")=0,1E+99,_xlfn.MINIFS(总表!$S$2:$S$235,总表!$T$2:$T$235,$F15,总表!$E$2:$E$235,$G15,总表!$C$2:$C$235,"典＋找贴",总表!$S$2:$S$235,">0")))) -> 11500 | K15: =IF(H15=0,"—",MAX(_xlfn.MAXIFS(总表!$S$2:$S$235,总表!$T$2:$T$235,$F15,总表!$E$2:$E$235,$G15,总表!$C$2:$C$235,"买卖（卖／卖断）",总表!$S$2:$S$235,">0"),_xlfn.MAXIFS(总表!$S$2:$S$235,总表!$T$2:$T$235,$F15,总表!$E$2:$E$235,$G15,总表!$C$2:$C$235,"典当／胎借",总表!$S$2:$S$235,">0"),_xlfn.MAXIFS(总表!$S$2:$S$235,总表!$T$2:$T$235,$F15,总表!$E$2:$E$235,$G15,总表!$C$2:$C$235,"找贴／凑断",总表!$S$2:$S$235,">0"),_xlfn.MAXIFS(总表!$S$2:$S$235,总表!$T$2:$T$235,$F15,总表!$E$2:$E$235,$G15,总表!$C$2:$C$235,"典＋找贴",总表!$S$2:$S$235,">0"))) -> 11500
A16: 合计 | B16: =SUM(B5:B15) -> 234 | C16: =SUM(C5:C15) -> 1 | F16: 铜钱 | G16: 4 咸同光宣（1851-1911） | H16: =SUMPRODUCT(COUNTIFS(总表!$T$2:$T$235,$F16,总表!$E$2:$E$235,$G16,总表!$C$2:$C$235,{"买卖（卖／卖断）","典当／胎借","找贴／凑断","典＋找贴"},总表!$S$2:$S$235,">0")) -> 11 | I16: =IFERROR(SUMPRODUCT(SUMIFS(总表!$S$2:$S$235,总表!$T$2:$T$235,$F16,总表!$E$2:$E$235,$G16,总表!$C$2:$C$235,{"买卖（卖／卖断）","典当／胎借","找贴／凑断","典＋找贴"},总表!$S$2:$S$235,">0"))/H16,"—") -> 73418.182 | J16: =IF(H16=0,"—",MIN(IF(COUNTIFS(总表!$T$2:$T$235,$F16,总表!$E$2:$E$235,$G16,总表!$C$2:$C$235,"买卖（卖／卖断）",总表!$S$2:$S$235,">0")=0,1E+99,_xlfn.MINIFS(总表!$S$2:$S$235,总表!$T$2:$T$235,$F16,总表!$E$2:$E$235,$G16,总表!$C$2:$C$235,"买卖（卖／卖断）",总表!$S$2:$S$235,">0")),IF(COUNTIFS(总表!$T$2:$T$235,$F16,总表!$E$2:$E$235,$G16,总表!$C$2:$C$235,"典当／胎借",总表!$S$2:$S$235,">0")=0,1E+99,_xlfn.MINIFS(总表!$S$2:$S$235,总表!$T$2:$T$235,$F16,总表!$E$2:$E$235,$G16,总表!$C$2:$C$235,"典当／胎借",总表!$S$2:$S$235,">0")),IF(COUNTIFS(总表!$T$2:$T$235,$F16,总表!$E$2:$E$235,$G16,总表!$C$2:$C$235,"找贴／凑断",总表!$S$2:$S$235,">0")=0,1E+99,_xlfn.MINIFS(总表!$S$2:$S$235,总表!$T$2:$T$235,$F16,总表!$E$2:$E$235,$G16,总表!$C$2:$C$235,"找贴／凑断",总表!$S$2:$S$235,">0")),IF(COUNTIFS(总表!$T$2:$T$235,$F16,总表!$E$2:$E$235,$G16,总表!$C$2:$C$235,"典＋找贴",总表!$S$2:$S$235,">0")=0,1E+99,_xlfn.MINIFS(总表!$S$2:$S$235,总表!$T$2:$T$235,$F16,总表!$E$2:$E$235,$G16,总表!$C$2:$C$235,"典＋找贴",总表!$S$2:$S$235,">0")))) -> 2000 | K16: =IF(H16=0,"—",MAX(_xlfn.MAXIFS(总表!$S$2:$S$235,总表!$T$2:$T$235,$F16,总表!$E$2:$E$235,$G16,总表!$C$2:$C$235,"买卖（卖／卖断）",总表!$S$2:$S$235,">0"),_xlfn.MAXIFS(总表!$S$2:$S$235,总表!$T$2:$T$235,$F16,总表!$E$2:$E$235,$G16,总表!$C$2:$C$235,"典当／胎借",总表!$S$2:$S$235,">0"),_xlfn.MAXIFS(总表!$S$2:$S$235,总表!$T$2:$T$235,$F16,总表!$E$2:$E$235,$G16,总表!$C$2:$C$235,"找贴／凑断",总表!$S$2:$S$235,">0"),_xlfn.MAXIFS(总表!$S$2:$S$235,总表!$T$2:$T$235,$F16,总表!$E$2:$E$235,$G16,总表!$C$2:$C$235,"典＋找贴",总表!$S$2:$S$235,">0"))) -> 148000
F17: 铜钱 | G17: 5 北洋（1912-1927） | H17: =SUMPRODUCT(COUNTIFS(总表!$T$2:$T$235,$F17,总表!$E$2:$E$235,$G17,总表!$C$2:$C$235,{"买卖（卖／卖断）","典当／胎借","找贴／凑断","典＋找贴"},总表!$S$2:$S$235,">0")) -> 1 | I17: =IFERROR(SUMPRODUCT(SUMIFS(总表!$S$2:$S$235,总表!$T$2:$T$235,$F17,总表!$E$2:$E$235,$G17,总表!$C$2:$C$235,{"买卖（卖／卖断）","典当／胎借","找贴／凑断","典＋找贴"},总表!$S$2:$S$235,">0"))/H17,"—") -> 64500 | J17: =IF(H17=0,"—",MIN(IF(COUNTIFS(总表!$T$2:$T$235,$F17,总表!$E$2:$E$235,$G17,总表!$C$2:$C$235,"买卖（卖／卖断）",总表!$S$2:$S$235,">0")=0,1E+99,_xlfn.MINIFS(总表!$S$2:$S$235,总表!$T$2:$T$235,$F17,总表!$E$2:$E$235,$G17,总表!$C$2:$C$235,"买卖（卖／卖断）",总表!$S$2:$S$235,">0")),IF(COUNTIFS(总表!$T$2:$T$235,$F17,总表!$E$2:$E$235,$G17,总表!$C$2:$C$235,"典当／胎借",总表!$S$2:$S$235,">0")=0,1E+99,_xlfn.MINIFS(总表!$S$2:$S$235,总表!$T$2:$T$235,$F17,总表!$E$2:$E$235,$G17,总表!$C$2:$C$235,"典当／胎借",总表!$S$2:$S$235,">0")),IF(COUNTIFS(总表!$T$2:$T$235,$F17,总表!$E$2:$E$235,$G17,总表!$C$2:$C$235,"找贴／凑断",总表!$S$2:$S$235,">0")=0,1E+99,_xlfn.MINIFS(总表!$S$2:$S$235,总表!$T$2:$T$235,$F17,总表!$E$2:$E$235,$G17,总表!$C$2:$C$235,"找贴／凑断",总表!$S$2:$S$235,">0")),IF(COUNTIFS(总表!$T$2:$T$235,$F17,总表!$E$2:$E$235,$G17,总表!$C$2:$C$235,"典＋找贴",总表!$S$2:$S$235,">0")=0,1E+99,_xlfn.MINIFS(总表!$S$2:$S$235,总表!$T$2:$T$235,$F17,总表!$E$2:$E$235,$G17,总表!$C$2:$C$235,"典＋找贴",总表!$S$2:$S$235,">0")))) -> 64500 | K17: =IF(H17=0,"—",MAX(_xlfn.MAXIFS(总表!$S$2:$S$235,总表!$T$2:$T$235,$F17,总表!$E$2:$E$235,$G17,总表!$C$2:$C$235,"买卖（卖／卖断）",总表!$S$2:$S$235,">0"),_xlfn.MAXIFS(总表!$S$2:$S$235,总表!$T$2:$T$235,$F17,总表!$E$2:$E$235,$G17,总表!$C$2:$C$235,"典当／胎借",总表!$S$2:$S$235,">0"),_xlfn.MAXIFS(总表!$S$2:$S$235,总表!$T$2:$T$235,$F17,总表!$E$2:$E$235,$G17,总表!$C$2:$C$235,"找贴／凑断",总表!$S$2:$S$235,">0"),_xlfn.MAXIFS(总表!$S$2:$S$235,总表!$T$2:$T$235,$F17,总表!$E$2:$E$235,$G17,总表!$C$2:$C$235,"典＋找贴",总表!$S$2:$S$235,">0"))) -> 64500
A18: 二、时期 | F18: 铜钱 | G18: 6 南京国民政府（1928-1948） | H18: =SUMPRODUCT(COUNTIFS(总表!$T$2:$T$235,$F18,总表!$E$2:$E$235,$G18,总表!$C$2:$C$235,{"买卖（卖／卖断）","典当／胎借","找贴／凑断","典＋找贴"},总表!$S$2:$S$235,">0")) -> 3 | I18: =IFERROR(SUMPRODUCT(SUMIFS(总表!$S$2:$S$235,总表!$T$2:$T$235,$F18,总表!$E$2:$E$235,$G18,总表!$C$2:$C$235,{"买卖（卖／卖断）","典当／胎借","找贴／凑断","典＋找贴"},总表!$S$2:$S$235,">0"))/H18,"—") -> 34366.667 | J18: =IF(H18=0,"—",MIN(IF(COUNTIFS(总表!$T$2:$T$235,$F18,总表!$E$2:$E$235,$G18,总表!$C$2:$C$235,"买卖（卖／卖断）",总表!$S$2:$S$235,">0")=0,1E+99,_xlfn.MINIFS(总表!$S$2:$S$235,总表!$T$2:$T$235,$F18,总表!$E$2:$E$235,$G18,总表!$C$2:$C$235,"买卖（卖／卖断）",总表!$S$2:$S$235,">0")),IF(COUNTIFS(总表!$T$2:$T$235,$F18,总表!$E$2:$E$235,$G18,总表!$C$2:$C$235,"典当／胎借",总表!$S$2:$S$235,">0")=0,1E+99,_xlfn.MINIFS(总表!$S$2:$S$235,总表!$T$2:$T$235,$F18,总表!$E$2:$E$235,$G18,总表!$C$2:$C$235,"典当／胎借",总表!$S$2:$S$235,">0")),IF(COUNTIFS(总表!$T$2:$T$235,$F18,总表!$E$2:$E$235,$G18,总表!$C$2:$C$235,"找贴／凑断",总表!$S$2:$S$235,">0")=0,1E+99,_xlfn.MINIFS(总表!$S$2:$S$235,总表!$T$2:$T$235,$F18,总表!$E$2:$E$235,$G18,总表!$C$2:$C$235,"找贴／凑断",总表!$S$2:$S$235,">0")),IF(COUNTIFS(总表!$T$2:$T$235,$F18,总表!$E$2:$E$235,$G18,总表!$C$2:$C$235,"典＋找贴",总表!$S$2:$S$235,">0")=0,1E+99,_xlfn.MINIFS(总表!$S$2:$S$235,总表!$T$2:$T$235,$F18,总表!$E$2:$E$235,$G18,总表!$C$2:$C$235,"典＋找贴",总表!$S$2:$S$235,">0")))) -> 11500 | K18: =IF(H18=0,"—",MAX(_xlfn.MAXIFS(总表!$S$2:$S$235,总表!$T$2:$T$235,$F18,总表!$E$2:$E$235,$G18,总表!$C$2:$C$235,"买卖（卖／卖断）",总表!$S$2:$S$235,">0"),_xlfn.MAXIFS(总表!$S$2:$S$235,总表!$T$2:$T$235,$F18,总表!$E$2:$E$235,$G18,总表!$C$2:$C$235,"典当／胎借",总表!$S$2:$S$235,">0"),_xlfn.MAXIFS(总表!$S$2:$S$235,总表!$T$2:$T$235,$F18,总表!$E$2:$E$235,$G18,总表!$C$2:$C$235,"找贴／凑断",总表!$S$2:$S$235,">0"),_xlfn.MAXIFS(总表!$S$2:$S$235,总表!$T$2:$T$235,$F18,总表!$E$2:$E$235,$G18,总表!$C$2:$C$235,"典＋找贴",总表!$S$2:$S$235,">0"))) -> 68600
A19: 类别 | B19: 件数 | C19: 占比 | F19: 番银 | G19: 3 嘉道（1796-1850） | H19: =SUMPRODUCT(COUNTIFS(总表!$T$2:$T$235,$F19,总表!$E$2:$E$235,$G19,总表!$C$2:$C$235,{"买卖（卖／卖断）","典当／胎借","找贴／凑断","典＋找贴"},总表!$S$2:$S$235,">0")) -> 1 | I19: =IFERROR(SUMPRODUCT(SUMIFS(总表!$S$2:$S$235,总表!$T$2:$T$235,$F19,总表!$E$2:$E$235,$G19,总表!$C$2:$C$235,{"买卖（卖／卖断）","典当／胎借","找贴／凑断","典＋找贴"},总表!$S$2:$S$235,">0"))/H19,"—") -> 6 | J19: =IF(H19=0,"—",MIN(IF(COUNTIFS(总表!$T$2:$T$235,$F19,总表!$E$2:$E$235,$G19,总表!$C$2:$C$235,"买卖（卖／卖断）",总表!$S$2:$S$235,">0")=0,1E+99,_xlfn.MINIFS(总表!$S$2:$S$235,总表!$T$2:$T$235,$F19,总表!$E$2:$E$235,$G19,总表!$C$2:$C$235,"买卖（卖／卖断）",总表!$S$2:$S$235,">0")),IF(COUNTIFS(总表!$T$2:$T$235,$F19,总表!$E$2:$E$235,$G19,总表!$C$2:$C$235,"典当／胎借",总表!$S$2:$S$235,">0")=0,1E+99,_xlfn.MINIFS(总表!$S$2:$S$235,总表!$T$2:$T$235,$F19,总表!$E$2:$E$235,$G19,总表!$C$2:$C$235,"典当／胎借",总表!$S$2:$S$235,">0")),IF(COUNTIFS(总表!$T$2:$T$235,$F19,总表!$E$2:$E$235,$G19,总表!$C$2:$C$235,"找贴／凑断",总表!$S$2:$S$235,">0")=0,1E+99,_xlfn.MINIFS(总表!$S$2:$S$235,总表!$T$2:$T$235,$F19,总表!$E$2:$E$235,$G19,总表!$C$2:$C$235,"找贴／凑断",总表!$S$2:$S$235,">0")),IF(COUNTIFS(总表!$T$2:$T$235,$F19,总表!$E$2:$E$235,$G19,总表!$C$2:$C$235,"典＋找贴",总表!$S$2:$S$235,">0")=0,1E+99,_xlfn.MINIFS(总表!$S$2:$S$235,总表!$T$2:$T$235,$F19,总表!$E$2:$E$235,$G19,总表!$C$2:$C$235,"典＋找贴",总表!$S$2:$S$235,">0")))) -> 6 | K19: =IF(H19=0,"—",MAX(_xlfn.MAXIFS(总表!$S$2:$S$235,总表!$T$2:$T$235,$F19,总表!$E$2:$E$235,$G19,总表!$C$2:$C$235,"买卖（卖／卖断）",总表!$S$2:$S$235,">0"),_xlfn.MAXIFS(总表!$S$2:$S$235,总表!$T$2:$T$235,$F19,总表!$E$2:$E$235,$G19,总表!$C$2:$C$235,"典当／胎借",总表!$S$2:$S$235,">0"),_xlfn.MAXIFS(总表!$S$2:$S$235,总表!$T$2:$T$235,$F19,总表!$E$2:$E$235,$G19,总表!$C$2:$C$235,"找贴／凑断",总表!$S$2:$S$235,">0"),_xlfn.MAXIFS(总表!$S$2:$S$235,总表!$T$2:$T$235,$F19,总表!$E$2:$E$235,$G19,总表!$C$2:$C$235,"典＋找贴",总表!$S$2:$S$235,">0"))) -> 6
A20: 1 明（-1643） | B20: =COUNTIF(总表!$E$2:$E$235,A20) -> 1 | C20: =IFERROR(B20/COUNTA(总表!$AI$2:$AI$235),0) -> 0.0042735043 | F20: 番银 | G20: 4 咸同光宣（1851-1911） | H20: =SUMPRODUCT(COUNTIFS(总表!$T$2:$T$235,$F20,总表!$E$2:$E$235,$G20,总表!$C$2:$C$235,{"买卖（卖／卖断）","典当／胎借","找贴／凑断","典＋找贴"},总表!$S$2:$S$235,">0")) -> 1 | I20: =IFERROR(SUMPRODUCT(SUMIFS(总表!$S$2:$S$235,总表!$T$2:$T$235,$F20,总表!$E$2:$E$235,$G20,总表!$C$2:$C$235,{"买卖（卖／卖断）","典当／胎借","找贴／凑断","典＋找贴"},总表!$S$2:$S$235,">0"))/H20,"—") -> 70 | J20: =IF(H20=0,"—",MIN(IF(COUNTIFS(总表!$T$2:$T$235,$F20,总表!$E$2:$E$235,$G20,总表!$C$2:$C$235,"买卖（卖／卖断）",总表!$S$2:$S$235,">0")=0,1E+99,_xlfn.MINIFS(总表!$S$2:$S$235,总表!$T$2:$T$235,$F20,总表!$E$2:$E$235,$G20,总表!$C$2:$C$235,"买卖（卖／卖断）",总表!$S$2:$S$235,">0")),IF(COUNTIFS(总表!$T$2:$T$235,$F20,总表!$E$2:$E$235,$G20,总表!$C$2:$C$235,"典当／胎借",总表!$S$2:$S$235,">0")=0,1E+99,_xlfn.MINIFS(总表!$S$2:$S$235,总表!$T$2:$T$235,$F20,总表!$E$2:$E$235,$G20,总表!$C$2:$C$235,"典当／胎借",总表!$S$2:$S$235,">0")),IF(COUNTIFS(总表!$T$2:$T$235,$F20,总表!$E$2:$E$235,$G20,总表!$C$2:$C$235,"找贴／凑断",总表!$S$2:$S$235,">0")=0,1E+99,_xlfn.MINIFS(总表!$S$2:$S$235,总表!$T$2:$T$235,$F20,总表!$E$2:$E$235,$G20,总表!$C$2:$C$235,"找贴／凑断",总表!$S$2:$S$235,">0")),IF(COUNTIFS(总表!$T$2:$T$235,$F20,总表!$E$2:$E$235,$G20,总表!$C$2:$C$235,"典＋找贴",总表!$S$2:$S$235,">0")=0,1E+99,_xlfn.MINIFS(总表!$S$2:$S$235,总表!$T$2:$T$235,$F20,总表!$E$2:$E$235,$G20,总表!$C$2:$C$235,"典＋找贴",总表!$S$2:$S$235,">0")))) -> 70 | K20: =IF(H20=0,"—",MAX(_xlfn.MAXIFS(总表!$S$2:$S$235,总表!$T$2:$T$235,$F20,总表!$E$2:$E$235,$G20,总表!$C$2:$C$235,"买卖（卖／卖断）",总表!$S$2:$S$235,">0"),_xlfn.MAXIFS(总表!$S$2:$S$235,总表!$T$2:$T$235,$F20,总表!$E$2:$E$235,$G20,总表!$C$2:$C$235,"典当／胎借",总表!$S$2:$S$235,">0"),_xlfn.MAXIFS(总表!$S$2:$S$235,总表!$T$2:$T$235,$F20,总表!$E$2:$E$235,$G20,总表!$C$2:$C$235,"找贴／凑断",总表!$S$2:$S$235,">0"),_xlfn.MAXIFS(总表!$S$2:$S$235,总表!$T$2:$T$235,$F20,总表!$E$2:$E$235,$G20,总表!$C$2:$C$235,"典＋找贴",总表!$S$2:$S$235,">0"))) -> 70
A21: 2 清前期（1644-1795） | B21: =COUNTIF(总表!$E$2:$E$235,A21) -> 9 | C21: =IFERROR(B21/COUNTA(总表!$AI$2:$AI$235),0) -> 0.038461538 | F21: 番银 | G21: 5 北洋（1912-1927） | H21: =SUMPRODUCT(COUNTIFS(总表!$T$2:$T$235,$F21,总表!$E$2:$E$235,$G21,总表!$C$2:$C$235,{"买卖（卖／卖断）","典当／胎借","找贴／凑断","典＋找贴"},总表!$S$2:$S$235,">0")) -> 2 | I21: =IFERROR(SUMPRODUCT(SUMIFS(总表!$S$2:$S$235,总表!$T$2:$T$235,$F21,总表!$E$2:$E$235,$G21,总表!$C$2:$C$235,{"买卖（卖／卖断）","典当／胎借","找贴／凑断","典＋找贴"},总表!$S$2:$S$235,">0"))/H21,"—") -> 112.5 | J21: =IF(H21=0,"—",MIN(IF(COUNTIFS(总表!$T$2:$T$235,$F21,总表!$E$2:$E$235,$G21,总表!$C$2:$C$235,"买卖（卖／卖断）",总表!$S$2:$S$235,">0")=0,1E+99,_xlfn.MINIFS(总表!$S$2:$S$235,总表!$T$2:$T$235,$F21,总表!$E$2:$E$235,$G21,总表!$C$2:$C$235,"买卖（卖／卖断）",总表!$S$2:$S$235,">0")),IF(COUNTIFS(总表!$T$2:$T$235,$F21,总表!$E$2:$E$235,$G21,总表!$C$2:$C$235,"典当／胎借",总表!$S$2:$S$235,">0")=0,1E+99,_xlfn.MINIFS(总表!$S$2:$S$235,总表!$T$2:$T$235,$F21,总表!$E$2:$E$235,$G21,总表!$C$2:$C$235,"典当／胎借",总表!$S$2:$S$235,">0")),IF(COUNTIFS(总表!$T$2:$T$235,$F21,总表!$E$2:$E$235,$G21,总表!$C$2:$C$235,"找贴／凑断",总表!$S$2:$S$235,">0")=0,1E+99,_xlfn.MINIFS(总表!$S$2:$S$235,总表!$T$2:$T$235,$F21,总表!$E$2:$E$235,$G21,总表!$C$2:$C$235,"找贴／凑断",总表!$S$2:$S$235,">0")),IF(COUNTIFS(总表!$T$2:$T$235,$F21,总表!$E$2:$E$235,$G21,总表!$C$2:$C$235,"典＋找贴",总表!$S$2:$S$235,">0")=0,1E+99,_xlfn.MINIFS(总表!$S$2:$S$235,总表!$T$2:$T$235,$F21,总表!$E$2:$E$235,$G21,总表!$C$2:$C$235,"典＋找贴",总表!$S$2:$S$235,">0")))) -> 27 | K21: =IF(H21=0,"—",MAX(_xlfn.MAXIFS(总表!$S$2:$S$235,总表!$T$2:$T$235,$F21,总表!$E$2:$E$235,$G21,总表!$C$2:$C$235,"买卖（卖／卖断）",总表!$S$2:$S$235,">0"),_xlfn.MAXIFS(总表!$S$2:$S$235,总表!$T$2:$T$235,$F21,总表!$E$2:$E$235,$G21,总表!$C$2:$C$235,"典当／胎借",总表!$S$2:$S$235,">0"),_xlfn.MAXIFS(总表!$S$2:$S$235,总表!$T$2:$T$235,$F21,总表!$E$2:$E$235,$G21,总表!$C$2:$C$235,"找贴／凑断",总表!$S$2:$S$235,">0"),_xlfn.MAXIFS(总表!$S$2:$S$235,总表!$T$2:$T$235,$F21,总表!$E$2:$E$235,$G21,总表!$C$2:$C$235,"典＋找贴",总表!$S$2:$S$235,">0"))) -> 198
A22: 3 嘉道（1796-1850） | B22: =COUNTIF(总表!$E$2:$E$235,A22) -> 24 | C22: =IFERROR(B22/COUNTA(总表!$AI$2:$AI$235),0) -> 0.1025641 | F22: 番银 | G22: 6 南京国民政府（1928-1948） | H22: =SUMPRODUCT(COUNTIFS(总表!$T$2:$T$235,$F22,总表!$E$2:$E$235,$G22,总表!$C$2:$C$235,{"买卖（卖／卖断）","典当／胎借","找贴／凑断","典＋找贴"},总表!$S$2:$S$235,">0")) -> 1 | I22: =IFERROR(SUMPRODUCT(SUMIFS(总表!$S$2:$S$235,总表!$T$2:$T$235,$F22,总表!$E$2:$E$235,$G22,总表!$C$2:$C$235,{"买卖（卖／卖断）","典当／胎借","找贴／凑断","典＋找贴"},总表!$S$2:$S$235,">0"))/H22,"—") -> 40 | J22: =IF(H22=0,"—",MIN(IF(COUNTIFS(总表!$T$2:$T$235,$F22,总表!$E$2:$E$235,$G22,总表!$C$2:$C$235,"买卖（卖／卖断）",总表!$S$2:$S$235,">0")=0,1E+99,_xlfn.MINIFS(总表!$S$2:$S$235,总表!$T$2:$T$235,$F22,总表!$E$2:$E$235,$G22,总表!$C$2:$C$235,"买卖（卖／卖断）",总表!$S$2:$S$235,">0")),IF(COUNTIFS(总表!$T$2:$T$235,$F22,总表!$E$2:$E$235,$G22,总表!$C$2:$C$235,"典当／胎借",总表!$S$2:$S$235,">0")=0,1E+99,_xlfn.MINIFS(总表!$S$2:$S$235,总表!$T$2:$T$235,$F22,总表!$E$2:$E$235,$G22,总表!$C$2:$C$235,"典当／胎借",总表!$S$2:$S$235,">0")),IF(COUNTIFS(总表!$T$2:$T$235,$F22,总表!$E$2:$E$235,$G22,总表!$C$2:$C$235,"找贴／凑断",总表!$S$2:$S$235,">0")=0,1E+99,_xlfn.MINIFS(总表!$S$2:$S$235,总表!$T$2:$T$235,$F22,总表!$E$2:$E$235,$G22,总表!$C$2:$C$235,"找贴／凑断",总表!$S$2:$S$235,">0")),IF(COUNTIFS(总表!$T$2:$T$235,$F22,总表!$E$2:$E$235,$G22,总表!$C$2:$C$235,"典＋找贴",总表!$S$2:$S$235,">0")=0,1E+99,_xlfn.MINIFS(总表!$S$2:$S$235,总表!$T$2:$T$235,$F22,总表!$E$2:$E$235,$G22,总表!$C$2:$C$235,"典＋找贴",总表!$S$2:$S$235,">0")))) -> 40 | K22: =IF(H22=0,"—",MAX(_xlfn.MAXIFS(总表!$S$2:$S$235,总表!$T$2:$T$235,$F22,总表!$E$2:$E$235,$G22,总表!$C$2:$C$235,"买卖（卖／卖断）",总表!$S$2:$S$235,">0"),_xlfn.MAXIFS(总表!$S$2:$S$235,总表!$T$2:$T$235,$F22,总表!$E$2:$E$235,$G22,总表!$C$2:$C$235,"典当／胎借",总表!$S$2:$S$235,">0"),_xlfn.MAXIFS(总表!$S$2:$S$235,总表!$T$2:$T$235,$F22,总表!$E$2:$E$235,$G22,总表!$C$2:$C$235,"找贴／凑断",总表!$S$2:$S$235,">0"),_xlfn.MAXIFS(总表!$S$2:$S$235,总表!$T$2:$T$235,$F22,总表!$E$2:$E$235,$G22,总表!$C$2:$C$235,"典＋找贴",总表!$S$2:$S$235,">0"))) -> 40
A23: 4 咸同光宣（1851-1911） | B23: =COUNTIF(总表!$E$2:$E$235,A23) -> 68 | C23: =IFERROR(B23/COUNTA(总表!$AI$2:$AI$235),0) -> 0.29059829 | F23: 法币／国币 | G23: 6 南京国民政府（1928-1948） | H23: =SUMPRODUCT(COUNTIFS(总表!$T$2:$T$235,$F23,总表!$E$2:$E$235,$G23,总表!$C$2:$C$235,{"买卖（卖／卖断）","典当／胎借","找贴／凑断","典＋找贴"},总表!$S$2:$S$235,">0")) -> 9 | I23: =IFERROR(SUMPRODUCT(SUMIFS(总表!$S$2:$S$235,总表!$T$2:$T$235,$F23,总表!$E$2:$E$235,$G23,总表!$C$2:$C$235,{"买卖（卖／卖断）","典当／胎借","找贴／凑断","典＋找贴"},总表!$S$2:$S$235,">0"))/H23,"—") -> 112581.67 | J23: =IF(H23=0,"—",MIN(IF(COUNTIFS(总表!$T$2:$T$235,$F23,总表!$E$2:$E$235,$G23,总表!$C$2:$C$235,"买卖（卖／卖断）",总表!$S$2:$S$235,">0")=0,1E+99,_xlfn.MINIFS(总表!$S$2:$S$235,总表!$T$2:$T$235,$F23,总表!$E$2:$E$235,$G23,总表!$C$2:$C$235,"买卖（卖／卖断）",总表!$S$2:$S$235,">0")),IF(COUNTIFS(总表!$T$2:$T$235,$F23,总表!$E$2:$E$235,$G23,总表!$C$2:$C$235,"典当／胎借",总表!$S$2:$S$235,">0")=0,1E+99,_xlfn.MINIFS(总表!$S$2:$S$235,总表!$T$2:$T$235,$F23,总表!$E$2:$E$235,$G23,总表!$C$2:$C$235,"典当／胎借",总表!$S$2:$S$235,">0")),IF(COUNTIFS(总表!$T$2:$T$235,$F23,总表!$E$2:$E$235,$G23,总表!$C$2:$C$235,"找贴／凑断",总表!$S$2:$S$235,">0")=0,1E+99,_xlfn.MINIFS(总表!$S$2:$S$235,总表!$T$2:$T$235,$F23,总表!$E$2:$E$235,$G23,总表!$C$2:$C$235,"找贴／凑断",总表!$S$2:$S$235,">0")),IF(COUNTIFS(总表!$T$2:$T$235,$F23,总表!$E$2:$E$235,$G23,总表!$C$2:$C$235,"典＋找贴",总表!$S$2:$S$235,">0")=0,1E+99,_xlfn.MINIFS(总表!$S$2:$S$235,总表!$T$2:$T$235,$F23,总表!$E$2:$E$235,$G23,总表!$C$2:$C$235,"典＋找贴",总表!$S$2:$S$235,">0")))) -> 60 | K23: =IF(H23=0,"—",MAX(_xlfn.MAXIFS(总表!$S$2:$S$235,总表!$T$2:$T$235,$F23,总表!$E$2:$E$235,$G23,总表!$C$2:$C$235,"买卖（卖／卖断）",总表!$S$2:$S$235,">0"),_xlfn.MAXIFS(总表!$S$2:$S$235,总表!$T$2:$T$235,$F23,总表!$E$2:$E$235,$G23,总表!$C$2:$C$235,"典当／胎借",总表!$S$2:$S$235,">0"),_xlfn.MAXIFS(总表!$S$2:$S$235,总表!$T$2:$T$235,$F23,总表!$E$2:$E$235,$G23,总表!$C$2:$C$235,"找贴／凑断",总表!$S$2:$S$235,">0"),_xlfn.MAXIFS(总表!$S$2:$S$235,总表!$T$2:$T$235,$F23,总表!$E$2:$E$235,$G23,总表!$C$2:$C$235,"典＋找贴",总表!$S$2:$S$235,">0"))) -> 1000000
A24: 5 北洋（1912-1927） | B24: =COUNTIF(总表!$E$2:$E$235,A24) -> 41 | C24: =IFERROR(B24/COUNTA(总表!$AI$2:$AI$235),0) -> 0.17521368 | F24: 人民币 | G24: 7 1949 以后 | H24: =SUMPRODUCT(COUNTIFS(总表!$T$2:$T$235,$F24,总表!$E$2:$E$235,$G24,总表!$C$2:$C$235,{"买卖（卖／卖断）","典当／胎借","找贴／凑断","典＋找贴"},总表!$S$2:$S$235,">0")) -> 6 | I24: =IFERROR(SUMPRODUCT(SUMIFS(总表!$S$2:$S$235,总表!$T$2:$T$235,$F24,总表!$E$2:$E$235,$G24,总表!$C$2:$C$235,{"买卖（卖／卖断）","典当／胎借","找贴／凑断","典＋找贴"},总表!$S$2:$S$235,">0"))/H24,"—") -> 680000 | J24: =IF(H24=0,"—",MIN(IF(COUNTIFS(总表!$T$2:$T$235,$F24,总表!$E$2:$E$235,$G24,总表!$C$2:$C$235,"买卖（卖／卖断）",总表!$S$2:$S$235,">0")=0,1E+99,_xlfn.MINIFS(总表!$S$2:$S$235,总表!$T$2:$T$235,$F24,总表!$E$2:$E$235,$G24,总表!$C$2:$C$235,"买卖（卖／卖断）",总表!$S$2:$S$235,">0")),IF(COUNTIFS(总表!$T$2:$T$235,$F24,总表!$E$2:$E$235,$G24,总表!$C$2:$C$235,"典当／胎借",总表!$S$2:$S$235,">0")=0,1E+99,_xlfn.MINIFS(总表!$S$2:$S$235,总表!$T$2:$T$235,$F24,总表!$E$2:$E$235,$G24,总表!$C$2:$C$235,"典当／胎借",总表!$S$2:$S$235,">0")),IF(COUNTIFS(总表!$T$2:$T$235,$F24,总表!$E$2:$E$235,$G24,总表!$C$2:$C$235,"找贴／凑断",总表!$S$2:$S$235,">0")=0,1E+99,_xlfn.MINIFS(总表!$S$2:$S$235,总表!$T$2:$T$235,$F24,总表!$E$2:$E$235,$G24,总表!$C$2:$C$235,"找贴／凑断",总表!$S$2:$S$235,">0")),IF(COUNTIFS(总表!$T$2:$T$235,$F24,总表!$E$2:$E$235,$G24,总表!$C$2:$C$235,"典＋找贴",总表!$S$2:$S$235,">0")=0,1E+99,_xlfn.MINIFS(总表!$S$2:$S$235,总表!$T$2:$T$235,$F24,总表!$E$2:$E$235,$G24,总表!$C$2:$C$235,"典＋找贴",总表!$S$2:$S$235,">0")))) -> 230000 | K24: =IF(H24=0,"—",MAX(_xlfn.MAXIFS(总表!$S$2:$S$235,总表!$T$2:$T$235,$F24,总表!$E$2:$E$235,$G24,总表!$C$2:$C$235,"买卖（卖／卖断）",总表!$S$2:$S$235,">0"),_xlfn.MAXIFS(总表!$S$2:$S$235,总表!$T$2:$T$235,$F24,总表!$E$2:$E$235,$G24,总表!$C$2:$C$235,"典当／胎借",总表!$S$2:$S$235,">0"),_xlfn.MAXIFS(总表!$S$2:$S$235,总表!$T$2:$T$235,$F24,总表!$E$2:$E$235,$G24,总表!$C$2:$C$235,"找贴／凑断",总表!$S$2:$S$235,">0"),_xlfn.MAXIFS(总表!$S$2:$S$235,总表!$T$2:$T$235,$F24,总表!$E$2:$E$235,$G24,总表!$C$2:$C$235,"典＋找贴",总表!$S$2:$S$235,">0"))) -> 1600000
A25: 6 南京国民政府（1928-1948） | B25: =COUNTIF(总表!$E$2:$E$235,A25) -> 64 | C25: =IFERROR(B25/COUNTA(总表!$AI$2:$AI$235),0) -> 0.27350427
A26: 7 1949 以后 | B26: =COUNTIF(总表!$E$2:$E$235,A26) -> 23 | C26: =IFERROR(B26/COUNTA(总表!$AI$2:$AI$235),0) -> 0.098290598
A27: 无年代 | B27: =COUNTIF(总表!$E$2:$E$235,A27) -> 4 | C27: =IFERROR(B27/COUNTA(总表!$AI$2:$AI$235),0) -> 0.017094017
A28: 合计 | B28: =SUM(B20:B27) -> 234 | C28: =SUM(C20:C27) -> 1
A30: 三、立契人性别
A31: 类别 | B31: 件数 | C31: 占比
A32: 男 | B32: =COUNTIF(总表!$J$2:$J$235,A32) -> 160 | C32: =IFERROR(B32/COUNTA(总表!$AI$2:$AI$235),0) -> 0.68376068
A33: 官方 | B33: =COUNTIF(总表!$J$2:$J$235,A33) -> 43 | C33: =IFERROR(B33/COUNTA(总表!$AI$2:$AI$235),0) -> 0.18376068
A34: 不详 | B34: =COUNTIF(总表!$J$2:$J$235,A34) -> 10 | C34: =IFERROR(B34/COUNTA(总表!$AI$2:$AI$235),0) -> 0.042735043
A35: 男女合立 | B35: =COUNTIF(总表!$J$2:$J$235,A35) -> 8 | C35: =IFERROR(B35/COUNTA(总表!$AI$2:$AI$235),0) -> 0.034188034
A36: 团体 | B36: =COUNTIF(总表!$J$2:$J$235,A36) -> 6 | C36: =IFERROR(B36/COUNTA(总表!$AI$2:$AI$235),0) -> 0.025641026
A37: 女 | B37: =COUNTIF(总表!$J$2:$J$235,A37) -> 6 | C37: =IFERROR(B37/COUNTA(总表!$AI$2:$AI$235),0) -> 0.025641026
A38: 僧道 | B38: =COUNTIF(总表!$J$2:$J$235,A38) -> 1 | C38: =IFERROR(B38/COUNTA(总表!$AI$2:$AI$235),0) -> 0.0042735043
A39: 合计 | B39: =SUM(B32:B38) -> 234 | C39: =SUM(C32:C38) -> 1
A41: 四、县（按图像辨读）
A42: 类别 | B42: 件数 | C42: 占比
A43: 不详 | B43: =COUNTIF(总表!$M$2:$M$235,A43) -> 44 | C43: =IFERROR(B43/COUNTA(总表!$AI$2:$AI$235),0) -> 0.18803419
A44: 闽侯县 | B44: =COUNTIF(总表!$M$2:$M$235,A44) -> 29 | C44: =IFERROR(B44/COUNTA(总表!$AI$2:$AI$235),0) -> 0.12393162
A45: 侯官县 | B45: =COUNTIF(总表!$M$2:$M$235,A45) -> 25 | C45: =IFERROR(B45/COUNTA(总表!$AI$2:$AI$235),0) -> 0.10683761
A46: 闽县 | B46: =COUNTIF(总表!$M$2:$M$235,A46) -> 24 | C46: =IFERROR(B46/COUNTA(总表!$AI$2:$AI$235),0) -> 0.1025641
A47: 永泰县 | B47: =COUNTIF(总表!$M$2:$M$235,A47) -> 18 | C47: =IFERROR(B47/COUNTA(总表!$AI$2:$AI$235),0) -> 0.076923077
A48: 林森县 | B48: =COUNTIF(总表!$M$2:$M$235,A48) -> 18 | C48: =IFERROR(B48/COUNTA(总表!$AI$2:$AI$235),0) -> 0.076923077
A49: 古田县 | B49: =COUNTIF(总表!$M$2:$M$235,A49) -> 17 | C49: =IFERROR(B49/COUNTA(总表!$AI$2:$AI$235),0) -> 0.072649573
A50: 闽清县 | B50: =COUNTIF(总表!$M$2:$M$235,A50) -> 12 | C50: =IFERROR(B50/COUNTA(总表!$AI$2:$AI$235),0) -> 0.051282051
A51: 晋江县 | B51: =COUNTIF(总表!$M$2:$M$235,A51) -> 8 | C51: =IFERROR(B51/COUNTA(总表!$AI$2:$AI$235),0) -> 0.034188034
A52: 东山县 | B52: =COUNTIF(总表!$M$2:$M$235,A52) -> 8 | C52: =IFERROR(B52/COUNTA(总表!$AI$2:$AI$235),0) -> 0.034188034
A53: 建阳县 | B53: =COUNTIF(总表!$M$2:$M$235,A53) -> 8 | C53: =IFERROR(B53/COUNTA(总表!$AI$2:$AI$235),0) -> 0.034188034
A54: 屏南县 | B54: =COUNTIF(总表!$M$2:$M$235,A54) -> 3 | C54: =IFERROR(B54/COUNTA(总表!$AI$2:$AI$235),0) -> 0.012820513
... A70: 歙县 | B70: =COUNTIF(总表!$M$2:$M$235,A70) -> 1 | C70: =IFERROR(B70/COUNTA(总表!$AI$2:$AI$235),0) -> 0.0042735043
A71: 合计 | B71: =SUM(B43:B70) -> 234 | C71: =SUM(C43:C70) -> 1
A73: 五、交易物大类
A74: 类别 | B74: 件数 | C74: 占比
A75: 田 | B75: =COUNTIF(总表!$O$2:$O$235,A75) -> 104 | C75: =IFERROR(B75/COUNTA(总表!$AI$2:$AI$235),0) -> 0.44444444
A76: 屋／厝 | B76: =COUNTIF(总表!$O$2:$O$235,A76) -> 54 | C76: =IFERROR(B76/COUNTA(总表!$AI$2:$AI$235),0) -> 0.23076923
A77: 田根 | B77: =COUNTIF(总表!$O$2:$O$235,A77) -> 15 | C77: =IFERROR(B77/COUNTA(总表!$AI$2:$AI$235),0) -> 0.064102564
A78: 田面 | B78: =COUNTIF(总表!$O$2:$O$235,A78) -> 11 | C78: =IFERROR(B78/COUNTA(总表!$AI$2:$AI$235),0) -> 0.047008547
A79: 其他／非土地 | B79: =COUNTIF(总表!$O$2:$O$235,A79) -> 10 | C79: =IFERROR(B79/COUNTA(总表!$AI$2:$AI$235),0) -> 0.042735043
A80: 田（根面全） | B80: =COUNTIF(总表!$O$2:$O$235,A80) -> 10 | C80: =IFERROR(B80/COUNTA(总表!$AI$2:$AI$235),0) -> 0.042735043
A81: 山林 | B81: =COUNTIF(总表!$O$2:$O$235,A81) -> 10 | C81: =IFERROR(B81/COUNTA(总表!$AI$2:$AI$235),0) -> 0.042735043
A82: 店屋 | B82: =COUNTIF(总表!$O$2:$O$235,A82) -> 9 | C82: =IFERROR(B82/COUNTA(总表!$AI$2:$AI$235),0) -> 0.038461538
A83: 园 | B83: =COUNTIF(总表!$O$2:$O$235,A83) -> 6 | C83: =IFERROR(B83/COUNTA(总表!$AI$2:$AI$235),0) -> 0.025641026
A84: 其他 | B84: =COUNTIF(总表!$O$2:$O$235,A84) -> 2 | C84: =IFERROR(B84/COUNTA(总表!$AI$2:$AI$235),0) -> 0.0085470085
A85: 坟地 | B85: =COUNTIF(总表!$O$2:$O$235,A85) -> 2 | C85: =IFERROR(B85/COUNTA(总表!$AI$2:$AI$235),0) -> 0.0085470085
A86: 地基 | B86: =COUNTIF(总表!$O$2:$O$235,A86) -> 1 | C86: =IFERROR(B86/COUNTA(总表!$AI$2:$AI$235),0) -> 0.0042735043
A87: 合计 | B87: =SUM(B75:B86) -> 234 | C87: =SUM(C75:C86) -> 1
A89: 六、年号
A90: 类别 | B90: 件数 | C90: 占比
A91: 民国 | B91: =COUNTIF(总表!$F$2:$F$235,A91) -> 110 | C91: =IFERROR(B91/COUNTA(总表!$AI$2:$AI$235),0) -> 0.47008547
A92: 光绪 | B92: =COUNTIF(总表!$F$2:$F$235,A92) -> 40 | C92: =IFERROR(B92/COUNTA(总表!$AI$2:$AI$235),0) -> 0.17094017
A93: 同治 | B93: =COUNTIF(总表!$F$2:$F$235,A93) -> 20 | C93: =IFERROR(B93/COUNTA(总表!$AI$2:$AI$235),0) -> 0.085470085
A94: 公元 | B94: =COUNTIF(总表!$F$2:$F$235,A94) -> 17 | C94: =IFERROR(B94/COUNTA(总表!$AI$2:$AI$235),0) -> 0.072649573
A95: 道光 | B95: =COUNTIF(总表!$F$2:$F$235,A95) -> 16 | C95: =IFERROR(B95/COUNTA(总表!$AI$2:$AI$235),0) -> 0.068376068
A96: 嘉庆 | B96: =COUNTIF(总表!$F$2:$F$235,A96) -> 10 | C96: =IFERROR(B96/COUNTA(总表!$AI$2:$AI$235),0) -> 0.042735043
A97: 乾隆 | B97: =COUNTIF(总表!$F$2:$F$235,A97) -> 7 | C97: =IFERROR(B97/COUNTA(总表!$AI$2:$AI$235),0) -> 0.02991453
A98: 宣统 | B98: =COUNTIF(总表!$F$2:$F$235,A98) -> 6 | C98: =IFERROR(B98/COUNTA(总表!$AI$2:$AI$235),0) -> 0.025641026
A99: 咸丰 | B99: =COUNTIF(总表!$F$2:$F$235,A99) -> 2 | C99: =IFERROR(B99/COUNTA(总表!$AI$2:$AI$235),0) -> 0.0085470085
A100: 中华人民共和国 | B100: =COUNTIF(总表!$F$2:$F$235,A100) -> 1 | C100: =IFERROR(B100/COUNTA(总表!$AI$2:$AI$235),0) -> 0.0042735043
A101: 民国（东北解放区） | B101: =COUNTIF(总表!$F$2:$F$235,A101) -> 1 | C101: =IFERROR(B101/COUNTA(总表!$AI$2:$AI$235),0) -> 0.0042735043
A102: 顺治 | B102: =COUNTIF(总表!$F$2:$F$235,A102) -> 1 | C102: =IFERROR(B102/COUNTA(总表!$AI$2:$AI$235),0) -> 0.0042735043
... A104: 万历 | B104: =COUNTIF(总表!$F$2:$F$235,A104) -> 1 | C104: =IFERROR(B104/COUNTA(总表!$AI$2:$AI$235),0) -> 0.0042735043
A105: 合计 | B105: =SUM(B91:B104) -> 233 | C105: =SUM(C91:C104) -> 0.9957265
A107: 七、辨读置信度
A108: 类别 | B108: 件数 | C108: 占比
A109: 高 | B109: =COUNTIF(总表!$AC$2:$AC$235,A109) -> 62 | C109: =IFERROR(B109/COUNTA(总表!$AI$2:$AI$235),0) -> 0.26495726
A110: 中 | B110: =COUNTIF(总表!$AC$2:$AC$235,A110) -> 160 | C110: =IFERROR(B110/COUNTA(总表!$AI$2:$AI$235),0) -> 0.68376068
A111: 低 | B111: =COUNTIF(总表!$AC$2:$AC$235,A111) -> 12 | C111: =IFERROR(B111/COUNTA(总表!$AI$2:$AI$235),0) -> 0.051282051
A112: 合计 | B112: =SUM(B109:B111) -> 234 | C112: =SUM(C109:C111) -> 1

Sheet 人物索引
A1: 姓名 | B1: 出现件数 | C1: 作中人次数 | D1: 作代笔次数 | E1: 年代范围 | F1: 县 | G1: 涉及件（箱/夹）
A2: 陈菊花 | B2: 5 | C2: 5 | D2: 0 | E2: 1932–1936 | F2: 不详、福清县 | G2: 3/159；3/157；3/147；3/158；3/156
A3: 吴红经 | B3: 4 | C3: 4 | D3: 0 | E3: 1936–1936 | F3: 不详 | G3: 3/159；3/157；3/158；3/156
A4: 陈端辛 | B4: 3 | C4: 3 | D4: 2 | E4: 1909–1917 | F4: 不详、连江县 | G4: 2/105；2/102；2/90
A5: 施性楼 | B5: 3 | C5: 3 | D5: 0 | E5: 1953–1953 | F5: 晋江县 | G5: 4/203；4/208；4/205
A6: 陈九龄 | B6: 2 | C6: 0 | D6: 2 | E6: 1917–1918 | F6: 闽侯县 | G6: 2/106；2/108A
A7: 陈钦隆 | B7: 2 | C7: 0 | D7: 2 | E7: 1936–1936 | F7: 不详 | G7: 3/159；3/158
A8: 陈仁山 | B8: 2 | C8: 0 | D8: 2 | E8: 1936–1936 | F8: 不详 | G8: 3/157；3/156
A9: 陈友梅 | B9: 2 | C9: 2 | D9: 0 | E9: 1866–1869 | F9: 闽县 | G9: 1/41；1/48
A10: 方忠恭 | B10: 2 | C10: 0 | D10: 2 | E10: 1887–1888 | F10: 闽县 | G10: 2/64；2/69
A11: 高依赐 | B11: 2 | C11: 2 | D11: 0 | E11: 1906–1906 | F11: 闽县 | G11: 2/88；2/88B
A12: 黄隆贯 | B12: 2 | C12: 0 | D12: 2 | E12: 1805–1829 | F12: 不详 | G12: 1/23；1/15
A13: 蒋则荣 | B13: 2 | C13: 0 | D13: 2 | E13: 1844–1854 | F13: 侯官县 | G13: 1/31；1/34
... A28: 吴维清 | B28: 2 | C28: 2 | D28: 0 | E28: 1918–1918 | F28: 闽侯县 | G28: 2/108；2/108A
A29: 邦如孙 | C29: 0 | D29: 1 | E29: 1870–1870 | F29: 不详 | G29: 18660
A30: 胞孙张大都 | C30: 1 | D30: 0 | E30: 1870–1870 | F30: 屏南县 | G30: 17899
A31: 蔡书波 | C31: 1 | D31: 0 | E31: 1862–1862 | F31: 侯官县 | G31: 13516
A32: 蔡廷有 | C32: 1 | D32: 0 | E32: 1863–1863 | F32: 不详 | G32: 13881
A33: 曾瑞图 | C33: 0 | D33: 1 | E33: 1934–1934 | F33: 闽侯县 | G33: 3/151
A34: 曾笋 | C34: 0 | D34: 1 | E34: 1947–1947 | F34: 东山县 | G34: 4/188
A35: 曾侄孙圣乾 | C35: 1 | D35: 1 | E35: 1945–1945 | F35: 不详 | G35: 3/169
A36: 陈炳星 | C36: 0 | D36: 1 | E36: 1935–1935 | F36: 古田县 | G36: 3/153
A37: 陈春雷 | C37: 1 | D37: 0 | E37: 1876–1876 | F37: 侯官县 | G37: 19756
A38: 陈红鳀 | C38: 1 | D38: 0 | E38: 1941–1941 | F38: 不详 | G38: 3/163
A39: 陈华 | C39: 0 | D39: 1 | E39: 1882–1882 | F39: 侯官县 | G39: 20852
A40: 陈金槐 | C40: 1 | D40: 0 | E40: 1884–1884 | F40: 侯官县 | G40: 21582
A41: 陈经森 | C41: 0 | D41: 1 | E41: 1904–1904 | F41: 闽县 | G41: 31444
A42: 陈开文 | C42: 1 | D42: 0 | E42: 1858–1858 | F42: 侯官县 | G42: 12785
A43: 陈明金 | C43: 0 | D43: 1 | E43: 1837–1837 | F43: 不详 | G43: 46046
A44: 陈仁芳 | C44: 0 | D44: 1 | E44: 1932–1932 | F44: 福清县 | G44: 3/147
A45: 陈文明 | C45: 1 | D45: 0 | E45: 1927–1927 | F45: 闽侯县 | G45: 3/140C
A46: 陈五费 | C46: 0 | D46: 1 | E46: 1678–1678 | F46: 闽清县 | G46: 46025
A47: 陈务睦 | C47: 1 | D47: 0 | E47: 1822–1822 | F47: 闽县 | G47: 46042
A48: 陈扬英 | C48: 0 | D48: 1 | E48: 1940–1940 | F48: 不详 | G48: 3/162
A49: 陈奕谋 | C49: 0 | D49: 1 | E49: 1921–1921 | F49: 晋江县 | G49: 3/116
A50: 陈有义 | C50: 0 | D50: 1 | E50: 1906–1906 | F50: 闽县 | G50: 2/88A
A51: 陈赠寿 | C51: 1 | D51: 0 | E51: 1935–1935 | F51: 古田县 | G51: 3/153
A52: 陈兆长 | C52: 1 | D52: 0 | E52: 1918–1918 | F52: 永泰县 | G52: 3/131A
A53: 陈竹付 | C53: 0 | D53: 1 | E53: 1935–1935 | F53: 闽清县 | G53: 3/155A
A54: 程本容 | C54: 1 | D54: 0 | E54: 1903–1903 | F54: 不详 | G54: 30713
A55: 程道法 | C55: 1 | D55: 0 | E55: 1929–1929 | F55: 闽侯县 | G55: 3/140A
A56: 程叔顺 | C56: 1 | D56: 0 | E56: 1782–1782 | F56: 不详 | G56: 46032
A57: 程章 | C57: 1 | D57: 1 | E57: 1903–1903 | F57: 永泰县 | G57: 31079
A58: 的笔 | C58: 0 | D58: 1 | E58: 1869–1869 | F58: 不详 | G58: 16438
A59: 弟陈桂能 | C59: 1 | D59: 1 | E59: 1929–1929 | F59: 闽侯县 | G59: 3/140B
A60: 弟荣 | C60: 0 | D60: 1 | E60: 1841–1841 | F60: 不详 | G60: 46051
A61: 弟有汉 | C61: 1 | D61: 0 | E61: 1802–1802 | F61: 闽清县 | G61: 46034
A62: 端辛 | C62: 1 | D62: 0 | E62: 1910–1910 | F62: 不详 | G62: 33270
A63: 法功江 | C63: 1 | D63: 0 | E63: 1864–1864 | F63: 古田县 | G63: 14246
A64: 方赓田 | C64: 1 | D64: 0 | E64: 1910–1910 | F64: 侯官县 | G64: 34001
A65: 方添喜 | C65: 1 | D65: 0 | E65: 1953–1953 | F65: 东山县 | G65: 4/204
A66: 方兆扬 | C66: 0 | D66: 1 | E66: 1910–1910 | F66: 侯官县 | G66: 2/93A
A67: 房叔陈宿赠 | C67: 0 | D67: 1 | E67: 1932–1932 | F67: 闽侯县 | G67: 3/147A
A68: 甘兴业 | C68: 0 | D68: 1 | E68: 1872–1872 | F68: 古田县 | G68: 19025
A69: 官盛清 | C69: 1 | D69: 0 | E69: 1761–1761 | F69: 永定县 | G69: 46027
A70: 海中 | C70: 0 | D70: 1 | E70: 1877–1877 | F70: 永安县 | G70: 20121
A71: 何章林 | C71: 1 | D71: 0 | E71: 1899–1899 | F71: 不详 | G71: 29618
A72: 胡振仁 | C72: 1 | D72: 0 | E72: 1888–1888 | F72: 古田县 | G72: 24139
A73: 黄继书 | C73: 0 | D73: 1 | E73: 1842–1842 | F73: 不详 | G73: 46052
A74: 黄家仙 | C74: 1 | D74: 0 | E74: 1926–1926 | F74: 不详 | G74: 3/126
A75: 黄杰 | C75: 0 | D75: 1 | E75: 1886–1886 | F75: 闽县 | G75: 22678
A76: 黄明德 | C76: 0 | D76: 1 | E76: 1952–1952 | F76: 东山县 | G76: 4/198
A77: 黄庆麟 | C77: 1 | D77: 0 | E77: 1934–1934 | F77: 永泰县 | G77: 3/161
A78: 黄振章 | C78: 1 | D78: 0 | E78: 1904–1904 | F78: 闽县 | G78: 31444
A79: 揭时发 | C79: 0 | D79: 1 | E79: 1659–1659 | F79: 不详 | G79: 46024
A80: 金存国 | C80: 1 | D80: 0 | E80: 1805–1805 | F80: 闽县 | G80: 46038
A81: 金石友 | C81: 0 | D81: 1 | E81: 1929–1929 | F81: 永泰县 | G81: 3/125
A82: 经管 | C82: 0 | D82: 1 | E82: 1933–1933 | F82: 古田县 | G82: 3/149
A83: 经管陈诚 | C83: 0 | D83: 1 | E83: 1933–1933 | F83: 古田县 | G83: 3/148
A84: 开次 | C84: 0 | D84: 1 | E84: 1910–1910 | F84: 不详 | G84: 33270
A85: 赖文仔 | C85: 1 | D85: 0 | E85: 1890–1890 | F85: 不详 | G85: 26330
A86: 李逢铨 | C86: 0 | D86: 1 | E86: 1887–1887 | F86: 闽县 | G86: 23043
A87: 李珪甫 | C87: 0 | D87: 1 | E87: 1889–1889 | F87: 闽县 | G87: 25600
A88: 李华茂 | C88: 1 | D88: 0 | E88: 1915–1915 | F88: 闽侯县 | G88: 2/101
A89: 李怀镜 | C89: 1 | D89: 0 | E89: 1870–1870 | F89: 闽县 | G89: 25965
A90: 李龙泉 | C90: 0 | D90: 1 | E90: 1840–1840 | F90: 不详 | G90: 46048
A91: 李钰成 | C91: 0 | D91: 1 | E91: 1889–1889 | F91: 闽县 | G91: 2/70A
A92: 李兆桐 | C92: 1 | D92: 0 | E92: 1862–1862 | F92: 侯官县 | G92: 13516
A93: 李肇松 | C93: 0 | D93: 1 | E93: 1862–1862 | F93: 侯官县 | G93: 13516
A94: 李祖谦 | C94: 0 | D94: 1 | E94: 1869–1869 | F94: 闽县 | G94: 17533
A95: 林标人 | C95: 0 | D95: 1 | E95: 1805–1805 | F95: 侯官县 | G95: 46036
A96: 林发祥 | C96: 1 | D96: 0 | E96: 1929–1929 | F96: 永泰县 | G96: 3/125
A97: 林和 | C97: 1 | D97: 0 | E97: 1952–1952 | F97: 东山县 | G97: 4/198
A98: 林吉昌 | C98: 0 | D98: 1 | E98: 1934–1934 | F98: 闽侯县 | G98: 3/150
A99: 林金锡 | C99: 1 | D99: 0 | E99: 1949–1949 | F99: 东山县 | G99: 4/199
A100: 林可辉 | C100: 0 | D100: 1 | E100: 1889–1889 | F100: 闽县 | G100: 2/70B
A101: 林坛 | C101: 1 | D101: 0 | E101: 1935–1935 | F101: 晋江县 | G101: 3/155
A102: 林天送 | C102: 1 | D102: 0 | E102: 1886–1886 | F102: 闽县 | G102: 22678
A103: 林万斌 | C103: 1 | D103: 0 | E103: 1865–1865 | F103: 侯官县 | G103: 14611
A104: 林万开 | C104: 1 | D104: 0 | E104: 1866–1866 | F104: 侯官县 | G104: 15342
A105: 林万利自笔 | C105: 0 | D105: 1 | E105: 1884–1884 | F105: 侯官县 | G105: 21582
A106: 林细弟 | C106: 1 | D106: 0 | E106: 1887–1887 | F106: 闽县 | G106: 23043
A107: 林兴清自笔 | C107: 0 | D107: 1 | E107: 1903–1903 | F107: 不详 | G107: 30713
A108: 林学纶 | C108: 0 | D108: 1 | E108: 1805–1805 | F108: 闽县 | G108: 46038
A109: 林有泰 | C109: 1 | D109: 0 | E109: 1934–1934 | F109: 闽侯县 | G109: 3/150
A110: 林玉明 | C110: 1 | D110: 0 | E110: 1906–1906 | F110: 闽县 | G110: 2/88A
A111: 林枝三 | C111: 0 | D111: 1 | E111: 1870–1870 | F111: 闽县 | G111: 25965
A112: 林宗年 | C112: 1 | D112: 0 | E112: 1934–1934 | F112: 闽侯县 | G112: 3/150
A113: 刘贵年 | C113: 1 | D113: 0 | E113: 1863–1863 | F113: 不详 | G113: 13881
A114: 刘礼 | C114: 1 | D114: 0 | E114: 1782–1782 | F114: 建阳县 | G114: 46031
...
